Workbook

Sheet Energy Schedule
C1: 44896 | F1: =C1+1 -> 44897 | I1: =F1+1 -> 44898 | L1: =I1+1 -> 44899 | O1: =L1+1 -> 44900 | R1: =O1+1 -> 44901 | U1: =R1+1 -> 44902 | X1: =U1+1 -> 44903 | AA1: =X1+1 -> 44904 | AD1: =AA1+1 -> 44905 | AG1: =AD1+1 -> 44906 | AJ1: =AG1+1 -> 44907 | AM1: =AJ1+1 -> 44908 | AP1: =AM1+1 -> 44909 | AS1: =AP1+1 -> 44910 | AV1: =AS1+1 -> 44911 | AY1: =AV1+1 -> 44912 | BB1: =AY1+1 -> 44913 | BE1: =BB1+1 -> 44914 | BH1: =BE1+1 -> 44915 | BK1: =BH1+1 -> 44916 | BN1: =BK1+1 -> 44917 | BQ1: =BN1+1 -> 44918 | BT1: =BQ1+1 -> 44919 | BW1: =BT1+1 -> 44920 | BZ1: =BW1+1 -> 44921 | CC1: =BZ1+1 -> 44922 | CF1: =CC1+1 -> 44923 | CI1: =CF1+1 -> 44924 | CL1: =CI1+1 -> 44925 | CO1: =CL1+1 -> 44926
C2: GDAM | D2: DAM | E2: RTM | F2: GDAM | G2: DAM | H2: RTM | I2: GDAM | J2: DAM | K2: RTM | L2: GDAM | M2: DAM | N2: RTM | O2: GDAM | P2: DAM | Q2: RTM | R2: GDAM | S2: DAM | T2: RTM | U2: GDAM | V2: DAM | W2: RTM | X2: GDAM | Y2: DAM | Z2: RTM | AA2: GDAM | AB2: DAM | AC2: RTM | AD2: GDAM | AE2: DAM | AF2: RTM | AG2: GDAM | AH2: DAM | AI2: RTM | AJ2: GDAM | AK2: DAM | AL2: RTM | AM2: GDAM | AN2: DAM | AO2: RTM | AP2: GDAM | AQ2: DAM | AR2: RTM | AS2: GDAM | AT2: DAM | AU2: RTM | AV2: GDAM | AW2: DAM | AX2: RTM | AY2: GDAM | AZ2: DAM | BA2: RTM | BB2: GDAM | BC2: DAM | BD2: RTM | BE2: GDAM | BF2: DAM | BG2: RTM | BH2: GDAM | BI2: DAM | BJ2: RTM | BK2: GDAM | BL2: DAM | BM2: RTM | BN2: GDAM | BO2: DAM | BP2: RTM | BQ2: GDAM | BR2: DAM | BS2: RTM | BT2: GDAM | BU2: DAM | BV2: RTM | BW2: GDAM | BX2: DAM | BY2: RTM | BZ2: GDAM | CA2: DAM | CB2: RTM | CC2: GDAM | CD2: DAM | CE2: RTM | CF2: GDAM | CG2: DAM | CH2: RTM | CI2: GDAM | CJ2: DAM | CK2: RTM | CL2: GDAM | CM2: DAM | CN2: RTM | CO2: GDAM | CP2: DAM | CQ2: RTM
A3: CTU Losses | D3: 0.0343 | G3: 0.0343 | J3: 0.0343 | M3: 0.0343 | P3: 0.0361 | R3: 0.0361 | S3: 0.0361 | V3: 0.0361 | W3: 0.0361 | Y3: 0.0361 | Z3: 0.0361 | AB3: 0.0361 | AE3: 0.0361 | AH3: 0.0361 | AK3: 0.0382 | AN3: 0.0382 | AQ3: 0.0382 | AT3: 0.0382 | AW3: 0.0382 | AZ3: 0.0382 | BC3: 0.0382 | BF3: 0.0418 | BI3: 0.0418 | BL3: 0.0418 | BO3: 0.0418 | BR3: 0.0418 | BU3: 0.0418 | BX3: 0.0418 | CA3: 0.0419 | CD3: 0.0419 | CG3: 0.0419 | CJ3: 0.0419 | CM3: 0.0419
A4: CTU Charges | D4: 457.6 | G4: 457.6 | J4: 457.6 | M4: 457.6 | P4: 457.6 | S4: 457.6 | V4: 457.6 | Y4: 457.6 | AB4: 457.6 | AE4: 457.6 | AH4: 457.6 | AK4: 457.6 | AN4: 457.6 | AQ4: 457.6 | AT4: 457.6 | AW4: 457.6 | BO4: 457.6 | BR4: 457.6 | BU4: 457.6 | BX4: 457.6 | CA4: 457.6 | CD4: 484.8 | CG4: 484.8 | CJ4: 484.8 | CM4: 484.8
A5: Cost | D5: 45070.355 | E5: 3103.11 | G5: 46896.22 | J5: 38325.914 | K5: 14307.76 | M5: 83092.96 | N5: 12749.83 | P5: 39837.968 | Q5: 16147.49 | S5: 54907.277 | T5: 13002.64 | V5: 33736.898 | W5: 22760.98 | Y5: 51549.744 | Z5: 32714.22 | AB5: 55906.487 | AC5: 28235.38 | AE5: 70274.661 | AH5: 98538.321 | AI5: 27909.59 | AK5: 63830.988 | AL5: 24341.29 | AN5: 64149.079 | AO5: 8811.53 | AQ5: 43154.523 | AR5: 24088.83 | AT5: 49631.555 | AU5: 12125.1 | AW5: 28682.671 | AX5: 4361.8 | AZ5: 29034.378 | BA5: 11232.94 | BC5: 44876.773 | BD5: 36010.11 | BF5: 23821.927 | BG5: 18669.45 | BI5: 24262.558 | BJ5: 8641.65 | BL5: 27772.575 | BM5: 35135.35 | BO5: 28861.726 | BP5: 19716.8 | BR5: 26822.584 | BS5: 15252.89 | BU5: 49873.604 | BV5: 8203.36 | BX5: 48944.949 | CA5: 23502.102 | CD5: 26051.972 | CG5: 31764.668 | CJ5: 21325.134 | CM5: 30980.829
A6: NLDC App Fee | D6: 9.09 | E6: 13.7 | G6: 8.91 | J6: 8.99 | K6: 13.19 | M6: 7.67 | N6: 14.29 | P6: 8.18 | Q6: 13.55 | S6: 8.35 | T6: 12.53 | V6: 8.61 | W6: 12.89 | Y6: 8.61 | Z6: 12.53 | AB6: 8.28 | AC6: 12.32 | AE6: 7.91 | AH6: 7.36 | AI6: 12.92 | AK6: 7.44 | AL6: 11.74 | AN6: 7.69 | AO6: 12.56 | AQ6: 7.62 | AR6: 12.92 | AT6: 8.04 | AU6: 15.43 | AW6: 8.59 | AX6: 24.39 | AZ6: 8.5 | BA6: 18.66 | BC6: 8.42 | BD6: 14.16 | BF6: 8.25 | BG6: 13.66 | BI6: 8.22 | BJ6: 12.92 | BL6: 7.74 | BM6: 13.16 | BO6: 8.13 | BP6: 12.53 | BR6: 7.69 | BS6: 11.79 | BU6: 7.42 | BV6: 13.02 | BX6: 7.22 | CA6: 7.65 | CD6: 7.41 | CG6: 7.36 | CJ6: 7.58 | CM6: 8.16
A7: 00:00 - 00:15 | B7: C5 | D7: 1 | E7: 0 | G7: 1 | J7: 0 | K7: 0 | M7: 0.5 | N7: 0 | P7: 0.5 | Q7: 0 | S7: 0.5 | T7: 0 | V7: 0.5 | W7: 0 | Y7: 0.5 | Z7: 0 | AB7: 0.5 | AC7: 0 | AE7: 0.5 | AH7: 0.5 | AI7: 0 | AK7: 0.5 | AL7: 0 | AN7: 0.5 | AO7: 0 | AQ7: 0.3 | AR7: 0.3 | AT7: 0.3 | AU7: 0 | AW7: 0.3 | AX7: 0 | AZ7: 0.3 | BA7: 0 | BC7: 0.3 | BD7: 0 | BF7: 0.3 | BG7: 0 | BI7: 0.3 | BJ7: 0 | BL7: 0.3 | BM7: 0.3 | BO7: 0.3 | BP7: 0.3 | BR7: 0.3 | BS7: 0.3 | BU7: 0.3 | BV7: 0.3 | BX7: 0.3 | CA7: 0.3 | CD7: 0.3 | CG7: 0.3 | CJ7: 0.3 | CM7: 0.3
A8: 00:15 - 00:30 | D8: 1 | E8: 0 | G8: 1 | J8: 0.5 | K8: 0 | M8: 0.5 | N8: 0 | P8: 0.5 | Q8: 0 | S8: 0.5 | T8: 0 | V8: 0.5 | W8: 0 | Y8: 0.5 | Z8: 0 | AB8: 0.5 | AC8: 0 | AE8: 0.5 | AH8: 0.5 | AI8: 0 | AK8: 0.5 | AL8: 0 | AN8: 0.5 | AO8: 0 | AQ8: 0.3 | AR8: 0.3 | AT8: 0.3 | AU8: 0 | AW8: 0.3 | AX8: 0 | AZ8: 0.3 | BA8: 0.3 | BC8: 0.3 | BD8: 0 | BF8: 0.3 | BG8: 0 | BI8: 0.3 | BJ8: 0 | BL8: 0.3 | BM8: 0.3 | BO8: 0.3 | BP8: 0.3 | BR8: 0.3 | BS8: 0.3 | BU8: 0.3 | BV8: 0.3 | BX8: 0.3 | CA8: 0.3 | CD8: 0.3 | CG8: 0.3 | CJ8: 0.3 | CM8: 0.3
A9: 00:30 - 00:45 | D9: 1 | E9: 0 | G9: 1 | J9: 0.5 | K9: 0 | M9: 0.5 | N9: 0 | P9: 0.5 | Q9: 0 | S9: 0.5 | T9: 0 | V9: 0.5 | W9: 0 | Y9: 0.5 | Z9: 0 | AB9: 0.5 | AC9: 0 | AE9: 0.5 | AH9: 0.5 | AI9: 0 | AK9: 0.5 | AL9: 0 | AN9: 0.5 | AO9: 0 | AQ9: 0.3 | AR9: 0.3 | AT9: 0.3 | AU9: 0 | AW9: 0.3 | AX9: 0 | AZ9: 0.3 | BA9: 0.3 | BC9: 0.3 | BD9: 0 | BF9: 0.3 | BG9: 0 | BI9: 0.3 | BJ9: 0 | BL9: 0.3 | BM9: 0 | BO9: 0.3 | BP9: 0 | BR9: 0.3 | BS9: 0.3 | BU9: 0.3 | BV9: 0.3 | BX9: 0.3 | CA9: 0.3 | CD9: 0.3 | CG9: 0.3 | CJ9: 0.3 | CM9: 0.3
A10: 00:45 - 01:00 | D10: 1 | E10: 0 | G10: 1 | J10: 0.5 | K10: 0 | M10: 0.5 | N10: 0 | P10: 0.5 | Q10: 0 | S10: 0.5 | T10: 0 | V10: 0.5 | W10: 0 | Y10: 0.5 | Z10: 0 | AB10: 0.5 | AC10: 0 | AE10: 0.5 | AH10: 0.5 | AI10: 0 | AK10: 0.5 | AL10: 0 | AN10: 0.5 | AO10: 0 | AQ10: 0.3 | AR10: 0.3 | AT10: 0.3 | AU10: 0 | AW10: 0.3 | AX10: 0.3 | AZ10: 0.3 | BA10: 0.3 | BC10: 0.3 | BD10: 0 | BF10: 0.3 | BG10: 0 | BI10: 0.3 | BJ10: 0 | BL10: 0.3 | BM10: 0 | BO10: 0.3 | BP10: 0 | BR10: 0.3 | BS10: 0.3 | BU10: 0.3 | BV10: 0.3 | BX10: 0.3 | CA10: 0.3 | CD10: 0.3 | CG10: 0.3 | CJ10: 0.3 | CM10: 0.3
A11: 01:00 - 01:15 | D11: 1 | E11: 0 | G11: 1 | J11: 0.5 | K11: 0 | M11: 0.5 | N11: 0 | P11: 0.5 | Q11: 0 | S11: 0.5 | T11: 0 | V11: 0.5 | W11: 0 | Y11: 0.5 | Z11: 0 | AB11: 0.5 | AC11: 0 | AE11: 0.5 | AH11: 0.5 | AI11: 0 | AK11: 0.5 | AL11: 0 | AN11: 0.5 | AO11: 0 | AQ11: 0.3 | AR11: 0.3 | AT11: 0.3 | AU11: 0.2 | AW11: 0.3 | AX11: 0.3 | AZ11: 0.3 | BA11: 0 | BC11: 0.3 | BD11: 0.3 | BF11: 0.3 | BG11: 0 | BI11: 0.3 | BJ11: 0 | BL11: 0.3 | BM11: 0.3 | BO11: 0.3 | BP11: 0.3 | BR11: 0.3 | BS11: 0.3 | BU11: 0.3 | BV11: 0.3 | BX11: 0.3 | CA11: 0.3 | CD11: 0.3 | CG11: 0.3 | CJ11: 0.3 | CM11: 0.3
A12: 01:15 - 01:30 | D12: 1 | E12: 0 | G12: 1 | J12: 0.5 | K12: 0 | M12: 0.5 | N12: 0 | P12: 0.5 | Q12: 0 | S12: 0.5 | T12: 0 | V12: 0.5 | W12: 0 | Y12: 0.5 | Z12: 0 | AB12: 0.5 | AC12: 0 | AE12: 0.5 | AH12: 0.5 | AI12: 0 | AK12: 0.5 | AL12: 0 | AN12: 0.5 | AO12: 0 | AQ12: 0.3 | AR12: 0.3 | AT12: 0.3 | AU12: 0.2 | AW12: 0.3 | AX12: 0.3 | AZ12: 0.3 | BA12: 0 | BC12: 0.3 | BD12: 0.3 | BF12: 0.3 | BG12: 0 | BI12: 0.3 | BJ12: 0 | BL12: 0.3 | BM12: 0.3 | BO12: 0.3 | BP12: 0.3 | BR12: 0.3 | BS12: 0.3 | BU12: 0.3 | BV12: 0.3 | BX12: 0.3 | CA12: 0.3 | CD12: 0.3 | CG12: 0.3 | CJ12: 0.3 | CM12: 0.3
A13: 01:30 - 01:45 | D13: 1 | E13: 0 | G13: 1 | J13: 0.5 | K13: 0 | M13: 0.5 | N13: 0 | P13: 0.5 | Q13: 0 | S13: 0.5 | T13: 0 | V13: 0.5 | W13: 0 | Y13: 0.5 | Z13: 0 | AB13: 0.5 | AC13: 0 | AE13: 0.5 | AH13: 0.5 | AI13: 0 | AK13: 0.5 | AL13: 0 | AN13: 0.5 | AO13: 0 | AQ13: 0.3 | AR13: 0.3 | AT13: 0.3 | AU13: 0.2 | AW13: 0.3 | AX13: 0 | AZ13: 0.3 | BA13: 0 | BC13: 0.3 | BD13: 0.3 | BF13: 0.3 | BG13: 0 | BI13: 0.3 | BJ13: 0 | BL13: 0.3 | BM13: 0.3 | BO13: 0.3 | BP13: 0.3 | BR13: 0.3 | BS13: 0.3 | BU13: 0.3 | BV13: 0.3 | BX13: 0.3 | CA13: 0.3 | CD13: 0.3 | CG13: 0.3 | CJ13: 0.3 | CM13: 0.3
A14: 01:45 - 02:00 | D14: 1 | E14: 0 | G14: 1 | J14: 0.5 | K14: 0 | M14: 0.5 | N14: 0 | P14: 0.5 | Q14: 0 | S14: 0.5 | T14: 0 | V14: 0.5 | W14: 0 | Y14: 0.5 | Z14: 0 | AB14: 0.5 | AC14: 0 | AE14: 0.5 | AH14: 0.5 | AI14: 0 | AK14: 0.5 | AL14: 0 | AN14: 0.5 | AO14: 0 | AQ14: 0.3 | AR14: 0.3 | AT14: 0.3 | AU14: 0.2 | AW14: 0.3 | AX14: 0 | AZ14: 0.3 | BA14: 0 | BC14: 0.3 | BD14: 0.3 | BF14: 0.3 | BG14: 0 | BI14: 0.3 | BJ14: 0 | BL14: 0.3 | BM14: 0.3 | BO14: 0.3 | BP14: 0.3 | BR14: 0.3 | BS14: 0.3 | BU14: 0.3 | BV14: 0.3 | BX14: 0.3 | CA14: 0.3 | CD14: 0.3 | CG14: 0.3 | CJ14: 0.3 | CM14: 0.3
A15: 02:00 - 02:15 | D15: 1 | E15: 0 | G15: 1 | J15: 0.5 | K15: 0 | M15: 0.5 | N15: 0 | P15: 0.5 | Q15: 0 | S15: 0.5 | T15: 0 | V15: 0.5 | W15: 0 | Y15: 0.5 | Z15: 0 | AB15: 0.5 | AC15: 0 | AE15: 0.5 | AH15: 0.5 | AI15: 0 | AK15: 0.5 | AL15: 0 | AN15: 0.5 | AO15: 0 | AQ15: 0.3 | AR15: 0.3 | AT15: 0.3 | AU15: 0.2 | AW15: 0.3 | AX15: 0 | AZ15: 0.3 | BA15: 0 | BC15: 0.3 | BD15: 0.3 | BF15: 0.3 | BG15: 0 | BI15: 0.3 | BJ15: 0.3 | BL15: 0.3 | BM15: 0.3 | BO15: 0.3 | BP15: 0.3 | BR15: 0.3 | BS15: 0.3 | BU15: 0.3 | BV15: 0.3 | BX15: 0.3 | CA15: 0.3 | CD15: 0.3 | CG15: 0.3 | CJ15: 0.3 | CM15: 0.3
A16: 02:15 - 02:30 | D16: 1 | E16: 0 | G16: 1 | J16: 0.5 | K16: 0 | M16: 0.5 | N16: 0 | P16: 0.5 | Q16: 0 | S16: 0.5 | T16: 0 | V16: 0.5 | W16: 0 | Y16: 0.5 | Z16: 0 | AB16: 0.5 | AC16: 0 | AE16: 0.5 | AH16: 0.5 | AI16: 0 | AK16: 0.5 | AL16: 0 | AN16: 0.5 | AO16: 0 | AQ16: 0.3 | AR16: 0.3 | AT16: 0.3 | AU16: 0.2 | AW16: 0.3 | AX16: 0 | AZ16: 0.3 | BA16: 0 | BC16: 0.3 | BD16: 0 | BF16: 0.3 | BG16: 0 | BI16: 0.3 | BJ16: 0.3 | BL16: 0.3 | BM16: 0.3 | BO16: 0.3 | BP16: 0.3 | BR16: 0.3 | BS16: 0.3 | BU16: 0.3 | BV16: 0.3 | BX16: 0.3 | CA16: 0.3 | CD16: 0.3 | CG16: 0.3 | CJ16: 0.3 | CM16: 0.3
A17: 02:30 - 02:45 | D17: 1 | E17: 0 | G17: 1 | J17: 0.5 | K17: 0 | M17: 0.5 | N17: 0 | P17: 0.5 | Q17: 0 | S17: 0.5 | T17: 0 | V17: 0.5 | W17: 0 | Y17: 0.5 | Z17: 0 | AB17: 0.5 | AC17: 0 | AE17: 0.5 | AH17: 0.5 | AI17: 0 | AK17: 0.5 | AL17: 0 | AN17: 0.5 | AO17: 0 | AQ17: 0.3 | AR17: 0.3 | AT17: 0.3 | AU17: 0.2 | AW17: 0.3 | AX17: 0 | AZ17: 0.3 | BA17: 0.3 | BC17: 0.3 | BD17: 0 | BF17: 0.3 | BG17: 0 | BI17: 0.3 | BJ17: 0.3 | BL17: 0.3 | BM17: 0.3 | BO17: 0.3 | BP17: 0.3 | BR17: 0.3 | BS17: 0.3 | BU17: 0.3 | BV17: 0.3 | BX17: 0.3 | CA17: 0.3 | CD17: 0.3 | CG17: 0.3 | CJ17: 0.3 | CM17: 0.3
A18: 02:45 - 03:00 | D18: 1 | E18: 0 | G18: 1 | J18: 0.5 | K18: 0 | M18: 0.5 | N18: 0 | P18: 0.5 | Q18: 0 | S18: 0.5 | T18: 0 | V18: 0.5 | W18: 0 | Y18: 0.5 | Z18: 0 | AB18: 0.5 | AC18: 0 | AE18: 0.5 | AH18: 0.5 | AI18: 0 | AK18: 0.5 | AL18: 0 | AN18: 0.5 | AO18: 0 | AQ18: 0.3 | AR18: 0.3 | AT18: 0.3 | AU18: 0.2 | AW18: 0.3 | AX18: 0.3 | AZ18: 0.3 | BA18: 0.3 | BC18: 0.3 | BD18: 0 | BF18: 0.3 | BG18: 0 | BI18: 0.3 | BJ18: 0.3 | BL18: 0.3 | BM18: 0.3 | BO18: 0.3 | BP18: 0.3 | BR18: 0.3 | BS18: 0.3 | BU18: 0.3 | BV18: 0.3 | BX18: 0.3 | CA18: 0.3 | CD18: 0.3 | CG18: 0.3 | CJ18: 0.3 | CM18: 0.3
A19: 03:00 - 03:15 | D19: 1 | E19: 0 | G19: 1 | J19: 0.5 | K19: 0 | M19: 0.5 | N19: 0 | P19: 0.5 | Q19: 0 | S19: 0.5 | T19: 0 | V19: 0.5 | W19: 0 | Y19: 0.5 | Z19: 0 | AB19: 0.5 | AC19: 0 | AE19: 0.5 | AH19: 0.5 | AI19: 0 | AK19: 0.5 | AL19: 0 | AN19: 0.5 | AO19: 0 | AQ19: 0.3 | AR19: 0.3 | AT19: 0.3 | AU19: 0.2 | AW19: 0.3 | AX19: 0 | AZ19: 0.3 | BA19: 0.3 | BC19: 0.3 | BD19: 0.3 | BF19: 0.3 | BG19: 0 | BI19: 0.3 | BJ19: 0.3 | BL19: 0.3 | BM19: 0.3 | BO19: 0.3 | BP19: 0.3 | BR19: 0.3 | BS19: 0.3 | BU19: 0.3 | BV19: 0.3 | BX19: 0.3 | CA19: 0.3 | CD19: 0.3 | CG19: 0.3 | CJ19: 0.3 | CM19: 0.3
... A26: 04:45 - 05:00 | D26: 1 | E26: 0 | G26: 1 | J26: 0.5 | K26: 0 | M26: 0.5 | N26: 0 | P26: 0.5 | Q26: 0 | S26: 0.5 | T26: 0 | V26: 0.5 | W26: 0 | Y26: 0.5 | Z26: 0 | AB26: 0.5 | AC26: 0 | AE26: 0.5 | AH26: 0.5 | AI26: 0 | AK26: 0.5 | AL26: 0 | AN26: 0.5 | AO26: 0 | AQ26: 0.3 | AR26: 0 | AT26: 0.3 | AU26: 0 | AW26: 0.3 | AX26: 0 | AZ26: 0.3 | BA26: 0 | BC26: 0.3 | BD26: 0 | BF26: 0.3 | BG26: 0 | BI26: 0.3 | BJ26: 0 | BL26: 0.3 | BM26: 0.3 | BO26: 0.3 | BP26: 0.3 | BR26: 0.3 | BS26: 0 | BU26: 0.3 | BV26: 0 | BX26: 0.3 | CA26: 0.3 | CD26: 0.3 | CG26: 0.3 | CJ26: 0.3 | CM26: 0.3
A27: 05:00 - 05:15 | B27: C4 | D27: 1 | E27: 0 | G27: 1 | J27: 0.5 | K27: 0 | M27: 0.5 | N27: 0 | P27: 0.5 | Q27: 0 | S27: 0.5 | T27: 0 | V27: 0.5 | W27: 0 | Y27: 0.5 | Z27: 0 | AB27: 0.5 | AC27: 0 | AE27: 0.5 | AH27: 0.5 | AI27: 0 | AK27: 0.5 | AL27: 0 | AN27: 0.5 | AO27: 0 | AQ27: 0.5 | AR27: 0.5 | AT27: 0.5 | AU27: 0.3 | AW27: 0.5 | AX27: 0 | AZ27: 0.5 | BA27: 0 | BC27: 0.5 | BD27: 0.5 | BF27: 0.5 | BG27: 0 | BI27: 0.5 | BJ27: 0 | BL27: 0.5 | BM27: 0.2 | BO27: 0.5 | BP27: 0.2 | BR27: 0.5 | BS27: 0 | BU27: 0.5 | BV27: 0 | BX27: 0.5 | CA27: 0.5 | CD27: 0.5 | CG27: 0.5 | CJ27: 0.5 | CM27: 0.5
A28: 05:15 - 05:30 | D28: 1 | E28: 0 | G28: 1 | J28: 0.5 | K28: 0 | M28: 0.5 | N28: 0 | P28: 0.5 | Q28: 0 | S28: 0.5 | T28: 0 | V28: 0.5 | W28: 0 | Y28: 0.5 | Z28: 0 | AB28: 0.5 | AC28: 0 | AE28: 0.5 | AH28: 0.5 | AI28: 0 | AK28: 0.5 | AL28: 0 | AN28: 0.5 | AO28: 0 | AQ28: 0.5 | AR28: 0 | AT28: 0.5 | AU28: 0.3 | AW28: 0.5 | AX28: 0 | AZ28: 0.5 | BA28: 0.6 | BC28: 0.5 | BD28: 0 | BF28: 0.5 | BG28: 0 | BI28: 0.5 | BJ28: 0 | BL28: 0.5 | BM28: 0.2 | BO28: 0.5 | BP28: 0.2 | BR28: 0.5 | BS28: 0 | BU28: 0.5 | BV28: 0.3 | BX28: 0.5 | CA28: 0.5 | CD28: 0.5 | CG28: 0.5 | CJ28: 0.5 | CM28: 0.5
A29: 05:30 - 05:45 | D29: 1 | E29: 0 | G29: 1 | J29: 0 | K29: 0 | M29: 0.5 | N29: 0 | P29: 0.5 | Q29: 0 | S29: 0.5 | T29: 0 | V29: 0.5 | W29: 0 | Y29: 0.5 | Z29: 0 | AB29: 0.5 | AC29: 0 | AE29: 0.5 | AH29: 0.5 | AI29: 0 | AK29: 0.5 | AL29: 0 | AN29: 0.5 | AO29: 0 | AQ29: 0.5 | AR29: 0 | AT29: 0.5 | AU29: 0 | AW29: 0.5 | AX29: 0 | AZ29: 0 | BA29: 0.6 | BC29: 0 | BD29: 0 | BF29: 0 | BG29: 0 | BI29: 0 | BJ29: 0.5 | BL29: 0.5 | BM29: 0.2 | BO29: 0.5 | BP29: 0.2 | BR29: 0.5 | BS29: 0.4 | BU29: 0.5 | BV29: 0 | BX29: 0.5 | CA29: 0.5 | CD29: 0.5 | CG29: 0.5 | CJ29: 0.5 | CM29: 0.5
A30: 05:45 - 06:00 | D30: 0 | E30: 0 | G30: 1 | J30: 0 | K30: 0 | M30: 0.5 | N30: 0 | P30: 0.5 | Q30: 0 | S30: 0.5 | T30: 0 | V30: 0 | W30: 0 | Y30: 0 | Z30: 0 | AB30: 0 | AC30: 0 | AE30: 0.5 | AH30: 0.5 | AI30: 0 | AK30: 0.5 | AL30: 0 | AN30: 0.5 | AO30: 0 | AQ30: 0.5 | AR30: 0 | AT30: 0.5 | AU30: 0 | AW30: 0 | AX30: 0 | AZ30: 0 | BA30: 0 | BC30: 0 | BD30: 0.5 | BF30: 0 | BG30: 0 | BI30: 0 | BJ30: 0.5 | BL30: 0.5 | BM30: 0.2 | BO30: 0.5 | BP30: 0.2 | BR30: 0.5 | BS30: 0.4 | BU30: 0.5 | BV30: 0.3 | BX30: 0.5 | CA30: 0.5 | CD30: 0.5 | CG30: 0.5 | CJ30: 0 | CM30: 0
A31: 06:00 - 06:15 | B31: C1 | D31: 0 | E31: 0 | G31: 0 | J31: 0 | K31: 0.5 | M31: 0.5 | N31: 0 | P31: 0.5 | Q31: 0 | S31: 0.5 | T31: 0 | V31: 0 | W31: 0 | Y31: 0 | Z31: 0 | AB31: 0 | AC31: 0 | AE31: 0.5 | AH31: 0.5 | AI31: 0 | AK31: 0.5 | AL31: 0 | AN31: 0.5 | AO31: 0 | AQ31: 0.5 | AR31: 0.5 | AT31: 0.5 | AU31: 0 | AW31: 0 | AX31: 0 | AZ31: 0 | BA31: 0 | BC31: 0 | BD31: 0.6 | BF31: 0.5 | BG31: 0 | BI31: 0.5 | BJ31: 0 | BL31: 0.5 | BM31: 0.2 | BO31: 0.5 | BP31: 0.2 | BR31: 0.5 | BS31: 0.1 | BU31: 0.5 | BV31: 0.1 | BX31: 0.5 | CA31: 0.5 | CD31: 0.5 | CG31: 0.5 | CJ31: 0.5 | CM31: 0.5
A32: 06:15 - 06:30 | D32: 0 | E32: 0 | G32: 0 | J32: 0 | K32: 0.5 | M32: 0.5 | N32: 0 | P32: 0.5 | Q32: 0 | S32: 0 | T32: 0 | V32: 0 | W32: 0 | Y32: 0 | Z32: 0 | AB32: 0 | AC32: 0 | AE32: 0.5 | AH32: 0.5 | AI32: 0 | AK32: 0.5 | AL32: 0 | AN32: 0.5 | AO32: 0 | AQ32: 0 | AR32: 0.5 | AT32: 0 | AU32: 0 | AW32: 0 | AX32: 0 | AZ32: 0 | BA32: 0 | BC32: 0 | BD32: 0.6 | BF32: 0 | BG32: 0.6 | BI32: 0.5 | BJ32: 0 | BL32: 0 | BM32: 0.7 | BO32: 0.5 | BP32: 0.7 | BR32: 0.5 | BS32: 0.1 | BU32: 0 | BV32: 0.5 | BX32: 0.5 | CA32: 0.5 | CD32: 0.5 | CG32: 0.5 | CJ32: 0 | CM32: 0
A33: 06:30 - 06:45 | D33: 0 | E33: 0 | G33: 0 | J33: 0 | K33: 0 | M33: 0.5 | N33: 0 | P33: 0.5 | Q33: 0 | S33: 0 | T33: 0 | V33: 0 | W33: 0 | Y33: 0 | Z33: 0 | AB33: 0 | AC33: 0 | AE33: 0 | AH33: 0.5 | AI33: 0 | AK33: 0 | AL33: 0.6 | AN33: 0 | AO33: 0.6 | AQ33: 0.5 | AR33: 0.5 | AT33: 0 | AU33: 0 | AW33: 0 | AX33: 0 | AZ33: 0 | BA33: 0 | BC33: 0 | BD33: 0.6 | BF33: 0 | BG33: 0.6 | BI33: 0 | BJ33: 0.6 | BL33: 0 | BM33: 0.7 | BO33: 0 | BP33: 0.7 | BR33: 0 | BS33: 0.6 | BU33: 0 | BV33: 0 | BX33: 0.5 | CA33: 0 | CD33: 0.5 | CG33: 0.5 | CJ33: 0 | CM33: 0
A34: 06:45 - 07:00 | D34: 0 | E34: 0 | G34: 0 | J34: 0 | K34: 0 | M34: 0 | N34: 0 | P34: 0 | Q34: 0 | S34: 0 | T34: 0 | V34: 0 | W34: 0 | Y34: 0 | Z34: 0 | AB34: 0 | AC34: 0 | AE34: 0 | AH34: 0.5 | AI34: 0 | AK34: 0 | AL34: 0 | AN34: 0 | AO34: 0.6 | AQ34: 0 | AR34: 0 | AT34: 0 | AU34: 0 | AW34: 0 | AX34: 0 | AZ34: 0 | BA34: 0 | BC34: 0 | BD34: 0 | BF34: 0 | BG34: 0 | BI34: 0 | BJ34: 0.6 | BL34: 0 | BM34: 0 | BO34: 0 | BP34: 0 | BR34: 0 | BS34: 0 | BU34: 0 | BV34: 0 | BX34: 0 | CA34: 0 | CD34: 0 | CG34: 0.5 | CJ34: 0 | CM34: 0
A35: 07:00 - 07:15 | D35: 0 | E35: 0 | G35: 0 | J35: 0 | K35: 0 | M35: 0 | N35: 0 | P35: 0 | Q35: 0 | S35: 0 | T35: 0 | V35: 0 | W35: 0 | Y35: 0 | Z35: 0 | AB35: 0 | AC35: 0 | AE35: 0 | AH35: 0.5 | AI35: 0 | AK35: 0 | AL35: 0.6 | AN35: 0 | AO35: 0 | AQ35: 0 | AR35: 0 | AT35: 0 | AU35: 0 | AW35: 0 | AX35: 0 | AZ35: 0 | BA35: 0 | BC35: 0 | BD35: 0 | BF35: 0 | BG35: 0 | BI35: 0 | BJ35: 0 | BL35: 0 | BM35: 0 | BO35: 0 | BP35: 0 | BR35: 0 | BS35: 0 | BU35: 0 | BV35: 0 | BX35: 0 | CA35: 0 | CD35: 0 | CG35: 0 | CJ35: 0 | CM35: 0
A36: 07:15 - 07:30 | D36: 0 | E36: 0 | G36: 0 | J36: 0 | K36: 0 | M36: 0 | N36: 0 | P36: 0 | Q36: 0 | S36: 0 | T36: 0 | V36: 0 | W36: 0 | Y36: 0 | Z36: 0 | AB36: 0 | AC36: 0 | AE36: 0 | AH36: 0 | AI36: 0 | AK36: 0 | AL36: 0.6 | AN36: 0 | AO36: 0 | AQ36: 0 | AR36: 0 | AT36: 0 | AU36: 0 | AW36: 0 | AX36: 0 | AZ36: 0 | BA36: 0 | BC36: 0 | BD36: 0 | BF36: 0 | BG36: 0 | BI36: 0 | BJ36: 0 | BL36: 0 | BM36: 0 | BO36: 0 | BP36: 0 | BR36: 0 | BS36: 0 | BU36: 0 | BV36: 0 | BX36: 0 | CA36: 0 | CD36: 0 | CG36: 0 | CJ36: 0 | CM36: 0
A37: 07:30 - 07:45 | D37: 0 | E37: 0 | G37: 0 | J37: 0 | K37: 0 | M37: 0 | N37: 0 | P37: 0 | Q37: 0 | S37: 0 | T37: 0 | V37: 0 | W37: 0 | Y37: 0 | Z37: 0 | AB37: 0 | AC37: 0 | AE37: 0 | AH37: 0 | AI37: 0 | AK37: 0 | AL37: 0.6 | AN37: 0 | AO37: 0 | AQ37: 0 | AR37: 0 | AT37: 0 | AU37: 0 | AW37: 0 | AX37: 0 | AZ37: 0 | BA37: 0 | BC37: 0 | BD37: 0 | BF37: 0 | BG37: 0 | BI37: 0 | BJ37: 0 | BL37: 0 | BM37: 0 | BO37: 0 | BP37: 0 | BR37: 0 | BS37: 0 | BU37: 0 | BV37: 0 | BX37: 0 | CA37: 0 | CD37: 0 | CG37: 0 | CJ37: 0 | CM37: 0
A38: 07:45 - 08:00 | D38: 0 | E38: 0 | G38: 0 | J38: 0 | K38: 0 | M38: 0 | N38: 0 | P38: 0 | Q38: 0 | S38: 0 | T38: 0 | V38: 0 | W38: 0 | Y38: 0 | Z38: 0 | AB38: 0 | AC38: 0 | AE38: 0 | AH38: 0 | AI38: 0 | AK38: 0 | AL38: 0 | AN38: 0 | AO38: 0 | AQ38: 0 | AR38: 0 | AT38: 0 | AU38: 0 | AW38: 0 | AX38: 0 | AZ38: 0 | BA38: 0 | BC38: 0 | BD38: 0 | BF38: 0 | BG38: 0 | BI38: 0 | BJ38: 0 | BL38: 0 | BM38: 0 | BO38: 0 | BP38: 0 | BR38: 0 | BS38: 0 | BU38: 0 | BV38: 0 | BX38: 0 | CA38: 0 | CD38: 0 | CG38: 0 | CJ38: 0 | CM38: 0
A39: 08:00 - 08:15 | D39: 0 | E39: 0 | G39: 0 | J39: 0 | K39: 0.5 | M39: 0 | N39: 0 | P39: 0 | Q39: 0 | S39: 0 | T39: 0 | V39: 0 | W39: 0 | Y39: 0 | Z39: 0 | AB39: 0 | AC39: 0 | AE39: 0 | AH39: 0 | AI39: 0 | AK39: 0 | AL39: 0 | AN39: 0 | AO39: 0 | AQ39: 0 | AR39: 0 | AT39: 0 | AU39: 0 | AW39: 0 | AX39: 0 | AZ39: 0 | BA39: 0 | BC39: 0 | BD39: 0 | BF39: 0 | BG39: 0 | BI39: 0 | BJ39: 0 | BL39: 0 | BM39: 0 | BO39: 0 | BP39: 0 | BR39: 0 | BS39: 0 | BU39: 0 | BV39: 0 | BX39: 0 | CA39: 0 | CD39: 0 | CG39: 0 | CJ39: 0 | CM39: 0
A40: 08:15 - 08:30 | D40: 0 | E40: 0 | G40: 0 | J40: 0 | K40: 0.5 | M40: 0 | N40: 0 | P40: 0 | Q40: 0 | S40: 0 | T40: 0 | V40: 0 | W40: 0 | Y40: 0 | Z40: 0 | AB40: 0 | AC40: 0 | AE40: 0 | AH40: 0 | AI40: 0 | AK40: 0 | AL40: 0 | AN40: 0 | AO40: 0 | AQ40: 0 | AR40: 0 | AT40: 0 | AU40: 0 | AW40: 0 | AX40: 0 | AZ40: 0 | BA40: 0 | BC40: 0 | BD40: 0 | BF40: 0 | BG40: 0 | BI40: 0 | BJ40: 0 | BL40: 0 | BM40: 0 | BO40: 0 | BP40: 0 | BR40: 0 | BS40: 0 | BU40: 0 | BV40: 0 | BX40: 0 | CA40: 0 | CD40: 0 | CG40: 0 | CJ40: 0 | CM40: 0
A41: 08:30 - 08:45 | D41: 0 | E41: 0 | G41: 0 | J41: 0 | K41: 0 | M41: 0 | N41: 0 | P41: 0 | Q41: 0 | S41: 0 | T41: 0 | V41: 0 | W41: 0 | Y41: 0 | Z41: 0 | AB41: 0 | AC41: 0 | AE41: 0 | AH41: 0 | AI41: 0 | AK41: 0 | AL41: 0 | AN41: 0 | AO41: 0 | AQ41: 0 | AR41: 0 | AT41: 0 | AU41: 0 | AW41: 0 | AX41: 0 | AZ41: 0 | BA41: 0 | BC41: 0 | BD41: 0 | BF41: 0 | BG41: 0 | BI41: 0 | BJ41: 0 | BL41: 0 | BM41: 0 | BO41: 0 | BP41: 0 | BR41: 0 | BS41: 0 | BU41: 0 | BV41: 0 | BX41: 0 | CA41: 0 | CD41: 0 | CG41: 0 | CJ41: 0 | CM41: 0
A42: 08:45 - 09:00 | D42: 0 | E42: 0 | G42: 0 | J42: 0 | K42: 0 | M42: 0 | N42: 0 | P42: 0 | Q42: 0 | S42: 0 | T42: 0 | V42: 0 | W42: 0 | Y42: 0 | Z42: 0 | AB42: 0 | AC42: 0 | AE42: 0 | AH42: 0 | AI42: 0 | AK42: 0 | AL42: 0 | AN42: 0 | AO42: 0 | AQ42: 0 | AR42: 0 | AT42: 0 | AU42: 0 | AW42: 0 | AX42: 0 | AZ42: 0 | BA42: 0 | BC42: 0 | BD42: 0 | BF42: 0 | BG42: 0 | BI42: 0 | BJ42: 0 | BL42: 0 | BM42: 0 | BO42: 0 | BP42: 0 | BR42: 0 | BS42: 0 | BU42: 0 | BV42: 0 | BX42: 0 | CA42: 0 | CD42: 0 | CG42: 0 | CJ42: 0 | CM42: 0
A43: 09:00 - 09:15 | D43: 0 | E43: 0 | G43: 0 | J43: 0 | K43: 0 | M43: 0 | N43: 0 | P43: 0 | Q43: 0 | S43: 0 | T43: 0 | V43: 0 | W43: 0 | Y43: 0 | Z43: 0 | AB43: 0 | AC43: 0 | AE43: 0 | AH43: 0 | AI43: 0 | AK43: 0 | AL43: 0 | AN43: 0 | AO43: 0 | AQ43: 0 | AR43: 0 | AT43: 0 | AU43: 0 | AW43: 0 | AX43: 0 | AZ43: 0 | BA43: 0 | BC43: 0 | BD43: 0 | BF43: 0 | BG43: 0 | BI43: 0 | BJ43: 0 | BL43: 0 | BM43: 0.7 | BO43: 0 | BP43: 0.7 | BR43: 0 | BS43: 0 | BU43: 0 | BV43: 0 | BX43: 0 | CA43: 0 | CD43: 0 | CG43: 0 | CJ43: 0 | CM43: 0
... A46: 09:45 - 10:00 | D46: 0 | E46: 0 | G46: 0 | J46: 0 | K46: 0 | M46: 0 | N46: 0 | P46: 0 | Q46: 0 | S46: 0 | T46: 0 | V46: 0 | W46: 0 | Y46: 0 | Z46: 0 | AB46: 0 | AC46: 0 | AE46: 0 | AH46: 0 | AI46: 0 | AK46: 0 | AL46: 0 | AN46: 0 | AO46: 0 | AQ46: 0 | AR46: 0 | AT46: 0 | AU46: 0 | AW46: 0 | AX46: 0 | AZ46: 0 | BA46: 0 | BC46: 0 | BD46: 0.6 | BF46: 0 | BG46: 0 | BI46: 0 | BJ46: 0 | BL46: 0 | BM46: 0 | BO46: 0 | BP46: 0 | BR46: 0 | BS46: 0 | BU46: 0 | BV46: 0 | BX46: 0 | CA46: 0 | CD46: 0 | CG46: 0 | CJ46: 0 | CM46: 0
A47: 10:00 - 10:15 | B47: C4 | D47: 0 | E47: 0 | G47: 0 | J47: 0 | K47: 0 | M47: 0 | N47: 0 | P47: 0 | Q47: 0 | S47: 0 | T47: 0 | V47: 0 | W47: 0 | Y47: 0 | Z47: 0 | AB47: 0 | AC47: 0 | AE47: 0 | AH47: 0 | AI47: 0 | AK47: 0 | AL47: 0 | AN47: 0 | AO47: 0 | AQ47: 0 | AR47: 0 | AT47: 0 | AU47: 0 | AW47: 0 | AX47: 0 | AZ47: 0 | BA47: 0 | BC47: 0 | BD47: 0 | BF47: 0 | BG47: 0 | BI47: 0 | BJ47: 0 | BL47: 0 | BM47: 0 | BO47: 0 | BP47: 0 | BR47: 0 | BS47: 0 | BU47: 0 | BV47: 0 | BX47: 0 | CA47: 0 | CD47: 0 | CG47: 0 | CJ47: 0 | CM47: 0
A48: 10:15 - 10:30 | D48: 0 | E48: 0 | G48: 0 | J48: 0 | K48: 0 | M48: 0 | N48: 0 | P48: 0 | Q48: 0 | S48: 0 | T48: 0 | V48: 0 | W48: 0 | Y48: 0 | Z48: 0 | AB48: 0 | AC48: 0 | AE48: 0 | AH48: 0 | AI48: 0 | AK48: 0 | AL48: 2.6 | AN48: 0 | AO48: 0 | AQ48: 0 | AR48: 0 | AT48: 0 | AU48: 0 | AW48: 0 | AX48: 0 | AZ48: 0 | BA48: 0 | BC48: 0 | BD48: 0 | BF48: 0 | BG48: 0 | BI48: 0 | BJ48: 0 | BL48: 0 | BM48: 0 | BO48: 0 | BP48: 0 | BR48: 0 | BS48: 0 | BU48: 0 | BV48: 0 | BX48: 0 | CA48: 0 | CD48: 0 | CG48: 0 | CJ48: 0 | CM48: 0
A49: 10:30 - 10:45 | D49: 0 | E49: 0 | G49: 0 | J49: 0 | K49: 0 | M49: 0 | N49: 0 | P49: 0 | Q49: 0 | S49: 0 | T49: 0 | V49: 0 | W49: 0 | Y49: 0 | Z49: 0 | AB49: 0 | AC49: 0 | AE49: 0 | AH49: 0 | AI49: 0 | AK49: 0 | AL49: 0 | AN49: 0 | AO49: 0 | AQ49: 0 | AR49: 0 | AT49: 0 | AU49: 0 | AW49: 0 | AX49: 0 | AZ49: 0 | BA49: 0 | BC49: 0 | BD49: 0 | BF49: 0 | BG49: 0 | BI49: 0 | BJ49: 0 | BL49: 0 | BM49: 0 | BO49: 0 | BP49: 0 | BR49: 0 | BS49: 0 | BU49: 0 | BV49: 0 | BX49: 0 | CA49: 0 | CD49: 0 | CG49: 0 | CJ49: 0 | CM49: 0
A50: 10:45 - 11:00 | D50: 0 | E50: 0 | G50: 0 | J50: 0 | K50: 0 | M50: 0 | N50: 0 | P50: 0 | Q50: 0 | S50: 0 | T50: 0 | V50: 0 | W50: 0 | Y50: 0 | Z50: 0 | AB50: 0 | AC50: 0 | AE50: 0 | AH50: 0 | AI50: 0 | AK50: 0 | AL50: 0 | AN50: 0 | AO50: 0 | AQ50: 0 | AR50: 0 | AT50: 0 | AU50: 0 | AW50: 0 | AX50: 0 | AZ50: 0 | BA50: 0 | BC50: 0 | BD50: 0 | BF50: 0 | BG50: 0 | BI50: 0 | BJ50: 0 | BL50: 0 | BM50: 0 | BO50: 0 | BP50: 0 | BR50: 0 | BS50: 0 | BU50: 0 | BV50: 0 | BX50: 0 | CA50: 0 | CD50: 0 | CG50: 0 | CJ50: 0 | CM50: 0
A51: 11:00 - 11:15 | D51: 0 | E51: 0 | G51: 0 | J51: 0 | K51: 0 | M51: 0 | N51: 0 | P51: 0 | Q51: 0 | S51: 0 | T51: 0 | V51: 0 | W51: 0 | Y51: 0 | Z51: 0 | AB51: 0 | AC51: 0 | AE51: 0 | AH51: 0 | AI51: 0 | AK51: 0 | AL51: 0 | AN51: 0 | AO51: 0 | AQ51: 0 | AR51: 0 | AT51: 0 | AU51: 0 | AW51: 0 | AX51: 0 | AZ51: 0 | BA51: 0 | BC51: 0 | BD51: 0 | BF51: 0 | BG51: 0 | BI51: 0 | BJ51: 0 | BL51: 0 | BM51: 0 | BO51: 0 | BP51: 0 | BR51: 0 | BS51: 0 | BU51: 0 | BV51: 0 | BX51: 0 | CA51: 0 | CD51: 0 | CG51: 0 | CJ51: 0 | CM51: 0
A52: 11:15 - 11:30 | D52: 0 | E52: 0 | G52: 0 | J52: 0 | K52: 0 | M52: 0 | N52: 0 | P52: 0 | Q52: 0 | S52: 0 | T52: 0 | V52: 0 | W52: 0 | Y52: 0 | Z52: 0 | AB52: 0 | AC52: 0 | AE52: 0 | AH52: 2 | AI52: 0 | AK52: 0 | AL52: 0 | AN52: 0 | AO52: 0 | AQ52: 0 | AR52: 2.6 | AT52: 0 | AU52: 0 | AW52: 0 | AX52: 0 | AZ52: 0 | BA52: 0 | BC52: 0 | BD52: 0 | BF52: 0 | BG52: 0 | BI52: 0 | BJ52: 0 | BL52: 0 | BM52: 0 | BO52: 0 | BP52: 0 | BR52: 0 | BS52: 0 | BU52: 0 | BV52: 0 | BX52: 0 | CA52: 0 | CD52: 0 | CG52: 0 | CJ52: 0 | CM52: 0
A53: 11:30 - 11:45 | D53: 0 | E53: 2 | G53: 0 | J53: 0 | K53: 0 | M53: 0 | N53: 0 | P53: 0 | Q53: 0 | S53: 0 | T53: 0 | V53: 0 | W53: 0 | Y53: 0 | Z53: 0 | AB53: 0 | AC53: 0 | AE53: 0 | AH53: 2 | AI53: 0 | AK53: 0 | AL53: 2.6 | AN53: 0 | AO53: 0 | AQ53: 0 | AR53: 2.6 | AT53: 0 | AU53: 0 | AW53: 0 | AX53: 0 | AZ53: 0 | BA53: 0 | BC53: 0 | BD53: 0 | BF53: 0 | BG53: 0 | BI53: 0 | BJ53: 0 | BL53: 0 | BM53: 0 | BO53: 0 | BP53: 0 | BR53: 0 | BS53: 0 | BU53: 0 | BV53: 0 | BX53: 0 | CA53: 0 | CD53: 0 | CG53: 0 | CJ53: 0 | CM53: 0
A54: 11:45 - 12:00 | D54: 0 | E54: 2 | G54: 0 | J54: 0 | K54: 0 | M54: 0 | N54: 0 | P54: 0 | Q54: 0 | S54: 0 | T54: 0 | V54: 0 | W54: 0 | Y54: 0 | Z54: 2.6 | AB54: 0 | AC54: 0 | AE54: 0 | AH54: 2 | AI54: 0 | AK54: 0 | AL54: 0 | AN54: 0 | AO54: 0 | AQ54: 0 | AR54: 0 | AT54: 0 | AU54: 0 | AW54: 0 | AX54: 0 | AZ54: 0 | BA54: 0 | BC54: 0 | BD54: 0 | BF54: 0 | BG54: 0 | BI54: 0 | BJ54: 0 | BL54: 0 | BM54: 0 | BO54: 0 | BP54: 0 | BR54: 0 | BS54: 0 | BU54: 0 | BV54: 0 | BX54: 0 | CA54: 0 | CD54: 0 | CG54: 0 | CJ54: 0 | CM54: 0
A55: 12:00 - 12:15 | D55: 0 | E55: 2 | G55: 0 | J55: 0 | K55: 0 | M55: 2 | N55: 0 | P55: 0 | Q55: 0 | S55: 0 | T55: 0 | V55: 0 | W55: 0 | Y55: 0 | Z55: 2.6 | AB55: 0 | AC55: 2.6 | AE55: 0 | AH55: 2 | AI55: 0 | AK55: 0 | AL55: 0 | AN55: 0 | AO55: 0 | AQ55: 0 | AR55: 0 | AT55: 0 | AU55: 0 | AW55: 0 | AX55: 0 | AZ55: 0 | BA55: 0 | BC55: 0 | BD55: 0 | BF55: 0 | BG55: 0 | BI55: 0 | BJ55: 0 | BL55: 0 | BM55: 0 | BO55: 0 | BP55: 0 | BR55: 0 | BS55: 0 | BU55: 0.02 | BV55: 0 | BX55: 0 | CA55: 0 | CD55: 0 | CG55: 0 | CJ55: 0 | CM55: 0
A56: 12:15 - 12:30 | D56: 0 | E56: 2 | G56: 0 | J56: 0 | K56: 0 | M56: 2 | N56: 0 | P56: 0 | Q56: 0 | S56: 0 | T56: 0 | V56: 0 | W56: 0 | Y56: 0 | Z56: 2.6 | AB56: 0 | AC56: 0 | AE56: 0 | AH56: 2 | AI56: 0.6 | AK56: 0 | AL56: 0 | AN56: 0 | AO56: 0 | AQ56: 0 | AR56: 2.6 | AT56: 0 | AU56: 0 | AW56: 0 | AX56: 0 | AZ56: 0 | BA56: 0 | BC56: 0 | BD56: 0 | BF56: 0 | BG56: 0 | BI56: 0 | BJ56: 0 | BL56: 0 | BM56: 0 | BO56: 0 | BP56: 0 | BR56: 0 | BS56: 0 | BU56: 2 | BV56: 0 | BX56: 0 | CA56: 0 | CD56: 0 | CG56: 0 | CJ56: 0 | CM56: 0
A57: 12:30 - 12:45 | D57: 0 | E57: 0 | G57: 0 | J57: 0 | K57: 0 | M57: 2 | N57: 0 | P57: 0 | Q57: 0 | S57: 0 | T57: 0 | V57: 0 | W57: 0 | Y57: 0 | Z57: 0 | AB57: 0 | AC57: 0 | AE57: 0 | AH57: 2 | AI57: 0 | AK57: 0 | AL57: 0 | AN57: 0 | AO57: 0 | AQ57: 0 | AR57: 2.6 | AT57: 0 | AU57: 0 | AW57: 0 | AX57: 0 | AZ57: 0 | BA57: 0 | BC57: 0 | BD57: 0 | BF57: 0 | BG57: 0 | BI57: 0 | BJ57: 0 | BL57: 0 | BM57: 0 | BO57: 0 | BP57: 0 | BR57: 0 | BS57: 0 | BU57: 2 | BV57: 0 | BX57: 0 | CA57: 0 | CD57: 0 | CG57: 0 | CJ57: 0 | CM57: 0
A58: 12:45 - 13:00 | D58: 0 | E58: 0 | G58: 0 | J58: 0 | K58: 0 | M58: 2 | N58: 0 | P58: 0 | Q58: 0 | S58: 0 | T58: 2 | V58: 0 | W58: 0 | Y58: 0 | Z58: 0 | AB58: 0 | AC58: 0 | AE58: 0 | AH58: 2 | AI58: 0.6 | AK58: 0 | AL58: 0 | AN58: 2 | AO58: 0 | AQ58: 0 | AR58: 2.6 | AT58: 0 | AU58: 0 | AW58: 0 | AX58: 0 | AZ58: 0 | BA58: 0 | BC58: 2 | BD58: 0 | BF58: 0 | BG58: 0 | BI58: 0 | BJ58: 0 | BL58: 0 | BM58: 0 | BO58: 0 | BP58: 0 | BR58: 0 | BS58: 0 | BU58: 2 | BV58: 0 | BX58: 2 | CA58: 0 | CD58: 0 | CG58: 0 | CJ58: 0 | CM58: 0
A59: 13:00 - 13:15 | D59: 0 | E59: 2 | G59: 0 | J59: 2 | K59: 0 | M59: 2 | N59: 0 | P59: 2 | Q59: 0 | S59: 2 | T59: 0 | V59: 2 | W59: 0.6 | Y59: 2 | Z59: 0 | AB59: 2 | AC59: 0.6 | AE59: 2 | AH59: 2 | AI59: 0.6 | AK59: 2 | AL59: 0.6 | AN59: 2 | AO59: 0.6 | AQ59: 2 | AR59: 0.6 | AT59: 2 | AU59: 0.6 | AW59: 2 | AX59: 0 | AZ59: 0.37 | BA59: 2.6 | BC59: 2 | BD59: 0.6 | BF59: 0 | BG59: 2.6 | BI59: 0 | BJ59: 0 | BL59: 0 | BM59: 0 | BO59: 0 | BP59: 0 | BR59: 0 | BS59: 0 | BU59: 2 | BV59: 0 | BX59: 2 | CA59: 0 | CD59: 0 | CG59: 0 | CJ59: 0 | CM59: 0
... A78: 17:45 - 18:00 | D78: 0 | E78: 0 | G78: 0 | J78: 0 | K78: 0 | M78: 0 | N78: 0 | P78: 0 | Q78: 0 | S78: 0 | T78: 0 | V78: 0 | W78: 0 | Y78: 0 | Z78: 0 | AB78: 0 | AC78: 0 | AE78: 0 | AH78: 0 | AI78: 2.6 | AK78: 0 | AL78: 0 | AN78: 0 | AO78: 0 | AQ78: 0 | AR78: 0 | AT78: 0 | AU78: 0 | AW78: 0 | AX78: 0 | AZ78: 0 | BA78: 0 | BC78: 0 | BD78: 0 | BF78: 0 | BG78: 0 | BI78: 0 | BJ78: 0 | BL78: 0 | BM78: 0 | BO78: 0 | BP78: 0 | BR78: 0 | BS78: 0 | BU78: 0 | BV78: 0 | BX78: 0 | CA78: 0 | CD78: 0 | CG78: 0 | CJ78: 0 | CM78: 0
A79: 18:00 - 18:15 | B79: C2 | D79: 0 | E79: 0 | G79: 0 | J79: 0 | K79: 0.51 | M79: 3 | N79: 0 | P79: 0 | Q79: 0 | S79: 0 | T79: 0 | V79: 0 | W79: 0 | Y79: 0 | Z79: 0 | AB79: 0 | AC79: 3 | AE79: 3 | AH79: 3 | AI79: 0.3 | AK79: 0 | AL79: 3 | AN79: 0 | AO79: 0 | AQ79: 0 | AR79: 0 | AT79: 0 | AU79: 0 | AW79: 0 | AX79: 0 | AZ79: 0 | BA79: 0 | BC79: 0 | BD79: 3 | BF79: 0 | BG79: 0 | BI79: 0 | BJ79: 0 | BL79: 0 | BM79: 0 | BO79: 0 | BP79: 0 | BR79: 0 | BS79: 0 | BU79: 0 | BV79: 0 | BX79: 0 | CA79: 0 | CD79: 0 | CG79: 0 | CJ79: 0 | CM79: 0
A80: 18:15 - 18:30 | D80: 0 | E80: 0 | G80: 0 | J80: 0 | K80: 0 | M80: 3 | N80: 0 | P80: 0 | Q80: 0 | S80: 0 | T80: 0 | V80: 0 | W80: 0 | Y80: 0 | Z80: 0 | AB80: 0 | AC80: 0 | AE80: 0 | AH80: 3 | AI80: 0.3 | AK80: 0 | AL80: 3 | AN80: 0 | AO80: 0 | AQ80: 0 | AR80: 0 | AT80: 0 | AU80: 0 | AW80: 0 | AX80: 0 | AZ80: 0 | BA80: 0 | BC80: 0 | BD80: 3 | BF80: 0 | BG80: 0 | BI80: 0 | BJ80: 0 | BL80: 0 | BM80: 0 | BO80: 0 | BP80: 0 | BR80: 0 | BS80: 0 | BU80: 0 | BV80: 0 | BX80: 0 | CA80: 0 | CD80: 0 | CG80: 0 | CJ80: 0 | CM80: 0
A81: 18:30 - 18:45 | D81: 0 | E81: 0 | G81: 0 | J81: 0 | K81: 0 | M81: 3 | N81: 0 | P81: 0 | Q81: 0 | S81: 0 | T81: 0 | V81: 0 | W81: 0 | Y81: 0 | Z81: 3 | AB81: 0 | AC81: 3 | AE81: 0 | AH81: 3 | AI81: 0.3 | AK81: 0 | AL81: 3 | AN81: 0 | AO81: 0 | AQ81: 0 | AR81: 0 | AT81: 0 | AU81: 0 | AW81: 0 | AX81: 0 | AZ81: 0 | BA81: 0 | BC81: 0 | BD81: 3 | BF81: 0 | BG81: 0 | BI81: 0 | BJ81: 0 | BL81: 0 | BM81: 0 | BO81: 0 | BP81: 0 | BR81: 0 | BS81: 0 | BU81: 0 | BV81: 0 | BX81: 0 | CA81: 0 | CD81: 0 | CG81: 0 | CJ81: 0 | CM81: 0
A82: 18:45 - 19:00 | D82: 0 | E82: 0 | G82: 0 | J82: 0 | K82: 0 | M82: 3 | N82: 0 | P82: 0 | Q82: 0 | S82: 0 | T82: 0 | V82: 0 | W82: 0 | Y82: 0 | Z82: 3 | AB82: 0 | AC82: 3 | AE82: 0 | AH82: 3 | AI82: 0.3 | AK82: 0 | AL82: 3 | AN82: 0 | AO82: 0 | AQ82: 0 | AR82: 0 | AT82: 0 | AU82: 0 | AW82: 0 | AX82: 0 | AZ82: 0 | BA82: 0 | BC82: 0 | BD82: 3 | BF82: 0 | BG82: 0 | BI82: 0 | BJ82: 0 | BL82: 0 | BM82: 0 | BO82: 0 | BP82: 0 | BR82: 0 | BS82: 0 | BU82: 0 | BV82: 0 | BX82: 0 | CA82: 0 | CD82: 0 | CG82: 0 | CJ82: 0 | CM82: 0
A83: 19:00 - 19:15 | D83: 0 | E83: 0 | G83: 0 | J83: 0 | K83: 0 | M83: 0 | N83: 3 | P83: 0 | Q83: 3 | S83: 0 | T83: 3 | V83: 0 | W83: 0 | Y83: 0 | Z83: 3 | AB83: 0 | AC83: 3 | AE83: 0 | AH83: 3 | AI83: 0.3 | AK83: 3 | AL83: 0 | AN83: 0 | AO83: 0 | AQ83: 0 | AR83: 0 | AT83: 0 | AU83: 0 | AW83: 0 | AX83: 0 | AZ83: 0 | BA83: 0 | BC83: 0 | BD83: 3 | BF83: 0 | BG83: 0 | BI83: 0 | BJ83: 0 | BL83: 0 | BM83: 0 | BO83: 0 | BP83: 0 | BR83: 0 | BS83: 0 | BU83: 0 | BV83: 0 | BX83: 0 | CA83: 0 | CD83: 0 | CG83: 0 | CJ83: 0 | CM83: 0
A84: 19:15 - 19:30 | D84: 0 | E84: 0 | G84: 0 | J84: 0 | K84: 0 | M84: 0 | N84: 3 | P84: 0 | Q84: 0 | S84: 0 | T84: 3 | V84: 0 | W84: 0 | Y84: 0 | Z84: 3 | AB84: 0 | AC84: 3 | AE84: 3 | AH84: 3 | AI84: 0.3 | AK84: 3 | AL84: 0 | AN84: 2.5 | AO84: 0 | AQ84: 2.5 | AR84: 0 | AT84: 0 | AU84: 0 | AW84: 0 | AX84: 0 | AZ84: 0 | BA84: 0 | BC84: 0 | BD84: 0 | BF84: 0 | BG84: 0 | BI84: 0 | BJ84: 0 | BL84: 0 | BM84: 0 | BO84: 0 | BP84: 0 | BR84: 0 | BS84: 0 | BU84: 0 | BV84: 0 | BX84: 0 | CA84: 0 | CD84: 0 | CG84: 0 | CJ84: 0 | CM84: 0
A85: 19:30 - 19:45 | D85: 0 | E85: 3 | G85: 0 | J85: 0 | K85: 3 | M85: 0 | N85: 3 | P85: 0 | Q85: 3 | S85: 0 | T85: 3 | V85: 0 | W85: 3 | Y85: 0 | Z85: 3 | AB85: 3 | AC85: 0 | AE85: 3 | AH85: 3 | AI85: 0.3 | AK85: 3 | AL85: 0 | AN85: 2.5 | AO85: 0.5 | AQ85: 2.5 | AR85: 0.5 | AT85: 2.5 | AU85: 0 | AW85: 0 | AX85: 0 | AZ85: 0 | BA85: 0 | BC85: 2.5 | BD85: 0 | BF85: 0 | BG85: 0 | BI85: 0 | BJ85: 0 | BL85: 0 | BM85: 0 | BO85: 0 | BP85: 0 | BR85: 0 | BS85: 0 | BU85: 0 | BV85: 0 | BX85: 0 | CA85: 0 | CD85: 0 | CG85: 0 | CJ85: 0 | CM85: 0
A86: 19:45 - 20:00 | D86: 0 | E86: 3 | G86: 0 | J86: 0 | K86: 3 | M86: 0 | N86: 3 | P86: 0 | Q86: 3 | S86: 3 | T86: 0 | V86: 0 | W86: 3 | Y86: 3 | Z86: 0 | AB86: 3 | AC86: 0 | AE86: 3 | AH86: 3 | AI86: 0.3 | AK86: 3 | AL86: 0 | AN86: 2.5 | AO86: 0.5 | AQ86: 2.5 | AR86: 0.5 | AT86: 2.5 | AU86: 0 | AW86: 0 | AX86: 0 | AZ86: 0 | BA86: 0 | BC86: 2.5 | BD86: 0 | BF86: 0 | BG86: 0 | BI86: 0 | BJ86: 0 | BL86: 0 | BM86: 1.1 | BO86: 0 | BP86: 1.1 | BR86: 0 | BS86: 0 | BU86: 0 | BV86: 0 | BX86: 0 | CA86: 0 | CD86: 0 | CG86: 0 | CJ86: 0 | CM86: 0
A87: 20:00 - 20:15 | D87: 3 | E87: 0 | G87: 3 | J87: 3 | K87: 0 | M87: 3 | N87: 0 | P87: 0 | Q87: 3 | S87: 3 | T87: 0 | V87: 0 | W87: 3 | Y87: 3 | Z87: 0 | AB87: 3 | AC87: 0 | AE87: 3 | AH87: 3 | AI87: 0.3 | AK87: 3 | AL87: 0 | AN87: 2.5 | AO87: 0.5 | AQ87: 2.5 | AR87: 0 | AT87: 2.5 | AU87: 0 | AW87: 0 | AX87: 0 | AZ87: 0 | BA87: 0 | BC87: 2.5 | BD87: 0 | BF87: 0 | BG87: 0 | BI87: 0 | BJ87: 0 | BL87: 2.5 | BM87: 0.6 | BO87: 2.5 | BP87: 0.6 | BR87: 0 | BS87: 3 | BU87: 0 | BV87: 0 | BX87: 2.5 | CA87: 0 | CD87: 0 | CG87: 2.5 | CJ87: 0 | CM87: 2.5
A88: 20:15 - 20:30 | D88: 3 | E88: 0 | G88: 3 | J88: 0 | K88: 3 | M88: 3 | N88: 0 | P88: 0 | Q88: 3 | S88: 3 | T88: 0 | V88: 0 | W88: 3 | Y88: 3 | Z88: 0 | AB88: 3 | AC88: 0 | AE88: 3 | AH88: 3 | AI88: 0.3 | AK88: 3 | AL88: 0 | AN88: 2.5 | AO88: 0.5 | AQ88: 2.5 | AR88: 0 | AT88: 2.5 | AU88: 0 | AW88: 0 | AX88: 0 | AZ88: 2.5 | BA88: 0 | BC88: 2.5 | BD88: 0 | BF88: 0 | BG88: 3 | BI88: 0 | BJ88: 0 | BL88: 2.5 | BM88: 0.6 | BO88: 0 | BP88: 0.6 | BR88: 2.5 | BS88: 0.5 | BU88: 2.5 | BV88: 0 | BX88: 2.5 | CA88: 0 | CD88: 0 | CG88: 2.5 | CJ88: 0 | CM88: 2.5
A89: 20:30 - 20:45 | D89: 0 | E89: 3 | G89: 3 | J89: 0 | K89: 3 | M89: 3 | N89: 0 | P89: 3 | Q89: 0 | S89: 3 | T89: 0 | V89: 0 | W89: 3 | Y89: 3 | Z89: 0 | AB89: 3 | AC89: 0 | AE89: 3 | AH89: 3 | AI89: 0.3 | AK89: 3 | AL89: 0 | AN89: 2.5 | AO89: 0.5 | AQ89: 2.5 | AR89: 0.5 | AT89: 2.5 | AU89: 0.13 | AW89: 2.5 | AX89: 0 | AZ89: 2.5 | BA89: 0 | BC89: 2.5 | BD89: 0 | BF89: 2.5 | BG89: 0.5 | BI89: 2.5 | BJ89: 0.5 | BL89: 0 | BM89: 3 | BO89: 2.5 | BP89: 3 | BR89: 2.5 | BS89: 0.5 | BU89: 2.5 | BV89: 0.6 | BX89: 2.5 | CA89: 2.5 | CD89: 2.5 | CG89: 2.5 | CJ89: 0 | CM89: 2.5
A90: 20:45 - 21:00 | D90: 3 | E90: 0 | G90: 3 | J90: 3 | K90: 0 | M90: 3 | N90: 0 | P90: 3 | Q90: 0 | S90: 3 | T90: 0 | V90: 0 | W90: 3 | Y90: 3 | Z90: 0 | AB90: 3 | AC90: 0 | AE90: 3 | AH90: 3 | AI90: 0.3 | AK90: 3 | AL90: 0 | AN90: 2.5 | AO90: 0.5 | AQ90: 2.5 | AR90: 0.5 | AT90: 2.5 | AU90: 0.5 | AW90: 2.5 | AX90: 0 | AZ90: 2.5 | BA90: 0 | BC90: 2.5 | BD90: 0 | BF90: 2.5 | BG90: 0.5 | BI90: 2.5 | BJ90: 0.5 | BL90: 2.5 | BM90: 0.6 | BO90: 2.5 | BP90: 0.6 | BR90: 2.5 | BS90: 0.5 | BU90: 2.5 | BV90: 0.6 | BX90: 2.5 | CA90: 2.5 | CD90: 2.5 | CG90: 2.5 | CJ90: 2.5 | CM90: 2.5
A91: 21:00 - 21:15 | D91: 3 | E91: 0 | G91: 3 | J91: 3 | K91: 0 | M91: 3 | N91: 0 | P91: 3 | Q91: 0 | S91: 3 | T91: 0 | V91: 3 | W91: 0 | Y91: 3 | Z91: 0 | AB91: 3 | AC91: 0 | AE91: 3 | AH91: 3 | AI91: 0.3 | AK91: 3 | AL91: 0 | AN91: 2.5 | AO91: 0.5 | AQ91: 2.5 | AR91: 0.5 | AT91: 2.5 | AU91: 0.5 | AW91: 2.5 | AX91: 0.5 | AZ91: 2.5 | BA91: 0 | BC91: 2.5 | BD91: 0 | BF91: 2.5 | BG91: 0.5 | BI91: 2.5 | BJ91: 0.5 | BL91: 2.5 | BM91: 0.6 | BO91: 2.5 | BP91: 0.6 | BR91: 2.5 | BS91: 0.5 | BU91: 2.5 | BV91: 0.6 | BX91: 2.5 | CA91: 2.5 | CD91: 2.5 | CG91: 2.5 | CJ91: 2.5 | CM91: 2.5
... A94: 21:45 - 22:00 | D94: 3 | E94: 0 | G94: 3 | J94: 3 | K94: 0 | M94: 3 | N94: 0 | P94: 3 | Q94: 0 | S94: 3 | T94: 0 | V94: 3 | W94: 0 | Y94: 3 | Z94: 0 | AB94: 3 | AC94: 0 | AE94: 3 | AH94: 3 | AI94: 0.3 | AK94: 3 | AL94: 0 | AN94: 2.5 | AO94: 0.5 | AQ94: 2.5 | AR94: 0.5 | AT94: 2.5 | AU94: 0.5 | AW94: 2.5 | AX94: 0.5 | AZ94: 2.5 | BA94: 0.6 | BC94: 2.5 | BD94: 0 | BF94: 2.5 | BG94: 0.5 | BI94: 2.5 | BJ94: 0.5 | BL94: 2.5 | BM94: 0.6 | BO94: 2.5 | BP94: 0.6 | BR94: 2.5 | BS94: 0.5 | BU94: 2.5 | BV94: 0.6 | BX94: 2.5 | CA94: 2.5 | CD94: 2.5 | CG94: 2.5 | CJ94: 2.5 | CM94: 2.5
A95: 22:00 - 22:15 | B95: C5 | D95: 0 | E95: 0 | G95: 0 | J95: 0 | K95: 0 | M95: 0 | N95: 0 | P95: 0 | Q95: 0 | S95: 0 | T95: 0 | V95: 0 | W95: 0 | Y95: 0 | Z95: 0 | AB95: 0 | AC95: 0.5 | AE95: 0 | AH95: 0.5 | AI95: 0.1 | AK95: 0.5 | AL95: 0 | AN95: 0.5 | AO95: 0 | AQ95: 0 | AR95: 0 | AT95: 0 | AU95: 0 | AW95: 0 | AX95: 0 | AZ95: 0 | BA95: 0 | BC95: 0 | BD95: 0 | BF95: 0 | BG95: 0 | BI95: 0 | BJ95: 0.5 | BL95: 0 | BM95: 0 | BO95: 0 | BP95: 0 | BR95: 0 | BS95: 0 | BU95: 0 | BV95: 0 | BX95: 0.3 | CA95: 0 | CD95: 0 | CG95: 0 | CJ95: 0 | CM95: 0
A96: 22:15 - 22:30 | D96: 0 | E96: 0 | G96: 0 | J96: 0 | K96: 0 | M96: 0 | N96: 0 | P96: 0 | Q96: 0 | S96: 0 | T96: 0 | V96: 0 | W96: 0 | Y96: 0 | Z96: 0 | AB96: 0 | AC96: 0 | AE96: 0.5 | AH96: 0.5 | AI96: 0.1 | AK96: 0.5 | AL96: 0 | AN96: 0.5 | AO96: 0 | AQ96: 0.3 | AR96: 0 | AT96: 0 | AU96: 0 | AW96: 0 | AX96: 0 | AZ96: 0 | BA96: 0 | BC96: 0 | BD96: 0 | BF96: 0 | BG96: 0 | BI96: 0 | BJ96: 0.5 | BL96: 0 | BM96: 0 | BO96: 0 | BP96: 0 | BR96: 0 | BS96: 0 | BU96: 0.3 | BV96: 0 | BX96: 0.3 | CA96: 0 | CD96: 0 | CG96: 0 | CJ96: 0 | CM96: 0
A97: 22:30 - 22:45 | D97: 0 | E97: 0 | G97: 0 | J97: 0 | K97: 0 | M97: 0 | N97: 0 | P97: 0 | Q97: 0 | S97: 0 | T97: 0 | V97: 0 | W97: 0 | Y97: 0 | Z97: 0 | AB97: 0 | AC97: 0 | AE97: 0.5 | AH97: 0.5 | AI97: 0.1 | AK97: 0.5 | AL97: 0 | AN97: 0.5 | AO97: 0 | AQ97: 0.3 | AR97: 0 | AT97: 0.3 | AU97: 0 | AW97: 0 | AX97: 0 | AZ97: 0 | BA97: 0 | BC97: 0 | BD97: 0 | BF97: 0 | BG97: 0 | BI97: 0 | BJ97: 0.5 | BL97: 0 | BM97: 0 | BO97: 0 | BP97: 0 | BR97: 0 | BS97: 0 | BU97: 0.3 | BV97: 0 | BX97: 0.3 | CA97: 0 | CD97: 0.3 | CG97: 0.3 | CJ97: 0 | CM97: 0
A98: 22:45 - 23:00 | D98: 0 | E98: 0 | G98: 0 | J98: 0 | K98: 0 | M98: 0 | N98: 0 | P98: 0 | Q98: 0 | S98: 0 | T98: 0 | V98: 0 | W98: 0 | Y98: 0 | Z98: 0 | AB98: 0 | AC98: 0 | AE98: 0.5 | AH98: 0.5 | AI98: 0.1 | AK98: 0.5 | AL98: 0 | AN98: 0.5 | AO98: 0 | AQ98: 0.3 | AR98: 0 | AT98: 0.3 | AU98: 0 | AW98: 0 | AX98: 0 | AZ98: 0 | BA98: 0 | BC98: 0 | BD98: 0 | BF98: 0 | BG98: 0 | BI98: 0 | BJ98: 0.5 | BL98: 0 | BM98: 0 | BO98: 0 | BP98: 0 | BR98: 0 | BS98: 0 | BU98: 0.3 | BV98: 0 | BX98: 0.3 | CA98: 0.3 | CD98: 0.3 | CG98: 0.3 | CJ98: 0 | CM98: 0
A99: 23:00 - 23:15 | D99: 1 | E99: 0 | G99: 0 | J99: 0 | K99: 0 | M99: 0.5 | N99: 0 | P99: 0 | Q99: 0 | S99: 0 | T99: 0 | V99: 0 | W99: 0 | Y99: 0 | Z99: 0 | AB99: 0.5 | AC99: 0 | AE99: 0.5 | AH99: 0.5 | AI99: 0.1 | AK99: 0.5 | AL99: 0 | AN99: 0.5 | AO99: 0 | AQ99: 0.3 | AR99: 0 | AT99: 0.3 | AU99: 0 | AW99: 0.3 | AX99: 0 | AZ99: 0 | BA99: 0 | BC99: 0.3 | BD99: 0 | BF99: 0 | BG99: 0 | BI99: 0 | BJ99: 0 | BL99: 0 | BM99: 0 | BO99: 0 | BP99: 0 | BR99: 0 | BS99: 0 | BU99: 0.3 | BV99: 0 | BX99: 0.3 | CA99: 0.3 | CD99: 0.3 | CG99: 0.3 | CJ99: 0.3 | CM99: 0.3
A100: 23:15 - 23:30 | D100: 1 | E100: 0 | G100: 0 | J100: 0 | K100: 0 | M100: 0.5 | N100: 0 | P100: 0 | Q100: 0 | S100: 0 | T100: 0 | V100: 0 | W100: 0 | Y100: 0.5 | Z100: 0 | AB100: 0.5 | AC100: 0 | AE100: 0.5 | AH100: 0.5 | AI100: 0.1 | AK100: 0.5 | AL100: 0 | AN100: 0.5 | AO100: 0 | AQ100: 0.3 | AR100: 0 | AT100: 0.3 | AU100: 0 | AW100: 0.3 | AX100: 0 | AZ100: 0.3 | BA100: 0 | BC100: 0.3 | BD100: 0 | BF100: 0 | BG100: 0 | BI100: 0 | BJ100: 0 | BL100: 0.3 | BM100: 0 | BO100: 0 | BP100: 0 | BR100: 0.3 | BS100: 0 | BU100: 0.3 | BV100: 0 | BX100: 0.3 | CA100: 0.3 | CD100: 0.3 | CG100: 0.3 | CJ100: 0.3 | CM100: 0.3
A101: 23:30 - 23:45 | D101: 1 | E101: 0 | G101: 1 | J101: 0 | K101: 0 | M101: 0.5 | N101: 0 | P101: 0 | Q101: 0 | S101: 0 | T101: 0 | V101: 0 | W101: 0.8 | Y101: 0.5 | Z101: 0 | AB101: 0.5 | AC101: 0 | AE101: 0.5 | AH101: 0.5 | AI101: 0.1 | AK101: 0.5 | AL101: 0 | AN101: 0.5 | AO101: 0 | AQ101: 0.3 | AR101: 0 | AT101: 0.3 | AU101: 0 | AW101: 0.3 | AX101: 0 | AZ101: 0.3 | BA101: 0 | BC101: 0.3 | BD101: 0 | BF101: 0 | BG101: 0 | BI101: 0 | BJ101: 0 | BL101: 0.3 | BM101: 0 | BO101: 0.3 | BP101: 0 | BR101: 0.3 | BS101: 0 | BU101: 0.3 | BV101: 0 | BX101: 0.3 | CA101: 0.3 | CD101: 0.3 | CG101: 0.3 | CJ101: 0.3 | CM101: 0.3
A102: 23:45 - 24:00 | D102: 1 | E102: 0 | G102: 1 | J102: 0.5 | K102: 0 | M102: 0.5 | N102: 0 | P102: 0.5 | Q102: 0 | S102: 0.5 | T102: 0 | V102: 0.16 | W102: 0 | Y102: 0.5 | Z102: 0 | AB102: 0.5 | AC102: 0 | AE102: 0.5 | AH102: 0.5 | AI102: 0.1 | AK102: 0.5 | AL102: 0 | AN102: 0.5 | AO102: 0 | AQ102: 0.3 | AR102: 0 | AT102: 0.3 | AU102: 0 | AW102: 0.3 | AX102: 0 | AZ102: 0.3 | BA102: 0 | BC102: 0.3 | BD102: 0 | BF102: 0.3 | BG102: 0 | BI102: 0.3 | BJ102: 0 | BL102: 0.3 | BM102: 0 | BO102: 0.3 | BP102: 0 | BR102: 0.3 | BS102: 0 | BU102: 0.3 | BV102: 0.1 | BX102: 0.3 | CA102: 0.3 | CD102: 0.3 | CG102: 0.3 | CJ102: 0.3 | CM102: 0.3
D103: 12 | E103: 5.25 | G103: 12.5 | J103: 9.25 | K103: 3.6275 | M103: 20.375 | N103: 3 | P103: 10 | Q103: 3.75 | S103: 13 | T103: 2.75 | V103: 8.415 | W103: 5.45 | Y103: 12 | Z103: 7 | AB103: 13.375 | AC103: 6.575 | AE103: 17.125 | AH103: 26.625 | AI103: 7.6 | AK103: 16.75 | AL103: 5.2 | AN103: 17.625 | AO103: 2.15 | AQ103: 11.15 | AR103: 6.475 | AT103: 12.325 | AU103: 3.1575 | AW103: 6.925 | AX103: 1.025 | AZ103: 6.9425 | BA103: 3.15 | BC103: 10.3 | BD103: 7.825 | BF103: 5.7 | BG103: 4.4 | BI103: 5.825 | BJ103: 2.4 | BL103: 6.725 | BM103: 8.925 | BO103: 6.775 | BP103: 8.925 | BR103: 6.85 | BS103: 4.025 | BU103: 13.53 | BV103: 2.575 | BX103: 12.975 | CA103: 6.375 | CD103: 6.575 | CG103: 7.95 | CJ103: 5.425 | CM103: 7.3

Sheet Savings Sheet
A1: IEX POWER PURCHASE, DELIVERY AND COST SHEET
A2: DATE | B2: LINE LOSS % | C2: IEX Price | D2: Equivalent EB Price | E2: Total Cost Saving | F2: IEX Price per Unit | G2: Equivalent EB Price per Unit | H2: Cost Saving Per Unit | I2: Tata Power Bill
B3: CT
A4: 44896 | B4: ='Energy Schedule'!D3 -> 0.0343 | C4: ='01'!$B$44 -> 110442.82 | D4: ='01'!$B$46 -> 155363.77 | E4: =D4-C4 -> 44920.954 | F4: ='01'!$B$45 -> 6.9237573 | G4: ='01'!$B$47 -> 9.7398913 | H4: =G4-F4 -> 2.8161341
A5: =A4+1 -> 44897 | B5: ='Energy Schedule'!G3 -> 0.0343 | C5: ='02'!$B$44 -> 91934.959 | D5: ='02'!$B$46 -> 113273.19 | E5: =D5-C5 -> 21338.23 | F5: ='02'!$B$45 -> 7.9536069 | G5: ='02'!$B$47 -> 9.79965 | H5: =G5-F5 -> 1.8460431
A6: =A5+1 -> 44898 | B6: ='Energy Schedule'!J3 -> 0.0343 | C6: ='03'!$B$44 -> 99210.45 | D6: ='03'!$B$46 -> 122016.27 | E6: =D6-C6 -> 22805.82 | F6: ='03'!$B$45 -> 8.3314254 | G6: ='03'!$B$47 -> 10.246597 | H6: =G6-F6 -> 1.9151711
A7: =A6+1 -> 44899 | B7: ='Energy Schedule'!M3 -> 0.0343 | C7: ='04'!$B$44 -> 180092.63 | D7: ='04'!$B$46 -> 217210.11 | E7: =D7-C7 -> 37117.479 | F7: ='04'!$B$45 -> 8.3317795 | G7: ='04'!$B$47 -> 10.048977 | H7: =G7-F7 -> 1.7171977
A8: =A7+1 -> 44900 | B8: ='Energy Schedule'!P3 -> 0.0361 | C8: ='05'!$B$44 -> 105620.59 | D8: ='05'!$B$46 -> 129949.28 | E8: =D8-C8 -> 24328.691 | F8: ='05'!$B$45 -> 8.3224196 | G8: ='05'!$B$47 -> 10.239409 | H8: =G8-F8 -> 1.9169895
A9: =A8+1 -> 44901 | B9: ='Energy Schedule'!S3 -> 0.0361 | C9: ='06'!$B$44 -> 124711.24 | D9: ='06'!$B$46 -> 147454.34 | E9: =D9-C9 -> 22743.096 | F9: ='06'!$B$45 -> 8.5788436 | G9: ='06'!$B$47 -> 10.143333 | H9: =G9-F9 -> 1.5644897
A10: =A9+1 -> 44902 | B10: ='Energy Schedule'!V3 -> 0.0361 | C10: ='07'!$B$44 -> 106544.89 | D10: ='07'!$B$46 -> 128532.4 | E10: =D10-C10 -> 21987.517 | F10: ='07'!$B$45 -> 8.3256173 | G10: ='07'!$B$47 -> 10.043763 | H10: =G10-F10 -> 1.7181458
A11: =A10+1 -> 44903 | B11: ='Energy Schedule'!Y3 -> 0.0361 | C11: ='08'!$B$44 -> 152711.99 | D11: ='08'!$B$46 -> 176955.5 | E11: =D11-C11 -> 24243.512 | F11: ='08'!$B$45 -> 8.7080966 | G11: ='07'!$B$47 -> 10.043763 | H11: =G11-F11 -> 1.3356664
A12: =A11+1 -> 44904 | B12: ='Energy Schedule'!AB3 -> 0.0361 | C12: ='09'!$B$44 -> 155993.7 | D12: ='09'!$B$46 -> 186222.88 | E12: =D12-C12 -> 30229.187 | F12: ='09'!$B$45 -> 8.4716471 | G12: ='09'!$B$47 -> 10.113322 | H12: =G12-F12 -> 1.6416753
A13: =A12+1 -> 44905 | B13: ='Energy Schedule'!AE3 -> 0.0361 | C13: ='10'!$B$44 -> 131820.36 | D13: ='10'!$B$46 -> 158729.65 | E13: =D13-C13 -> 26909.296 | F13: ='10'!$B$45 -> 8.3397994 | G13: ='10'!$B$47 -> 10.042254 | H13: =G13-F13 -> 1.7024543
A14: =A13+1 -> 44906 | B14: ='Energy Schedule'!AH3 -> 0.0361 | C14: ='11'!$B$44 -> 249454.18 | D14: ='11'!$B$46 -> 308881.83 | E14: =D14-C14 -> 59427.653 | F14: ='11'!$B$45 -> 7.8967979 | G14: ='11'!$B$47 -> 9.7780579 | H14: =G14-F14 -> 1.88126
A15: =A14+1 -> 44907 | B15: ='Energy Schedule'!AK3 -> 0.0382 | C15: ='12'!$B$44 -> 167305.32 | D15: ='12'!$B$46 -> 206223.23 | E15: =D15-C15 -> 38917.911 | F15: ='12'!$B$45 -> 8.2426844 | G15: ='12'!$B$47 -> 10.160065 | H15: =G15-F15 -> 1.9173811
A16: =A15+1 -> 44908 | B16: ='Energy Schedule'!AN3 -> 0.0382 | C16: ='13'!$B$44 -> 144289.11 | D16: ='13'!$B$46 -> 179658.71 | E16: =D16-C16 -> 35369.598 | F16: ='13'!$B$45 -> 7.8906087 | G16: ='13'!$B$47 -> 9.8248341 | H16: =G16-F16 -> 1.9342254
A17: =A16+1 -> 44909 | B17: ='Energy Schedule'!AQ3 -> 0.0382 | C17: ='14'!$B$44 -> 130856.25 | D17: ='14'!$B$46 -> 161574.2 | E17: =D17-C17 -> 30717.945 | F17: ='14'!$B$45 -> 8.0289509 | G17: ='14'!$B$47 -> 9.9137128 | H17: =G17-F17 -> 1.8847619
A18: =A17+1 -> 44910 | B18: ='Energy Schedule'!AT3 -> 0.0382 | C18: ='15'!$B$44 -> 117683.51 | D18: ='15'!$B$46 -> 141214.94 | E18: =D18-C18 -> 23531.432 | F18: ='15'!$B$45 -> 8.2199272 | G18: ='15'!$B$47 -> 9.8635445 | H18: =G18-F18 -> 1.6436174
A19: =A18+1 -> 44911 | B19: ='Energy Schedule'!AW3 -> 0.0382 | C19: ='16'!$B$44 -> 61948.302 | D19: ='16'!$B$46 -> 73483.144 | E19: =D19-C19 -> 11534.843 | F19: ='16'!$B$45 -> 8.426665 | G19: ='16'!$B$47 -> 9.9957193 | H19: =G19-F19 -> 1.5690544
A20: =A19+1 -> 44912 | B20: ='Energy Schedule'!AZ3 -> 0.0382 | C20: ='17'!$B$44 -> 76854.303 | D20: ='17'!$B$46 -> 91670.816 | E20: =D20-C20 -> 14816.512 | F20: ='17'!$B$45 -> 8.2349863 | G20: ='17'!$B$47 -> 9.8225848 | H20: =G20-F20 -> 1.5875985
A21: =A20+1 -> 44913 | B21: ='Energy Schedule'!BC3 -> 0.0382 | C21: ='18'!$B$44 -> 146296.21 | D21: ='18'!$B$46 -> 170745.41 | E21: =D21-C21 -> 24449.191 | F21: ='18'!$B$45 -> 8.728679 | G21: ='18'!$B$47 -> 10.187426 | H21: =G21-F21 -> 1.4587468
A22: =A21+1 -> 44914 | B22: ='Energy Schedule'!BF3 -> 0.0418 | C22: ='19'!$B$44 -> 79100.029 | D22: ='19'!$B$46 -> 94414.957 | E22: =D22-C22 -> 15314.928 | F22: ='19'!$B$45 -> 8.4693234 | G22: ='19'!$B$47 -> 10.109109 | H22: =G22-F22 -> 1.6397855
A23: =A22+1 -> 44915 | B23: ='Energy Schedule'!BI3 -> 0.0418 | C23: ='20'!$B$44 -> 62783.116 | D23: ='20'!$B$46 -> 77197.019 | E23: =D23-C23 -> 14413.904 | F23: ='20'!$B$45 -> 8.2546832 | G23: ='20'!$B$47 -> 10.149814 | H23: =G23-F23 -> 1.8951307
A24: =A23+1 -> 44916 | B24: ='Energy Schedule'!BL3 -> 0.0418 | C24: ='21'!$B$44 -> 119433.33 | D24: ='21'!$B$46 -> 143004.82 | E24: =D24-C24 -> 23571.491 | F24: ='21'!$B$45 -> 8.2528633 | G24: ='21'!$B$47 -> 9.8816573 | H24: =G24-F24 -> 1.628794
A25: =A24+1 -> 44917 | B25: ='Energy Schedule'!BO3 -> 0.0418 | C25: ='22'!$B$44 -> 105283.13 | D25: ='22'!$B$46 -> 143706.33 | E25: =D25-C25 -> 38423.201 | F25: ='22'!$B$45 -> 7.2519131 | G25: ='22'!$B$47 -> 9.8985072 | H25: =G25-F25 -> 2.6465941
A26: =A25+1 -> 44918 | B26: ='Energy Schedule'!BR3 -> 0.0418 | C26: ='23'!$B$44 -> 81463.005 | D26: ='23'!$B$46 -> 101791.13 | E26: =D26-C26 -> 20328.12 | F26: ='23'!$B$45 -> 8.1007384 | G26: ='23'!$B$47 -> 10.122181 | H26: =G26-F26 -> 2.0214426
A27: =A26+1 -> 44919 | B27: ='Energy Schedule'!BU3 -> 0.0418 | C27: ='24'!$B$44 -> 116234.81 | D27: ='24'!$B$46 -> 142963.56 | E27: =D27-C27 -> 26728.749 | F27: ='24'!$B$45 -> 7.8049284 | G27: ='24'!$B$47 -> 9.5997089 | H27: =G27-F27 -> 1.7947806
A28: =A27+1 -> 44920 | B28: ='Energy Schedule'!BX3 -> 0.0418 | C28: ='25'!$B$44 -> 95686.671 | D28: ='25'!$B$46 -> 117306.87 | E28: =D28-C28 -> 21620.199 | F28: ='25'!$B$45 -> 7.9751256 | G28: ='25'!$B$47 -> 9.7770882 | H28: =G28-F28 -> 1.8019626
A29: =A28+1 -> 44921 | B29: ='Energy Schedule'!CA3 -> 0.0419 | C29: ='26'!$B$44 -> 46558.265 | D29: ='26'!$B$46 -> 60092.562 | E29: =D29-C29 -> 13534.297 | F29: ='26'!$B$45 -> 7.8978712 | G29: ='26'!$B$47 -> 10.19375 | H29: =G29-F29 -> 2.2958788
A30: =A29+1 -> 44922 | B30: ='Energy Schedule'!CD3 -> 0.0419 | C30: ='27'!$B$44 -> 49825.652 | D30: ='27'!$B$46 -> 61970.132 | E30: =D30-C30 -> 12144.48 | F30: ='27'!$B$45 -> 8.1950325 | G30: ='27'!$B$47 -> 10.192486 | H30: =G30-F30 -> 1.9974532
A31: =A30+1 -> 44923 | B31: ='Energy Schedule'!CG3 -> 0.0419 | C31: ='28'!$B$44 -> 60472.879 | D31: ='28'!$B$46 -> 76155.071 | E31: =D31-C31 -> 15682.192 | F31: ='28'!$B$45 -> 8.2259671 | G31: ='28'!$B$47 -> 10.359175 | H31: =G31-F31 -> 2.1332074
A32: =A31+1 -> 44924 | B32: ='Energy Schedule'!CJ3 -> 0.0419 | C32: ='29'!$B$44 -> 40971.879 | D32: ='29'!$B$46 -> 50735.66 | E32: =D32-C32 -> 9763.7802 | F32: ='29'!$B$45 -> 8.1673204 | G32: ='29'!$B$47 -> 10.113629 | H32: =G32-F32 -> 1.9463086
A33: =A32+1 -> 44925 | B33: ='Energy Schedule'!CM3 -> 0.0419 | C33: ='30'!$B$44 -> 57357.129 | D33: ='30'!$B$46 -> 70078.759 | E33: =D33-C33 -> 12721.63 | F33: ='30'!$B$45 -> 8.4968508 | G33: ='30'!$B$47 -> 10.381426 | H33: =G33-F33 -> 1.8845747
A34: =A33+1 -> 44926 | B34: ='Energy Schedule'!CP3 -> 0 | C34: ='31'!$B$44 -> 0 | D34: ='31'!$B$46 -> 0 | E34: =D34-C34 -> 0 | F34: ='31'!$B$45 -> #DIV/0! | G34: ='31'!$B$47 -> #DIV/0! | H34: =G34-F34 -> #DIV/0!
A35: Total | C35: =SUM(C4:C34) -> 3268940.7 | D35: =SUM(D4:D34) -> 4008576.5 | E35: =SUM(E4:E34) -> 739635.84 | F35: =AVERAGE(F4:F34) -> #DIV/0! | G35: =D35/#REF! -> #REF! | H35: =G35-F35 -> #REF!

Sheet Slot Wise Consolidate
A4: TNEB Slot | B4: IEX Allotment | C4: Consumption | D4: Balance
A5: C1 | B5: =SUM('01:31'!I6) -> 9683.9895 | C5: =SUM('01:31'!J6) -> 54900 | D5: =SUM('01:31'!K6) -> 45216.011
A6: C2 | B6: =SUM('01:31'!I7) -> 198750.18 | C6: =SUM('01:31'!J7) -> 274200 | D6: =SUM('01:31'!K7) -> 75449.823
A7: C4 | B7: =SUM('01:31'!I8) -> 112762.39 | C7: =SUM('01:31'!J8) -> 512800 | D7: =SUM('01:31'!K8) -> 400037.61
A8: C5 | B8: =SUM('01:31'!I9) -> 79826.454 | C8: =SUM('01:31'!J9) -> 104900 | D8: =SUM('01:31'!K9) -> 25073.546

Sheet Consumption Details
A2: Date | B2: C1 | C2: C2 | D2: C4 | E2: C5
A3: 44896 | B3: 1500 | C3: 9300 | D3: 18300 | E3: 5150
A4: =A3+1 -> 44897 | B4: 2050 | C4: 10000 | D4: 19250 | E4: 3650
A5: =A4+1 -> 44898 | B5: 1800 | C5: 10650 | D5: 20350 | E5: 3800
A6: =A5+1 -> 44899 | B6: 2050 | C6: 10600 | D6: 21850 | E6: 3750
A7: =A6+1 -> 44900 | B7: 1950 | C7: 9300 | D7: 19400 | E7: 3400
A8: =A7+1 -> 44901 | B8: 1850 | C8: 9050 | D8: 17550 | E8: 3350
A9: =A8+1 -> 44902 | B9: 1950 | C9: 9450 | D9: 17950 | E9: 3200
A10: =A9+1 -> 44903 | B10: 1800 | C10: 9100 | D10: 17800 | E10: 3400
A11: =A10+1 -> 44904 | B11: 1550 | C11: 8950 | D11: 18050 | E11: 3550
A12: =A11+1 -> 44905 | B12: 2300 | C12: 9350 | D12: 20250 | E12: 3650
A13: =A12+1 -> 44906 | B13: 2000 | C13: 10850 | D13: 20650 | E13: 3650
A14: =A13+1 -> 44907 | B14: 2700 | C14: 9150 | D14: 15600 | E14: 3200
A15: =A14+1 -> 44908 | B15: 1750 | C15: 9150 | D15: 18400 | E15: 3300
... A30: =A29+1 -> 44923 | B30: 1900 | C30: 10450 | D30: 20600 | E30: 4050
A31: =A30+1 -> 44924
A32: =A31+1 -> 44925
A33: =A32+1 -> 44926

Sheet 01
C2: G-DAM | D2: DAM | E2: RTM
A3: Unit Purchased in MWh | C3: 0 | D3: ='Energy Schedule'!D103 -> 12 | E3: ='Energy Schedule'!E103 -> 5.25
A4: IEX Payout | C4: ='Energy Schedule'!C5 -> 0 | D4: ='Energy Schedule'!D5 -> 45070.355 | E4: ='Energy Schedule'!E5 -> 3103.11
A5: Total Units in kWh | C5: =C3*1000 -> 0 | D5: =D3*1000 -> 12000 | E5: =E3*1000 -> 5250 | I5: IEX Delivered | J5: Consumption | K5: Balance
A6: CTU | B6: ='Energy Schedule'!D3 -> 0.0343 | C6: =C5-(C5*$B$6) -> 0 | D6: =D5-(D5*$B$6) -> 11588.4 | E6: =E5-(E5*$B$6) -> 5069.925 | H6: C1 | I6: =D33 -> 0 | J6: ='Consumption Details'!$B3 -> 1500 | K6: =J6-I6 -> 1500
A7: STU | B7: ='TNEB Charges'!B1 -> 0.0234 | C7: =C6-(C6*$B$7) -> 0 | D7: =D6-(D6*$B$7) -> 11317.231 | E7: =E6-(E6*$B$7) -> 4951.2888 | H7: C2 | I7: =D34 -> 6935.3409 | J7: ='Consumption Details'!$C3 -> 9300 | K7: =J7-I7 -> 2364.6591
A8: Discom Losses | B8: ='TNEB Charges'!B2 -> 0.0195 | C8: =C7-(C7*$B$8) -> 0 | D8: =D7-(D7*$B$8) -> 11096.545 | E8: =E7-(E7*$B$8) -> 4854.7386 | H8: C4 | I8: =D35 -> 3467.6704 | J8: ='Consumption Details'!$D3 -> 18300 | K8: =J8-I8 -> 14832.33
A9: Delivered @ Bus | C9: =C8 -> 0 | D9: =D8 -> 11096.545 | E9: =E8 -> 4854.7386 | H9: C5 | I9: =D36 -> 5548.2727 | J9: ='Consumption Details'!$E3 -> 5150 | K9: =J9-I9 -> -398.27271
A10: IEX Payout / Unit | C10: =C4/C9 -> #DIV/0! | D10: =D4/D9 -> 4.0616564 | E10: =E4/E9 -> 0.63919198 | K10: =J10-I10 -> 0
A11: IEX Transaction Charges | B11: ='TNEB Charges'!B5 -> 0.02 | C11: =(C3*1000*$B$11)+(C3*1000*$B$11*18%) -> 0 | D11: =(D3*1000*$B$11)+(D3*1000*$B$11*18%) -> 283.2 | E11: =(E3*1000*$B$11)+(E3*1000*$B$11*18%) -> 123.9
A12: NLDC Application fee | C12: ='Energy Schedule'!C$6 -> 0 | D12: ='Energy Schedule'!D$6 -> 9.09 | E12: ='Energy Schedule'!E$6 -> 13.7
A13: CTU Transmission Charges | B13: ='TNEB Charges'!B7 -> 457.6 | C13: =C3*$B$13 -> 0 | D13: =D3*$B$13 -> 5491.2 | E13: =E3*$B$13 -> 2402.4
A14: NLDC Sched & Oprn Charges | B14: ='TNEB Charges'!B8 -> 1 | C14: =C3*$B$14 -> 0 | D14: =D3*$B$14 -> 12 | E14: =E3*$B$14 -> 5.25
A15: STU Transmission Charges | B15: ='TNEB Charges'!B9 -> 260 | C15: =C3*$B$15 -> 0 | D15: =D3*$B$15 -> 3120 | E15: =E3*$B$15 -> 1365
A16: STU Scheduling | B16: ='TNEB Charges'!B10 -> 170 | C16: =IF(C3>0,$B$16,0) -> 0 | D16: =IF(D3>0,$B$16,0) -> 170 | E16: =IF(E3>0,$B$16,0) -> 170
A17: STU System Operating Charge | B17: ='TNEB Charges'!B11 -> 33.74 | C17: =C3*$B$17/24 -> 0 | D17: =D3*$B$17/24 -> 16.87 | E17: =E3*$B$17/24 -> 7.380625
A18: TPTCL Margin | B18: ='TNEB Charges'!B12 -> 0.02 | C18: =C3*$B$18*1000 -> 0 | D18: =D3*$B$18*1000 -> 240 | E18: =E3*$B$18*1000 -> 105
A19: CSS | B19: ='TNEB Charges'!B13 -> 1.99 | C19: =C9*$B$19 -> 0 | D19: =D9*$B$19 -> 22082.125 | E19: =E9*$B$19 -> 9660.9299
A20: ASC | B20: ='TNEB Charges'!B14 -> 0 | C20: =C9*$B$20 -> 0 | D20: =D9*$B$20 -> 0 | E20: =E9*$B$20 -> 0
A21: Wheeling Charges | B21: ='TNEB Charges'!B15 -> 1.04 | C21: =C8*$B$21 -> 0 | D21: =D8*$B$21 -> 11540.407 | E21: =E8*$B$21 -> 5048.9282
A22: E-Tax | B22: ='TNEB Charges'!B16 -> 0 | C22: =C9*$B$22 -> 0 | D22: =D9*$B$22 -> 0 | E22: =E9*$B$22 -> 0
A23: Solar RPO Charges | B23: ='TNEB Charges'!B17 -> 0.12 | C23: 0 | D23: =D9*$B$23*10.5% -> 139.81647 | E23: =E9*$B$23*10.5% -> 61.169707
A24: Non-Solar RPO Charges | B24: ='TNEB Charges'!B18 -> 0.12 | C24: 0 | D24: =D9*$B$24*10.5% -> 139.81647 | E24: =E9*$B$24*10.5% -> 61.169707
A25: Total Statutory Charges | C25: =SUM(C11:C24) -> 0 | D25: =SUM(D11:D24) -> 43244.526 | E25: =SUM(E11:E24) -> 19024.828
C26: =C25/C9 -> #DIV/0! | D26: =D25/D9 -> 3.8971161 | E26: =E25/E9 -> 3.9188161
A27: Total Cost incurred in IEX Purchase | C27: =C4+C25 -> 0 | D27: =D4+D25 -> 88314.881 | E27: =E4+E25 -> 22127.938
A28: Cost per Unit incurred | C28: =C27/C9 -> #DIV/0! | D28: =D27/D9 -> 7.9587725 | E28: =E27/E9 -> 4.5580081
I29: Slot | J29: Morning peak | K29: Evening peak | L29: Normal hour | M29: Normal hour | N29: Night Hour | O29: RTC
A30: EQUIVALENT EB PRICE TO THE UNITS PURCHASED FROM IEX | J30: C1 | K30: C2 | L30: C4 | M30: C5 | N30: C24
A31: DAM | I31: TNEB Tariff | J31: =$L$31+($L$31*25%) -> 10.625 | K31: =$L$31+($L$31*25%) -> 10.625 | L31: 8.5 | M31: =$L$31-($L$31*5%) -> 8.075 | N31: 6.03 | O31: =AVERAGE(J31:M31) -> 9.45625
A32: Slot | B32: Price | C32: Purchase | D32: Delivered | E32: EB Cost | I32: E-Tax | J32: 0.05 | K32: 0.05 | L32: 0.05 | M32: 0.05 | N32: 0.05 | O32: 0.05
A33: C1 | B33: =J33 -> 11.15625 | C33: =J39+J46+J53 -> 0 | D33: =M39+M46+M53 -> 0 | E33: =D33*B33 -> 0 | I33: Total price/Unit | J33: =J31+(J31*J32) -> 11.15625 | K33: =K31+(K31*K32) -> 11.15625 | L33: =L31+(L31*L32) -> 8.925 | M33: =M31+(M31*M32) -> 8.47875 | N33: =N31+(N31*N32) -> 6.3315 | O33: =AVERAGE(J33:M33) -> 9.9290625
A34: C2 | B34: =K33 -> 11.15625 | C34: =J41+J48+J55 -> 7500 | D34: =M41+M48+M55 -> 6935.3409 | E34: =D34*B34 -> 77372.397
A35: C4 | B35: =L33 -> 8.925 | C35: =J38+J40+J45+J47+J52+J54 -> 3750 | D35: =M38+M40+M45+M47+M52+M54 -> 3467.6704 | E35: =D35*B35 -> 30948.959
A36: C5 | B36: =M33 -> 8.47875 | C36: =J37+J42+J44+J49+J51+J56 -> 6000 | D36: =M37+M42+M44+M49+M51+M56 -> 5548.2727 | E36: =D36*B36 -> 47042.417 | I36: GDAM
A37: Total | C37: =SUM(C33:C36) -> 17250 | D37: =SUM(D33:D36) -> 15951.284 | E37: =SUM(E33:E36) -> 155363.77 | H37: C5 | I37: =SUM('Energy Schedule'!C7:C26)/4 -> 0 | J37: =I37*1000 -> 0 | K37: =J37-(J37*$B$6) -> 0 | L37: =K37-(K37*$B$7) -> 0 | M37: =L37-(L37*$B$8) -> 0
H38: C4 | I38: =SUM('Energy Schedule'!C27:C30)/4 -> 0 | J38: =I38*1000 -> 0 | K38: =J38-(J38*$B$6) -> 0 | L38: =K38-(K38*$B$7) -> 0 | M38: =L38-(L38*$B$8) -> 0
H39: C1 | I39: =SUM('Energy Schedule'!C31:C46)/4 -> 0 | J39: =I39*1000 -> 0 | K39: =J39-(J39*$B$6) -> 0 | L39: =K39-(K39*$B$7) -> 0 | M39: =L39-(L39*$B$8) -> 0
H40: C4 | I40: =SUM('Energy Schedule'!C47:C78)/4 -> 0 | J40: =I40*1000 -> 0 | K40: =J40-(J40*$B$6) -> 0 | L40: =K40-(K40*$B$7) -> 0 | M40: =L40-(L40*$B$8) -> 0
H41: C2 | I41: =SUM('Energy Schedule'!C79:C94)/4 -> 0 | J41: =I41*1000 -> 0 | K41: =J41-(J41*$B$6) -> 0 | L41: =K41-(K41*$B$7) -> 0 | M41: =L41-(L41*$B$8) -> 0
A42: Total Purchase | B42: =C37 -> 17250 | C42: C1 | D42: 700 | H42: C5 | I42: =SUM('Energy Schedule'!C95:C102)/4 -> 0 | J42: =I42*1000 -> 0 | K42: =J42-(J42*$B$6) -> 0 | L42: =K42-(K42*$B$7) -> 0 | M42: =L42-(L42*$B$8) -> 0
A43: Delivered | B43: =D37 -> 15951.284 | C43: C2 | D43: 7850 | I43: DAM
A44: IEX Price | B44: =C27+D27+E27 -> 110442.82 | C44: C3 | D44: 2000 | H44: C5 | I44: =SUM('Energy Schedule'!D7:D26)/4 -> 5 | J44: =I44*1000 -> 5000 | K44: =J44-(J44*$B$6) -> 4828.5 | L44: =K44-(K44*$B$7) -> 4715.5131 | M44: =L44-(L44*$B$8) -> 4623.5606
A45: IEX Price / Unit | B45: =B44/B43 -> 6.9237573 | C45: C4 | D45: 20100 | H45: C4 | I45: =SUM('Energy Schedule'!D27:D30)/4 -> 0.75 | J45: =I45*1000 -> 750 | K45: =J45-(J45*$B$6) -> 724.275 | L45: =K45-(K45*$B$7) -> 707.32696 | M45: =L45-(L45*$B$8) -> 693.53409
A46: EB Price | B46: =E37 -> 155363.77 | C46: C5 | D46: 2950 | H46: C1 | I46: =SUM('Energy Schedule'!D31:D46)/4 -> 0 | J46: =I46*1000 -> 0 | K46: =J46-(J46*$B$6) -> 0 | L46: =K46-(K46*$B$7) -> 0 | M46: =L46-(L46*$B$8) -> 0
A47: EB Price / Unit | B47: =B46/B43 -> 9.7398913 | C47: Total | D47: =SUM(D42:D46) -> 33600 | H47: C4 | I47: =SUM('Energy Schedule'!D47:D78)/4 -> 0 | J47: =I47*1000 -> 0 | K47: =J47-(J47*$B$6) -> 0 | L47: =K47-(K47*$B$7) -> 0 | M47: =L47-(L47*$B$8) -> 0
A48: Cost Saving | B48: =B46-B44 -> 44920.954 | H48: C2 | I48: =SUM('Energy Schedule'!D79:D94)/4 -> 5.25 | J48: =I48*1000 -> 5250 | K48: =J48-(J48*$B$6) -> 5069.925 | L48: =K48-(K48*$B$7) -> 4951.2888 | M48: =L48-(L48*$B$8) -> 4854.7386
A49: Cost Savings Unit | B49: =B47-B45 -> 2.8161341 | H49: C5 | I49: =SUM('Energy Schedule'!D95:D102)/4 -> 1 | J49: =I49*1000 -> 1000 | K49: =J49-(J49*$B$6) -> 965.7 | L49: =K49-(K49*$B$7) -> 943.10262 | M49: =L49-(L49*$B$8) -> 924.71212
I50: RTM
H51: C5 | I51: =SUM('Energy Schedule'!E7:E26)/4 -> 0 | J51: =I51*1000 -> 0 | K51: =J51-(J51*$B$6) -> 0 | L51: =K51-(K51*$B$7) -> 0 | M51: =L51-(L51*$B$8) -> 0
H52: C4 | I52: =SUM('Energy Schedule'!E27:E30)/4 -> 0 | J52: =I52*1000 -> 0 | K52: =J52-(J52*$B$6) -> 0 | L52: =K52-(K52*$B$7) -> 0 | M52: =L52-(L52*$B$8) -> 0
H53: C1 | I53: =SUM('Energy Schedule'!E31:E46)/4 -> 0 | J53: =I53*1000 -> 0 | K53: =J53-(J53*$B$6) -> 0 | L53: =K53-(K53*$B$7) -> 0 | M53: =L53-(L53*$B$8) -> 0
H54: C4 | I54: =SUM('Energy Schedule'!E47:E78)/4 -> 3 | J54: =I54*1000 -> 3000 | K54: =J54-(J54*$B$6) -> 2897.1 | L54: =K54-(K54*$B$7) -> 2829.3079 | M54: =L54-(L54*$B$8) -> 2774.1364
H55: C2 | I55: =SUM('Energy Schedule'!E79:E94)/4 -> 2.25 | J55: =I55*1000 -> 2250 | K55: =J55-(J55*$B$6) -> 2172.825 | L55: =K55-(K55*$B$7) -> 2121.9809 | M55: =L55-(L55*$B$8) -> 2080.6023
H56: C5 | I56: =SUM('Energy Schedule'!E95:E102)/4 -> 0 | J56: =I56*1000 -> 0 | K56: =J56-(J56*$B$6) -> 0 | L56: =K56-(K56*$B$7) -> 0 | M56: =L56-(L56*$B$8) -> 0

Sheet 02
C2: G-DAM | D2: DAM | E2: RTM
A3: Unit Purchased in MWh | C3: ='Energy Schedule'!F103 -> 0 | D3: ='Energy Schedule'!G103 -> 12.5 | E3: ='Energy Schedule'!H103 -> 0
A4: IEX Payout | C4: ='Energy Schedule'!F5 -> 0 | D4: ='Energy Schedule'!G$5 -> 46896.22 | E4: ='Energy Schedule'!H$5 -> 0
A5: Total Units in kWh | C5: =C3*1000 -> 0 | D5: =D3*1000 -> 12500 | E5: =E3*1000 -> 0 | I5: IEX Delivered | J5: Consumption | K5: Balance
A6: CTU | B6: ='Energy Schedule'!G3 -> 0.0343 | C6: =C5-(C5*$B$6) -> 0 | D6: =D5-(D5*$B$6) -> 12071.25 | E6: =E5-(E5*$B$6) -> 0 | H6: C1 | I6: =D33 -> 0 | J6: ='Consumption Details'!$B4 -> 2050 | K6: =J6-I6 -> 2050
A7: STU | B7: ='TNEB Charges'!B1 -> 0.0234 | C7: =C6-(C6*$B$7) -> 0 | D7: =D6-(D6*$B$7) -> 11788.783 | E7: =E6-(E6*$B$7) -> 0 | H7: C2 | I7: =D34 -> 5548.2727 | J7: ='Consumption Details'!$C4 -> 10000 | K7: =J7-I7 -> 4451.7273
A8: Discom Losses | B8: ='TNEB Charges'!B2 -> 0.0195 | C8: =C7-(C7*$B$8) -> 0 | D8: =D7-(D7*$B$8) -> 11558.901 | E8: =E7-(E7*$B$8) -> 0 | H8: C4 | I8: =D35 -> 924.71212 | J8: ='Consumption Details'!$D4 -> 19250 | K8: =J8-I8 -> 18325.288
A9: Delivered @ Bus | B9: ='TNEB Charges'!B3 -> 0 | C9: =C8 -> 0 | D9: =D8 -> 11558.901 | E9: =E8 -> 0 | H9: C5 | I9: =D36 -> 5085.9167 | J9: ='Consumption Details'!$E4 -> 3650 | K9: =J9-I9 -> -1435.9167
A10: IEX Payout / Unit | B10: ='TNEB Charges'!B4 -> 0 | C10: =C4/C9 -> #DIV/0! | D10: =D4/D9 -> 4.057152 | E10: =E4/E9 -> #DIV/0!
A11: IEX Transaction Charges | B11: ='TNEB Charges'!B5 -> 0.02 | C11: =(C3*1000*$B$11)+(C3*1000*$B$11*18%) -> 0 | D11: =(D3*1000*$B$11)+(D3*1000*$B$11*18%) -> 295 | E11: =(E3*1000*$B$11)+(E3*1000*$B$11*18%) -> 0
A12: NLDC Application fee | B12: ='TNEB Charges'!B6 -> 0 | C12: ='Energy Schedule'!F$6 -> 0 | D12: ='Energy Schedule'!G$6 -> 8.91 | E12: ='Energy Schedule'!H$6 -> 0
A13: CTU Transmission Charges | B13: ='TNEB Charges'!B7 -> 457.6 | C13: =C3*$B$13 -> 0 | D13: =D3*$B$13 -> 5720 | E13: =E3*$B$13 -> 0
A14: NLDC Sched & Oprn Charges | B14: ='TNEB Charges'!B8 -> 1 | C14: =C3*$B$14 -> 0 | D14: =D3*$B$14 -> 12.5 | E14: =E3*$B$14 -> 0
A15: STU Transmission Charges | B15: ='TNEB Charges'!B9 -> 260 | C15: =C3*$B$15 -> 0 | D15: =D3*$B$15 -> 3250 | E15: =E3*$B$15 -> 0
A16: STU Scheduling | B16: ='TNEB Charges'!B10 -> 170 | C16: =IF(C3>0,$B$16,0) -> 0 | D16: =IF(D3>0,$B$16,0) -> 170 | E16: =IF(E3>0,$B$16,0) -> 0
A17: STU System Operating Charge | B17: ='TNEB Charges'!B11 -> 33.74 | C17: =C3*$B$17/24 -> 0 | D17: =D3*$B$17/24 -> 17.572917 | E17: =E3*$B$17/24 -> 0
A18: TPTCL Margin | B18: ='TNEB Charges'!B12 -> 0.02 | C18: =C3*$B$18*1000 -> 0 | D18: =D3*$B$18*1000 -> 250 | E18: =E3*$B$18*1000 -> 0
A19: CSS | B19: ='TNEB Charges'!B13 -> 1.99 | C19: =C9*$B$19 -> 0 | D19: =D9*$B$19 -> 23002.214 | E19: =E9*$B$19 -> 0
A20: ASC | B20: ='TNEB Charges'!B14 -> 0 | C20: =C9*$B$20 -> 0 | D20: =D9*$B$20 -> 0 | E20: =E9*$B$20 -> 0
A21: Wheeling Charges | B21: ='TNEB Charges'!B15 -> 1.04 | C21: =C8*$B$21 -> 0 | D21: =D8*$B$21 -> 12021.258 | E21: =E8*$B$21 -> 0
A22: E-Tax | B22: ='TNEB Charges'!B16 -> 0 | C22: =C9*$B$22 -> 0 | D22: =D9*$B$22 -> 0 | E22: =E9*$B$22 -> 0
A23: Solar RPO Charges | B23: ='TNEB Charges'!B17 -> 0.12 | C23: 0 | D23: =D9*$B$23*10.5% -> 145.64216 | E23: =E9*$B$23*10.5% -> 0
A24: Non-Solar RPO Charges | B24: ='TNEB Charges'!B18 -> 0.12 | C24: 0 | D24: =D9*$B$24*10.5% -> 145.64216 | E24: =E9*$B$24*10.5% -> 0
A25: Total Statutory Charges | C25: =SUM(C11:C24) -> 0 | D25: =SUM(D11:D24) -> 45038.739 | E25: =SUM(E11:E24) -> 0
C26: =C25/C9 -> #DIV/0! | D26: =D25/D9 -> 3.8964549 | E26: =E25/E9 -> #DIV/0!
A27: Total Cost incurred in IEX Purchase | C27: =C4+C25 -> 0 | D27: =D4+D25 -> 91934.959 | E27: =E4+E25 -> 0
A28: Cost per Unit incurred | C28: =C27/C9 -> #DIV/0! | D28: =D27/D9 -> 7.9536069 | E28: =E27/E9 -> #DIV/0!
I29: Slot | J29: Morning peak | K29: Evening peak | L29: Normal hour | M29: Normal hour | N29: Night Hour | O29: RTC
A30: EQUIVALENT EB PRICE TO THE UNITS PURCHASED FROM IEX | J30: C1 | K30: C2 | L30: C4 | M30: C5 | N30: C24
A31: DAM | I31: TNEB Tariff | J31: =$L$31+($L$31*25%) -> 10.625 | K31: =$L$31+($L$31*25%) -> 10.625 | L31: 8.5 | M31: =$L$31-($L$31*5%) -> 8.075 | N31: 6.03 | O31: =AVERAGE(J31:M31) -> 9.45625
A32: Slot | B32: Price | C32: Purchase | D32: Delivered | E32: EB Cost | I32: E-Tax | J32: 0.05 | K32: 0.05 | L32: 0.05 | M32: 0.05 | N32: 0.05 | O32: 0.05
A33: C1 | B33: =J33 -> 11.15625 | C33: =J39+J46+J53 -> 0 | D33: =M39+M46+M53 -> 0 | E33: =D33*B33 -> 0 | I33: Total price/Unit | J33: =J31+(J31*J32) -> 11.15625 | K33: =K31+(K31*K32) -> 11.15625 | L33: =L31+(L31*L32) -> 8.925 | M33: =M31+(M31*M32) -> 8.47875 | N33: =N31+(N31*N32) -> 6.3315 | O33: =AVERAGE(J33:M33) -> 9.9290625
A34: C2 | B34: =K33 -> 11.15625 | C34: =J41+J48+J55 -> 6000 | D34: =M41+M48+M55 -> 5548.2727 | E34: =D34*B34 -> 61897.917
A35: C4 | B35: =L33 -> 8.925 | C35: =J38+J40+J45+J47+J52+J54 -> 1000 | D35: =M38+M40+M45+M47+M52+M54 -> 924.71212 | E35: =D35*B35 -> 8253.0557
A36: C5 | B36: =M33 -> 8.47875 | C36: =J37+J42+J44+J49+J51+J56 -> 5500 | D36: =M37+M42+M44+M49+M51+M56 -> 5085.9167 | E36: =D36*B36 -> 43122.216 | I36: GDAM
A37: Total | C37: =SUM(C33:C36) -> 12500 | D37: =SUM(D33:D36) -> 11558.901 | E37: =SUM(E33:E36) -> 113273.19 | H37: C5 | I37: =SUM('Energy Schedule'!F7:F26)/4 -> 0 | J37: =I37*1000 -> 0 | K37: =J37-(J37*$B$6) -> 0 | L37: =K37-(K37*$B$7) -> 0 | M37: =L37-(L37*$B$8) -> 0
H38: C4 | I38: =SUM('Energy Schedule'!F27:F30)/4 -> 0 | J38: =I38*1000 -> 0 | K38: =J38-(J38*$B$6) -> 0 | L38: =K38-(K38*$B$7) -> 0 | M38: =L38-(L38*$B$8) -> 0
H39: C1 | I39: =SUM('Energy Schedule'!F31:F46)/4 -> 0 | J39: =I39*1000 -> 0 | K39: =J39-(J39*$B$6) -> 0 | L39: =K39-(K39*$B$7) -> 0 | M39: =L39-(L39*$B$8) -> 0
H40: C4 | I40: =SUM('Energy Schedule'!F47:F78)/4 -> 0 | J40: =I40*1000 -> 0 | K40: =J40-(J40*$B$6) -> 0 | L40: =K40-(K40*$B$7) -> 0 | M40: =L40-(L40*$B$8) -> 0
H41: C2 | I41: =SUM('Energy Schedule'!F79:F94)/4 -> 0 | J41: =I41*1000 -> 0 | K41: =J41-(J41*$B$6) -> 0 | L41: =K41-(K41*$B$7) -> 0 | M41: =L41-(L41*$B$8) -> 0
A42: Total Purchase | B42: =C37 -> 12500 | C42: C1 | D42: 700 | H42: C5 | I42: =SUM('Energy Schedule'!F95:F102)/4 -> 0 | J42: =I42*1000 -> 0 | K42: =J42-(J42*$B$6) -> 0 | L42: =K42-(K42*$B$7) -> 0 | M42: =L42-(L42*$B$8) -> 0
A43: Delivered | B43: =D37 -> 11558.901 | C43: C2 | D43: 7850 | I43: DAM
A44: IEX Price | B44: =C27+D27+E27 -> 91934.959 | C44: C3 | D44: 2000 | H44: C5 | I44: =SUM('Energy Schedule'!G7:G26)/4 -> 5 | J44: =I44*1000 -> 5000 | K44: =J44-(J44*$B$6) -> 4828.5 | L44: =K44-(K44*$B$7) -> 4715.5131 | M44: =L44-(L44*$B$8) -> 4623.5606
A45: IEX Price / Unit | B45: =B44/B43 -> 7.9536069 | C45: C4 | D45: 20100 | H45: C4 | I45: =SUM('Energy Schedule'!G27:G30)/4 -> 1 | J45: =I45*1000 -> 1000 | K45: =J45-(J45*$B$6) -> 965.7 | L45: =K45-(K45*$B$7) -> 943.10262 | M45: =L45-(L45*$B$8) -> 924.71212
A46: EB Price | B46: =E37 -> 113273.19 | C46: C5 | D46: 2950 | H46: C1 | I46: =SUM('Energy Schedule'!G31:G46)/4 -> 0 | J46: =I46*1000 -> 0 | K46: =J46-(J46*$B$6) -> 0 | L46: =K46-(K46*$B$7) -> 0 | M46: =L46-(L46*$B$8) -> 0
A47: EB Price / Unit | B47: =B46/B43 -> 9.79965 | C47: Total | D47: =SUM(D42:D46) -> 33600 | H47: C4 | I47: =SUM('Energy Schedule'!G47:G78)/4 -> 0 | J47: =I47*1000 -> 0 | K47: =J47-(J47*$B$6) -> 0 | L47: =K47-(K47*$B$7) -> 0 | M47: =L47-(L47*$B$8) -> 0
A48: Cost Saving | B48: =B46-B44 -> 21338.23 | H48: C2 | I48: =SUM('Energy Schedule'!G79:G94)/4 -> 6 | J48: =I48*1000 -> 6000 | K48: =J48-(J48*$B$6) -> 5794.2 | L48: =K48-(K48*$B$7) -> 5658.6157 | M48: =L48-(L48*$B$8) -> 5548.2727
A49: Cost Savings Unit | B49: =B47-B45 -> 1.8460431 | H49: C5 | I49: =SUM('Energy Schedule'!G95:G102)/4 -> 0.5 | J49: =I49*1000 -> 500 | K49: =J49-(J49*$B$6) -> 482.85 | L49: =K49-(K49*$B$7) -> 471.55131 | M49: =L49-(L49*$B$8) -> 462.35606
I50: RTM
H51: C5 | I51: =SUM('Energy Schedule'!H7:H26)/4 -> 0 | J51: =I51*1000 -> 0 | K51: =J51-(J51*$B$6) -> 0 | L51: =K51-(K51*$B$7) -> 0 | M51: =L51-(L51*$B$8) -> 0
H52: C4 | I52: =SUM('Energy Schedule'!H27:H30)/4 -> 0 | J52: =I52*1000 -> 0 | K52: =J52-(J52*$B$6) -> 0 | L52: =K52-(K52*$B$7) -> 0 | M52: =L52-(L52*$B$8) -> 0
H53: C1 | I53: =SUM('Energy Schedule'!H31:H46)/4 -> 0 | J53: =I53*1000 -> 0 | K53: =J53-(J53*$B$6) -> 0 | L53: =K53-(K53*$B$7) -> 0 | M53: =L53-(L53*$B$8) -> 0
H54: C4 | I54: =SUM('Energy Schedule'!H47:H78)/4 -> 0 | J54: =I54*1000 -> 0 | K54: =J54-(J54*$B$6) -> 0 | L54: =K54-(K54*$B$7) -> 0 | M54: =L54-(L54*$B$8) -> 0
H55: C2 | I55: =SUM('Energy Schedule'!H79:H94)/4 -> 0 | J55: =I55*1000 -> 0 | K55: =J55-(J55*$B$6) -> 0 | L55: =K55-(K55*$B$7) -> 0 | M55: =L55-(L55*$B$8) -> 0
H56: C5 | I56: =SUM('Energy Schedule'!H95:H102)/4 -> 0 | J56: =I56*1000 -> 0 | K56: =J56-(J56*$B$6) -> 0 | L56: =K56-(K56*$B$7) -> 0 | M56: =L56-(L56*$B$8) -> 0

Sheet 03
C2: G-DAM | D2: DAM | E2: RTM
A3: Unit Purchased in MWh | C3: ='Energy Schedule'!I$103 -> 0 | D3: ='Energy Schedule'!J$103 -> 9.25 | E3: ='Energy Schedule'!K$103 -> 3.6275
A4: IEX Payout | C4: ='Energy Schedule'!I$5 -> 0 | D4: ='Energy Schedule'!J$5 -> 38325.914 | E4: ='Energy Schedule'!K$5 -> 14307.76
A5: Total Units in kWh | C5: =C3*1000 -> 0 | D5: =D3*1000 -> 9250 | E5: =E3*1000 -> 3627.5 | I5: IEX Delivered | J5: Consumption | K5: Balance
A6: CTU | B6: ='Energy Schedule'!J3 -> 0.0343 | C6: =C5-(C5*$B$6) -> 0 | D6: =D5-(D5*$B$6) -> 8932.725 | E6: =E5-(E5*$B$6) -> 3503.0768 | H6: C1 | I6: =D33 -> 462.35606 | J6: ='Consumption Details'!$B5 -> 1800 | K6: =J6-I6 -> 1337.6439
A7: STU | B7: ='TNEB Charges'!B1 -> 0.0234 | C7: =C6-(C6*$B$7) -> 0 | D7: =D6-(D6*$B$7) -> 8723.6992 | E7: =E6-(E6*$B$7) -> 3421.1048 | H7: C2 | I7: =D34 -> 7053.2417 | J7: ='Consumption Details'!$C5 -> 10650 | K7: =J7-I7 -> 3596.7583
A8: Discom Losses | B8: ='TNEB Charges'!B2 -> 0.0195 | C8: =C7-(C7*$B$8) -> 0 | D8: =D7-(D7*$B$8) -> 8553.5871 | E8: =E7-(E7*$B$8) -> 3354.3932 | H8: C4 | I8: =D35 -> 2080.6023 | J8: ='Consumption Details'!$D5 -> 20350 | K8: =J8-I8 -> 18269.398
A9: Delivered @ Bus | B9: ='TNEB Charges'!B3 -> 0 | C9: =C8 -> 0 | D9: =D8 -> 8553.5871 | E9: =E8 -> 3354.3932 | H9: C5 | I9: =D36 -> 2311.7803 | J9: ='Consumption Details'!$E5 -> 3800 | K9: =J9-I9 -> 1488.2197
A10: IEX Payout / Unit | B10: ='TNEB Charges'!B4 -> 0 | C10: =C4/C9 -> #DIV/0! | D10: =D4/D9 -> 4.4806833 | E10: =E4/E9 -> 4.2653795
A11: IEX Transaction Charges | B11: ='TNEB Charges'!B5 -> 0.02 | C11: =(C3*1000*$B$11)+(C3*1000*$B$11*18%) -> 0 | D11: =(D3*1000*$B$11)+(D3*1000*$B$11*18%) -> 218.3 | E11: =(E3*1000*$B$11)+(E3*1000*$B$11*18%) -> 85.609
A12: NLDC Application fee | B12: ='TNEB Charges'!B6 -> 0 | C12: ='Energy Schedule'!I$6 -> 0 | D12: ='Energy Schedule'!J$6 -> 8.99 | E12: ='Energy Schedule'!K$6 -> 13.19
A13: CTU Transmission Charges | B13: ='TNEB Charges'!B7 -> 457.6 | C13: =C3*$B$13 -> 0 | D13: =D3*$B$13 -> 4232.8 | E13: =E3*$B$13 -> 1659.944
A14: NLDC Sched & Oprn Charges | B14: ='TNEB Charges'!B8 -> 1 | C14: =C3*$B$14 -> 0 | D14: =D3*$B$14 -> 9.25 | E14: =E3*$B$14 -> 3.6275
A15: STU Transmission Charges | B15: ='TNEB Charges'!B9 -> 260 | C15: =C3*$B$15 -> 0 | D15: =D3*$B$15 -> 2405 | E15: =E3*$B$15 -> 943.15
A16: STU Scheduling | B16: ='TNEB Charges'!B10 -> 170 | C16: =IF(C3>0,$B$16,0) -> 0 | D16: =IF(D3>0,$B$16,0) -> 170 | E16: =IF(E3>0,$B$16,0) -> 170
A17: STU System Operating Charge | B17: ='TNEB Charges'!B11 -> 33.74 | C17: =C3*$B$17/24 -> 0 | D17: =D3*$B$17/24 -> 13.003958 | E17: =E3*$B$17/24 -> 5.0996604
A18: TPTCL Margin | B18: ='TNEB Charges'!B12 -> 0.02 | C18: =C3*$B$18*1000 -> 0 | D18: =D3*$B$18*1000 -> 185 | E18: =E3*$B$18*1000 -> 72.55
A19: CSS | B19: ='TNEB Charges'!B13 -> 1.99 | C19: =C9*$B$19 -> 0 | D19: =D9*$B$19 -> 17021.638 | E19: =E9*$B$19 -> 6675.2425
A20: ASC | B20: ='TNEB Charges'!B14 -> 0 | C20: =C9*$B$20 -> 0 | D20: =D9*$B$20 -> 0 | E20: =E9*$B$20 -> 0
A21: Wheeling Charges | B21: ='TNEB Charges'!B15 -> 1.04 | C21: =C8*$B$21 -> 0 | D21: =D8*$B$21 -> 8895.7306 | E21: =E8*$B$21 -> 3488.5689
A22: E-Tax | B22: ='TNEB Charges'!B16 -> 0 | C22: =C9*$B$22 -> 0 | D22: =D9*$B$22 -> 0 | E22: =E9*$B$22 -> 0
A23: Solar RPO Charges | B23: ='TNEB Charges'!B17 -> 0.12 | C23: 0 | D23: =D9*$B$23*10.5% -> 107.7752 | E23: =E9*$B$23*10.5% -> 42.265354
A24: Non-Solar RPO Charges | B24: ='TNEB Charges'!B18 -> 0.12 | C24: 0 | D24: =D9*$B$24*10.5% -> 107.7752 | E24: =E9*$B$24*10.5% -> 42.265354
A25: Total Statutory Charges | C25: =SUM(C11:C24) -> 0 | D25: =SUM(D11:D24) -> 33375.263 | E25: =SUM(E11:E24) -> 13201.512
C26: =C25/C9 -> #DIV/0! | D26: =D25/D9 -> 3.9019025 | E26: =E25/E9 -> 3.9355888
A27: Total Cost incurred in IEX Purchase | C27: =C4+C25 -> 0 | D27: =D4+D25 -> 71701.178 | E27: =E4+E25 -> 27509.272
A28: Cost per Unit incurred | C28: =C27/C9 -> #DIV/0! | D28: =D27/D9 -> 8.3825858 | E28: =E27/E9 -> 8.2009683
I29: Slot | J29: Morning peak | K29: Evening peak | L29: Normal hour | M29: Normal hour | N29: Night Hour | O29: RTC
A30: EQUIVALENT EB PRICE TO THE UNITS PURCHASED FROM IEX | J30: C1 | K30: C2 | L30: C4 | M30: C5 | N30: C24
A31: DAM | I31: TNEB Tariff | J31: =$L$31+($L$31*25%) -> 10.625 | K31: =$L$31+($L$31*25%) -> 10.625 | L31: 8.5 | M31: =$L$31-($L$31*5%) -> 8.075 | N31: 6.03 | O31: =AVERAGE(J31:M31) -> 9.45625
A32: Slot | B32: Price | C32: Purchase | D32: Delivered | E32: EB Cost | I32: E-Tax | J32: 0.05 | K32: 0.05 | L32: 0.05 | M32: 0.05 | N32: 0.05 | O32: 0.05
A33: C1 | B33: =J33 -> 11.15625 | C33: =J39+J46+J53 -> 500 | D33: =M39+M46+M53 -> 462.35606 | E33: =D33*B33 -> 5158.1598 | I33: Total price/Unit | J33: =J31+(J31*J32) -> 11.15625 | K33: =K31+(K31*K32) -> 11.15625 | L33: =L31+(L31*L32) -> 8.925 | M33: =M31+(M31*M32) -> 8.47875 | N33: =N31+(N31*N32) -> 6.3315 | O33: =AVERAGE(J33:M33) -> 9.9290625
A34: C2 | B34: =K33 -> 11.15625 | C34: =J41+J48+J55 -> 7627.5 | D34: =M41+M48+M55 -> 7053.2417 | E34: =D34*B34 -> 78687.728
A35: C4 | B35: =L33 -> 8.925 | C35: =J38+J40+J45+J47+J52+J54 -> 2250 | D35: =M38+M40+M45+M47+M52+M54 -> 2080.6023 | E35: =D35*B35 -> 18569.375
A36: C5 | B36: =M33 -> 8.47875 | C36: =J37+J42+J44+J49+J51+J56 -> 2500 | D36: =M37+M42+M44+M49+M51+M56 -> 2311.7803 | E36: =D36*B36 -> 19601.007 | I36: GDAM
A37: Total | C37: =SUM(C33:C36) -> 12877.5 | D37: =SUM(D33:D36) -> 11907.98 | E37: =SUM(E33:E36) -> 122016.27 | H37: C5 | I37: =SUM('Energy Schedule'!I7:I26)/4 -> 0 | J37: =I37*1000 -> 0 | K37: =J37-(J37*$B$6) -> 0 | L37: =K37-(K37*$B$7) -> 0 | M37: =L37-(L37*$B$8) -> 0
H38: C4 | I38: =SUM('Energy Schedule'!I27:I30)/4 -> 0 | J38: =I38*1000 -> 0 | K38: =J38-(J38*$B$6) -> 0 | L38: =K38-(K38*$B$7) -> 0 | M38: =L38-(L38*$B$8) -> 0
H39: C1 | I39: =SUM('Energy Schedule'!I31:I46)/4 -> 0 | J39: =I39*1000 -> 0 | K39: =J39-(J39*$B$6) -> 0 | L39: =K39-(K39*$B$7) -> 0 | M39: =L39-(L39*$B$8) -> 0
H40: C4 | I40: =SUM('Energy Schedule'!I47:I78)/4 -> 0 | J40: =I40*1000 -> 0 | K40: =J40-(J40*$B$6) -> 0 | L40: =K40-(K40*$B$7) -> 0 | M40: =L40-(L40*$B$8) -> 0
H41: C2 | I41: =SUM('Energy Schedule'!I79:I94)/4 -> 0 | J41: =I41*1000 -> 0 | K41: =J41-(J41*$B$6) -> 0 | L41: =K41-(K41*$B$7) -> 0 | M41: =L41-(L41*$B$8) -> 0
A42: Total Purchase | B42: =C37 -> 12877.5 | C42: C1 | D42: 700 | H42: C5 | I42: =SUM('Energy Schedule'!I95:I102)/4 -> 0 | J42: =I42*1000 -> 0 | K42: =J42-(J42*$B$6) -> 0 | L42: =K42-(K42*$B$7) -> 0 | M42: =L42-(L42*$B$8) -> 0
A43: Delivered | B43: =D37 -> 11907.98 | C43: C2 | D43: 7850 | I43: DAM
A44: IEX Price | B44: =C27+D27+E27 -> 99210.45 | C44: C3 | D44: 2000 | H44: C5 | I44: =SUM('Energy Schedule'!J7:J26)/4 -> 2.375 | J44: =I44*1000 -> 2375 | K44: =J44-(J44*$B$6) -> 2293.5375 | L44: =K44-(K44*$B$7) -> 2239.8687 | M44: =L44-(L44*$B$8) -> 2196.1913
A45: IEX Price / Unit | B45: =B44/B43 -> 8.3314254 | C45: C4 | D45: 20100 | H45: C4 | I45: =SUM('Energy Schedule'!J27:J30)/4 -> 0.25 | J45: =I45*1000 -> 250 | K45: =J45-(J45*$B$6) -> 241.425 | L45: =K45-(K45*$B$7) -> 235.77566 | M45: =L45-(L45*$B$8) -> 231.17803
A46: EB Price | B46: =E37 -> 122016.27 | C46: C5 | D46: 2950 | H46: C1 | I46: =SUM('Energy Schedule'!J31:J46)/4 -> 0 | J46: =I46*1000 -> 0 | K46: =J46-(J46*$B$6) -> 0 | L46: =K46-(K46*$B$7) -> 0 | M46: =L46-(L46*$B$8) -> 0
A47: EB Price / Unit | B47: =B46/B43 -> 10.246597 | C47: Total | D47: =SUM(D42:D46) -> 33600 | H47: C4 | I47: =SUM('Energy Schedule'!J47:J78)/4 -> 2 | J47: =I47*1000 -> 2000 | K47: =J47-(J47*$B$6) -> 1931.4 | L47: =K47-(K47*$B$7) -> 1886.2052 | M47: =L47-(L47*$B$8) -> 1849.4242
A48: Cost Saving | B48: =B46-B44 -> 22805.82 | H48: C2 | I48: =SUM('Energy Schedule'!J79:J94)/4 -> 4.5 | J48: =I48*1000 -> 4500 | K48: =J48-(J48*$B$6) -> 4345.65 | L48: =K48-(K48*$B$7) -> 4243.9618 | M48: =L48-(L48*$B$8) -> 4161.2045
A49: Cost Savings Unit | B49: =B47-B45 -> 1.9151711 | H49: C5 | I49: =SUM('Energy Schedule'!J95:J102)/4 -> 0.125 | J49: =I49*1000 -> 125 | K49: =J49-(J49*$B$6) -> 120.7125 | L49: =K49-(K49*$B$7) -> 117.88783 | M49: =L49-(L49*$B$8) -> 115.58901
I50: RTM
H51: C5 | I51: =SUM('Energy Schedule'!K7:K26)/4 -> 0 | J51: =I51*1000 -> 0 | K51: =J51-(J51*$B$6) -> 0 | L51: =K51-(K51*$B$7) -> 0 | M51: =L51-(L51*$B$8) -> 0
H52: C4 | I52: =SUM('Energy Schedule'!K27:K30)/4 -> 0 | J52: =I52*1000 -> 0 | K52: =J52-(J52*$B$6) -> 0 | L52: =K52-(K52*$B$7) -> 0 | M52: =L52-(L52*$B$8) -> 0
H53: C1 | I53: =SUM('Energy Schedule'!K31:K46)/4 -> 0.5 | J53: =I53*1000 -> 500 | K53: =J53-(J53*$B$6) -> 482.85 | L53: =K53-(K53*$B$7) -> 471.55131 | M53: =L53-(L53*$B$8) -> 462.35606
H54: C4 | I54: =SUM('Energy Schedule'!K47:K78)/4 -> 0 | J54: =I54*1000 -> 0 | K54: =J54-(J54*$B$6) -> 0 | L54: =K54-(K54*$B$7) -> 0 | M54: =L54-(L54*$B$8) -> 0
H55: C2 | I55: =SUM('Energy Schedule'!K79:K94)/4 -> 3.1275 | J55: =I55*1000 -> 3127.5 | K55: =J55-(J55*$B$6) -> 3020.2267 | L55: =K55-(K55*$B$7) -> 2949.5534 | M55: =L55-(L55*$B$8) -> 2892.0372
H56: C5 | I56: =SUM('Energy Schedule'!K95:K102)/4 -> 0 | J56: =I56*1000 -> 0 | K56: =J56-(J56*$B$6) -> 0 | L56: =K56-(K56*$B$7) -> 0 | M56: =L56-(L56*$B$8) -> 0

Sheet 04
C2: G-DAM | D2: DAM | E2: RTM
A3: Unit Purchased in MWh | C3: ='Energy Schedule'!L$103 -> 0 | D3: ='Energy Schedule'!M$103 -> 20.375 | E3: ='Energy Schedule'!N$103 -> 3
A4: IEX Payout | C4: ='Energy Schedule'!L$5 -> 0 | D4: ='Energy Schedule'!M$5 -> 83092.96 | E4: ='Energy Schedule'!N$5 -> 12749.83
A5: Total Units in kWh | C5: =C3*1000 -> 0 | D5: =D3*1000 -> 20375 | E5: =E3*1000 -> 3000 | I5: IEX Delivered | J5: Consumption | K5: Balance
A6: CTU | B6: ='Energy Schedule'!M3 -> 0.0343 | C6: =C5-(C5*$B$6) -> 0 | D6: =D5-(D5*$B$6) -> 19676.138 | E6: =E5-(E5*$B$6) -> 2897.1 | H6: C1 | I6: =D33 -> 346.76704 | J6: ='Consumption Details'!$B6 -> 2050 | K6: =J6-I6 -> 1703.233
A7: STU | B7: ='TNEB Charges'!B1 -> 0.0234 | C7: =C6-(C6*$B$7) -> 0 | D7: =D6-(D6*$B$7) -> 19215.716 | E7: =E6-(E6*$B$7) -> 2829.3079 | H7: C2 | I7: =D34 -> 11096.545 | J7: ='Consumption Details'!$C6 -> 10600 | K7: =J7-I7 -> -496.54543
A8: Discom Losses | B8: ='TNEB Charges'!B2 -> 0.0195 | C8: =C7-(C7*$B$8) -> 0 | D8: =D7-(D7*$B$8) -> 18841.009 | E8: =E7-(E7*$B$8) -> 2774.1364 | H8: C4 | I8: =D35 -> 7397.697 | J8: ='Consumption Details'!$D6 -> 21850 | K8: =J8-I8 -> 14452.303
A9: Delivered @ Bus | B9: ='TNEB Charges'!B3 -> 0 | C9: =C8 -> 0 | D9: =D8 -> 18841.009 | E9: =E8 -> 2774.1364 | H9: C5 | I9: =D36 -> 2774.1364 | J9: ='Consumption Details'!$E6 -> 3750 | K9: =J9-I9 -> 975.86364
A10: IEX Payout / Unit | B10: ='TNEB Charges'!B4 -> 0 | C10: =C4/C9 -> #DIV/0! | D10: =D4/D9 -> 4.410218 | E10: =E4/E9 -> 4.5959637
A11: IEX Transaction Charges | B11: ='TNEB Charges'!B5 -> 0.02 | C11: =(C3*1000*$B$11)+(C3*1000*$B$11*18%) -> 0 | D11: =(D3*1000*$B$11)+(D3*1000*$B$11*18%) -> 480.85 | E11: =(E3*1000*$B$11)+(E3*1000*$B$11*18%) -> 70.8
A12: NLDC Application fee | B12: ='TNEB Charges'!B6 -> 0 | C12: ='Energy Schedule'!L$6 -> 0 | D12: ='Energy Schedule'!M$6 -> 7.67 | E12: ='Energy Schedule'!N$6 -> 14.29
A13: CTU Transmission Charges | B13: ='TNEB Charges'!B7 -> 457.6 | C13: =C3*$B$13 -> 0 | D13: =D3*$B$13 -> 9323.6 | E13: =E3*$B$13 -> 1372.8
A14: NLDC Sched & Oprn Charges | B14: ='TNEB Charges'!B8 -> 1 | C14: =C3*$B$14 -> 0 | D14: =D3*$B$14 -> 20.375 | E14: =E3*$B$14 -> 3
A15: STU Transmission Charges | B15: ='TNEB Charges'!B9 -> 260 | C15: =C3*$B$15 -> 0 | D15: =D3*$B$15 -> 5297.5 | E15: =E3*$B$15 -> 780
A16: STU Scheduling | B16: ='TNEB Charges'!B10 -> 170 | C16: =IF(C3>0,$B$16,0) -> 0 | D16: =IF(D3>0,$B$16,0) -> 170 | E16: =IF(E3>0,$B$16,0) -> 170
A17: STU System Operating Charge | B17: ='TNEB Charges'!B11 -> 33.74 | C17: =C3*$B$17/24 -> 0 | D17: =D3*$B$17/24 -> 28.643854 | E17: =E3*$B$17/24 -> 4.2175
A18: TPTCL Margin | B18: ='TNEB Charges'!B12 -> 0.02 | C18: =C3*$B$18*1000 -> 0 | D18: =D3*$B$18*1000 -> 407.5 | E18: =E3*$B$18*1000 -> 60
A19: CSS | B19: ='TNEB Charges'!B13 -> 1.99 | C19: =C9*$B$19 -> 0 | D19: =D9*$B$19 -> 37493.609 | E19: =E9*$B$19 -> 5520.5313
A20: ASC | B20: ='TNEB Charges'!B14 -> 0 | C20: =C9*$B$20 -> 0 | D20: =D9*$B$20 -> 0 | E20: =E9*$B$20 -> 0
A21: Wheeling Charges | B21: ='TNEB Charges'!B15 -> 1.04 | C21: =C8*$B$21 -> 0 | D21: =D8*$B$21 -> 19594.65 | E21: =E8*$B$21 -> 2885.1018
A22: E-Tax | B22: ='TNEB Charges'!B16 -> 0 | C22: =C9*$B$22 -> 0 | D22: =D9*$B$22 -> 0 | E22: =E9*$B$22 -> 0
A23: Solar RPO Charges | B23: ='TNEB Charges'!B17 -> 0.12 | C23: 0 | D23: =D9*$B$23*10.5% -> 237.39672 | E23: =E9*$B$23*10.5% -> 34.954118
A24: Non-Solar RPO Charges | B24: ='TNEB Charges'!B18 -> 0.12 | C24: 0 | D24: =D9*$B$24*10.5% -> 237.39672 | E24: =E9*$B$24*10.5% -> 34.954118
A25: Total Statutory Charges | C25: =SUM(C11:C24) -> 0 | D25: =SUM(D11:D24) -> 73299.191 | E25: =SUM(E11:E24) -> 10950.649
C26: =C25/C9 -> #DIV/0! | D26: =D25/D9 -> 3.8904068 | E26: =E25/E9 -> 3.9474083
A27: Total Cost incurred in IEX Purchase | C27: =C4+C25 -> 0 | D27: =D4+D25 -> 156392.15 | E27: =E4+E25 -> 23700.479
A28: Cost per Unit incurred | C28: =C27/C9 -> #DIV/0! | D28: =D27/D9 -> 8.3006248 | E28: =E27/E9 -> 8.543372
I29: Slot | J29: Morning peak | K29: Evening peak | L29: Normal hour | M29: Normal hour | N29: Night Hour | O29: RTC
A30: EQUIVALENT EB PRICE TO THE UNITS PURCHASED FROM IEX | J30: C1 | K30: C2 | L30: C4 | M30: C5 | N30: C24
A31: DAM | I31: TNEB Tariff | J31: =$L$31+($L$31*25%) -> 10.625 | K31: =$L$31+($L$31*25%) -> 10.625 | L31: 8.5 | M31: =$L$31-($L$31*5%) -> 8.075 | N31: 6.03 | O31: =AVERAGE(J31:M31) -> 9.45625
A32: Slot | B32: Price | C32: Purchase | D32: Delivered | E32: EB Cost | I32: E-Tax | J32: 0.05 | K32: 0.05 | L32: 0.05 | M32: 0.05 | N32: 0.05 | O32: 0.05
A33: C1 | B33: =J33 -> 11.15625 | C33: =J39+J46+J53 -> 375 | D33: =M39+M46+M53 -> 346.76704 | E33: =D33*B33 -> 3868.6198 | I33: Total price/Unit | J33: =J31+(J31*J32) -> 11.15625 | K33: =K31+(K31*K32) -> 11.15625 | L33: =L31+(L31*L32) -> 8.925 | M33: =M31+(M31*M32) -> 8.47875 | N33: =N31+(N31*N32) -> 6.3315 | O33: =AVERAGE(J33:M33) -> 9.9290625
A34: C2 | B34: =K33 -> 11.15625 | C34: =J41+J48+J55 -> 12000 | D34: =M41+M48+M55 -> 11096.545 | E34: =D34*B34 -> 123795.83
A35: C4 | B35: =L33 -> 8.925 | C35: =J38+J40+J45+J47+J52+J54 -> 8000 | D35: =M38+M40+M45+M47+M52+M54 -> 7397.697 | E35: =D35*B35 -> 66024.445
A36: C5 | B36: =M33 -> 8.47875 | C36: =J37+J42+J44+J49+J51+J56 -> 3000 | D36: =M37+M42+M44+M49+M51+M56 -> 2774.1364 | E36: =D36*B36 -> 23521.209 | I36: GDAM
A37: Total | C37: =SUM(C33:C36) -> 23375 | D37: =SUM(D33:D36) -> 21615.146 | E37: =SUM(E33:E36) -> 217210.11 | H37: C5 | I37: =SUM('Energy Schedule'!L7:L26)/4 -> 0 | J37: =I37*1000 -> 0 | K37: =J37-(J37*$B$6) -> 0 | L37: =K37-(K37*$B$7) -> 0 | M37: =L37-(L37*$B$8) -> 0
H38: C4 | I38: =SUM('Energy Schedule'!L27:L30)/4 -> 0 | J38: =I38*1000 -> 0 | K38: =J38-(J38*$B$6) -> 0 | L38: =K38-(K38*$B$7) -> 0 | M38: =L38-(L38*$B$8) -> 0
H39: C1 | I39: =SUM('Energy Schedule'!L31:L46)/4 -> 0 | J39: =I39*1000 -> 0 | K39: =J39-(J39*$B$6) -> 0 | L39: =K39-(K39*$B$7) -> 0 | M39: =L39-(L39*$B$8) -> 0
H40: C4 | I40: =SUM('Energy Schedule'!L47:L78)/4 -> 0 | J40: =I40*1000 -> 0 | K40: =J40-(J40*$B$6) -> 0 | L40: =K40-(K40*$B$7) -> 0 | M40: =L40-(L40*$B$8) -> 0
H41: C2 | I41: =SUM('Energy Schedule'!L79:L94)/4 -> 0 | J41: =I41*1000 -> 0 | K41: =J41-(J41*$B$6) -> 0 | L41: =K41-(K41*$B$7) -> 0 | M41: =L41-(L41*$B$8) -> 0
A42: Total Purchase | B42: =C37 -> 23375 | C42: C1 | D42: 700 | H42: C5 | I42: =SUM('Energy Schedule'!L95:L102)/4 -> 0 | J42: =I42*1000 -> 0 | K42: =J42-(J42*$B$6) -> 0 | L42: =K42-(K42*$B$7) -> 0 | M42: =L42-(L42*$B$8) -> 0
A43: Delivered | B43: =D37 -> 21615.146 | C43: C2 | D43: 7850 | I43: DAM
A44: IEX Price | B44: =C27+D27+E27 -> 180092.63 | C44: C3 | D44: 2000 | H44: C5 | I44: =SUM('Energy Schedule'!M7:M26)/4 -> 2.5 | J44: =I44*1000 -> 2500 | K44: =J44-(J44*$B$6) -> 2414.25 | L44: =K44-(K44*$B$7) -> 2357.7566 | M44: =L44-(L44*$B$8) -> 2311.7803
A45: IEX Price / Unit | B45: =B44/B43 -> 8.3317795 | C45: C4 | D45: 20100 | H45: C4 | I45: =SUM('Energy Schedule'!M27:M30)/4 -> 0.5 | J45: =I45*1000 -> 500 | K45: =J45-(J45*$B$6) -> 482.85 | L45: =K45-(K45*$B$7) -> 471.55131 | M45: =L45-(L45*$B$8) -> 462.35606
A46: EB Price | B46: =E37 -> 217210.11 | C46: C5 | D46: 2950 | H46: C1 | I46: =SUM('Energy Schedule'!M31:M46)/4 -> 0.375 | J46: =I46*1000 -> 375 | K46: =J46-(J46*$B$6) -> 362.1375 | L46: =K46-(K46*$B$7) -> 353.66348 | M46: =L46-(L46*$B$8) -> 346.76704
A47: EB Price / Unit | B47: =B46/B43 -> 10.048977 | C47: Total | D47: =SUM(D42:D46) -> 33600 | H47: C4 | I47: =SUM('Energy Schedule'!M47:M78)/4 -> 7.5 | J47: =I47*1000 -> 7500 | K47: =J47-(J47*$B$6) -> 7242.75 | L47: =K47-(K47*$B$7) -> 7073.2697 | M47: =L47-(L47*$B$8) -> 6935.3409
A48: Cost Saving | B48: =B46-B44 -> 37117.479 | H48: C2 | I48: =SUM('Energy Schedule'!M79:M94)/4 -> 9 | J48: =I48*1000 -> 9000 | K48: =J48-(J48*$B$6) -> 8691.3 | L48: =K48-(K48*$B$7) -> 8487.9236 | M48: =L48-(L48*$B$8) -> 8322.4091
A49: Cost Savings Unit | B49: =B47-B45 -> 1.7171977 | H49: C5 | I49: =SUM('Energy Schedule'!M95:M102)/4 -> 0.5 | J49: =I49*1000 -> 500 | K49: =J49-(J49*$B$6) -> 482.85 | L49: =K49-(K49*$B$7) -> 471.55131 | M49: =L49-(L49*$B$8) -> 462.35606
I50: RTM
H51: C5 | I51: =SUM('Energy Schedule'!N7:N26)/4 -> 0 | J51: =I51*1000 -> 0 | K51: =J51-(J51*$B$6) -> 0 | L51: =K51-(K51*$B$7) -> 0 | M51: =L51-(L51*$B$8) -> 0
H52: C4 | I52: =SUM('Energy Schedule'!N27:N30)/4 -> 0 | J52: =I52*1000 -> 0 | K52: =J52-(J52*$B$6) -> 0 | L52: =K52-(K52*$B$7) -> 0 | M52: =L52-(L52*$B$8) -> 0
H53: C1 | I53: =SUM('Energy Schedule'!N31:N46)/4 -> 0 | J53: =I53*1000 -> 0 | K53: =J53-(J53*$B$6) -> 0 | L53: =K53-(K53*$B$7) -> 0 | M53: =L53-(L53*$B$8) -> 0
H54: C4 | I54: =SUM('Energy Schedule'!N47:N78)/4 -> 0 | J54: =I54*1000 -> 0 | K54: =J54-(J54*$B$6) -> 0 | L54: =K54-(K54*$B$7) -> 0 | M54: =L54-(L54*$B$8) -> 0
H55: C2 | I55: =SUM('Energy Schedule'!N79:N94)/4 -> 3 | J55: =I55*1000 -> 3000 | K55: =J55-(J55*$B$6) -> 2897.1 | L55: =K55-(K55*$B$7) -> 2829.3079 | M55: =L55-(L55*$B$8) -> 2774.1364
H56: C5 | I56: =SUM('Energy Schedule'!N95:N102)/4 -> 0 | J56: =I56*1000 -> 0 | K56: =J56-(J56*$B$6) -> 0 | L56: =K56-(K56*$B$7) -> 0 | M56: =L56-(L56*$B$8) -> 0

Sheet 05
C2: G-DAM | D2: DAM | E2: RTM
A3: Unit Purchased in MWh | C3: ='Energy Schedule'!O$103 -> 0 | D3: ='Energy Schedule'!P$103 -> 10 | E3: ='Energy Schedule'!Q$103 -> 3.75
A4: IEX Payout | C4: ='Energy Schedule'!O$5 -> 0 | D4: ='Energy Schedule'!P$5 -> 39837.968 | E4: ='Energy Schedule'!Q$5 -> 16147.49
A5: Total Units in kWh | C5: =C3*1000 -> 0 | D5: =D3*1000 -> 10000 | E5: =E3*1000 -> 3750 | I5: IEX Delivered | J5: Consumption | K5: Balance
A6: CTU | B6: ='Energy Schedule'!P3 -> 0.0361 | C6: =C5-(C5*$B$6) -> 0 | D6: =D5-(D5*$B$6) -> 9639 | E6: =E5-(E5*$B$6) -> 3614.625 | H6: C1 | I6: =D33 -> 346.12069 | J6: ='Consumption Details'!$B7 -> 1950 | K6: =J6-I6 -> 1603.8793
A7: STU | B7: ='TNEB Charges'!B1 -> 0.0234 | C7: =C6-(C6*$B$7) -> 0 | D7: =D6-(D6*$B$7) -> 9413.4474 | E7: =E6-(E6*$B$7) -> 3530.0428 | H7: C2 | I7: =D34 -> 7614.6553 | J7: ='Consumption Details'!$C7 -> 9300 | K7: =J7-I7 -> 1685.3447
A8: Discom Losses | B8: ='TNEB Charges'!B2 -> 0.0195 | C8: =C7-(C7*$B$8) -> 0 | D8: =D7-(D7*$B$8) -> 9229.8852 | E8: =E7-(E7*$B$8) -> 3461.2069 | H8: C4 | I8: =D35 -> 2307.4713 | J8: ='Consumption Details'!$D7 -> 19400 | K8: =J8-I8 -> 17092.529
A9: Delivered @ Bus | B9: ='TNEB Charges'!B3 -> 0 | C9: =C8 -> 0 | D9: =D8 -> 9229.8852 | E9: =E8 -> 3461.2069 | H9: C5 | I9: =D36 -> 2422.8449 | J9: ='Consumption Details'!$E7 -> 3400 | K9: =J9-I9 -> 977.15514
A10: IEX Payout / Unit | B10: ='TNEB Charges'!B4 -> 0 | C10: =C4/C9 -> #DIV/0! | D10: =D4/D9 -> 4.3161933 | E10: =E4/E9 -> 4.6652773
A11: IEX Transaction Charges | B11: ='TNEB Charges'!B5 -> 0.02 | C11: =(C3*1000*$B$11)+(C3*1000*$B$11*18%) -> 0 | D11: =(D3*1000*$B$11)+(D3*1000*$B$11*18%) -> 236 | E11: =(E3*1000*$B$11)+(E3*1000*$B$11*18%) -> 88.5
A12: NLDC Application fee | B12: ='TNEB Charges'!B6 -> 0 | C12: ='Energy Schedule'!O$6 -> 0 | D12: ='Energy Schedule'!P$6 -> 8.18 | E12: ='Energy Schedule'!Q$6 -> 13.55
A13: CTU Transmission Charges | B13: ='TNEB Charges'!B7 -> 457.6 | C13: =C3*$B$13 -> 0 | D13: =D3*$B$13 -> 4576 | E13: =E3*$B$13 -> 1716
A14: NLDC Sched & Oprn Charges | B14: ='TNEB Charges'!B8 -> 1 | C14: =C3*$B$14 -> 0 | D14: =D3*$B$14 -> 10 | E14: =E3*$B$14 -> 3.75
A15: STU Transmission Charges | B15: ='TNEB Charges'!B9 -> 260 | C15: =C3*$B$15 -> 0 | D15: =D3*$B$15 -> 2600 | E15: =E3*$B$15 -> 975
A16: STU Scheduling | B16: ='TNEB Charges'!B10 -> 170 | C16: =IF(C3>0,$B$16,0) -> 0 | D16: =IF(D3>0,$B$16,0) -> 170 | E16: =IF(E3>0,$B$16,0) -> 170
A17: STU System Operating Charge | B17: ='TNEB Charges'!B11 -> 33.74 | C17: =C3*$B$17/24 -> 0 | D17: =D3*$B$17/24 -> 14.058333 | E17: =E3*$B$17/24 -> 5.271875
A18: TPTCL Margin | B18: ='TNEB Charges'!B12 -> 0.02 | C18: =C3*$B$18*1000 -> 0 | D18: =D3*$B$18*1000 -> 200 | E18: =E3*$B$18*1000 -> 75
A19: CSS | B19: ='TNEB Charges'!B13 -> 1.99 | C19: =C9*$B$19 -> 0 | D19: =D9*$B$19 -> 18367.471 | E19: =E9*$B$19 -> 6887.8018
A20: ASC | B20: ='TNEB Charges'!B14 -> 0 | C20: =C9*$B$20 -> 0 | D20: =D9*$B$20 -> 0 | E20: =E9*$B$20 -> 0
A21: Wheeling Charges | B21: ='TNEB Charges'!B15 -> 1.04 | C21: =C8*$B$21 -> 0 | D21: =D8*$B$21 -> 9599.0806 | E21: =E8*$B$21 -> 3599.6552
A22: E-Tax | B22: ='TNEB Charges'!B16 -> 0 | C22: =C9*$B$22 -> 0 | D22: =D9*$B$22 -> 0 | E22: =E9*$B$22 -> 0
A23: Solar RPO Charges | B23: ='TNEB Charges'!B17 -> 0.12 | C23: 0 | D23: =D9*$B$23*10.5% -> 116.29655 | E23: =E9*$B$23*10.5% -> 43.611207
A24: Non-Solar RPO Charges | B24: ='TNEB Charges'!B18 -> 0.12 | C24: 0 | D24: =D9*$B$24*10.5% -> 116.29655 | E24: =E9*$B$24*10.5% -> 43.611207
A25: Total Statutory Charges | C25: =SUM(C11:C24) -> 0 | D25: =SUM(D11:D24) -> 36013.384 | E25: =SUM(E11:E24) -> 13621.751
C26: =C25/C9 -> #DIV/0! | D26: =D25/D9 -> 3.9018236 | E26: =E25/E9 -> 3.9355495
A27: Total Cost incurred in IEX Purchase | C27: =C4+C25 -> 0 | D27: =D4+D25 -> 75851.352 | E27: =E4+E25 -> 29769.241
A28: Cost per Unit incurred | C28: =C27/C9 -> #DIV/0! | D28: =D27/D9 -> 8.2180168 | E28: =E27/E9 -> 8.6008268
I29: Slot | J29: Morning peak | K29: Evening peak | L29: Normal hour | M29: Normal hour | N29: Night Hour | O29: RTC
A30: EQUIVALENT EB PRICE TO THE UNITS PURCHASED FROM IEX | J30: C1 | K30: C2 | L30: C4 | M30: C5 | N30: C24
A31: DAM | I31: TNEB Tariff | J31: =$L$31+($L$31*25%) -> 10.625 | K31: =$L$31+($L$31*25%) -> 10.625 | L31: 8.5 | M31: =$L$31-($L$31*5%) -> 8.075 | N31: 6.03 | O31: =AVERAGE(J31:M31) -> 9.45625
A32: Slot | B32: Price | C32: Purchase | D32: Delivered | E32: EB Cost | I32: E-Tax | J32: 0.05 | K32: 0.05 | L32: 0.05 | M32: 0.05 | N32: 0.05 | O32: 0.05
A33: C1 | B33: =J33 -> 11.15625 | C33: =J39+J46+J53 -> 375 | D33: =M39+M46+M53 -> 346.12069 | E33: =D33*B33 -> 3861.409 | I33: Total price/Unit | J33: =J31+(J31*J32) -> 11.15625 | K33: =K31+(K31*K32) -> 11.15625 | L33: =L31+(L31*L32) -> 8.925 | M33: =M31+(M31*M32) -> 8.47875 | N33: =N31+(N31*N32) -> 6.3315 | O33: =AVERAGE(J33:M33) -> 9.9290625
A34: C2 | B34: =K33 -> 11.15625 | C34: =J41+J48+J55 -> 8250 | D34: =M41+M48+M55 -> 7614.6553 | E34: =D34*B34 -> 84950.998
A35: C4 | B35: =L33 -> 8.925 | C35: =J38+J40+J45+J47+J52+J54 -> 2500 | D35: =M38+M40+M45+M47+M52+M54 -> 2307.4713 | E35: =D35*B35 -> 20594.181
A36: C5 | B36: =M33 -> 8.47875 | C36: =J37+J42+J44+J49+J51+J56 -> 2625 | D36: =M37+M42+M44+M49+M51+M56 -> 2422.8449 | E36: =D36*B36 -> 20542.696 | I36: GDAM
A37: Total | C37: =SUM(C33:C36) -> 13750 | D37: =SUM(D33:D36) -> 12691.092 | E37: =SUM(E33:E36) -> 129949.28 | H37: C5 | I37: =SUM('Energy Schedule'!O7:O26)/4 -> 0 | J37: =I37*1000 -> 0 | K37: =J37-(J37*$B$6) -> 0 | L37: =K37-(K37*$B$7) -> 0 | M37: =L37-(L37*$B$8) -> 0
H38: C4 | I38: =SUM('Energy Schedule'!O27:O30)/4 -> 0 | J38: =I38*1000 -> 0 | K38: =J38-(J38*$B$6) -> 0 | L38: =K38-(K38*$B$7) -> 0 | M38: =L38-(L38*$B$8) -> 0
H39: C1 | I39: =SUM('Energy Schedule'!O31:O46)/4 -> 0 | J39: =I39*1000 -> 0 | K39: =J39-(J39*$B$6) -> 0 | L39: =K39-(K39*$B$7) -> 0 | M39: =L39-(L39*$B$8) -> 0
H40: C4 | I40: =SUM('Energy Schedule'!O47:O78)/4 -> 0 | J40: =I40*1000 -> 0 | K40: =J40-(J40*$B$6) -> 0 | L40: =K40-(K40*$B$7) -> 0 | M40: =L40-(L40*$B$8) -> 0
H41: C2 | I41: =SUM('Energy Schedule'!O79:O94)/4 -> 0 | J41: =I41*1000 -> 0 | K41: =J41-(J41*$B$6) -> 0 | L41: =K41-(K41*$B$7) -> 0 | M41: =L41-(L41*$B$8) -> 0
A42: Total Purchase | B42: =C37 -> 13750 | C42: C1 | D42: 700 | H42: C5 | I42: =SUM('Energy Schedule'!O95:O102)/4 -> 0 | J42: =I42*1000 -> 0 | K42: =J42-(J42*$B$6) -> 0 | L42: =K42-(K42*$B$7) -> 0 | M42: =L42-(L42*$B$8) -> 0
A43: Delivered | B43: =D37 -> 12691.092 | C43: C2 | D43: 7850 | I43: DAM
A44: IEX Price | B44: =C27+D27+E27 -> 105620.59 | C44: C3 | D44: 2000 | H44: C5 | I44: =SUM('Energy Schedule'!P7:P26)/4 -> 2.5 | J44: =I44*1000 -> 2500 | K44: =J44-(J44*$B$6) -> 2409.75 | L44: =K44-(K44*$B$7) -> 2353.3618 | M44: =L44-(L44*$B$8) -> 2307.4713
A45: IEX Price / Unit | B45: =B44/B43 -> 8.3224196 | C45: C4 | D45: 20100 | H45: C4 | I45: =SUM('Energy Schedule'!P27:P30)/4 -> 0.5 | J45: =I45*1000 -> 500 | K45: =J45-(J45*$B$6) -> 481.95 | L45: =K45-(K45*$B$7) -> 470.67237 | M45: =L45-(L45*$B$8) -> 461.49426
A46: EB Price | B46: =E37 -> 129949.28 | C46: C5 | D46: 2950 | H46: C1 | I46: =SUM('Energy Schedule'!P31:P46)/4 -> 0.375 | J46: =I46*1000 -> 375 | K46: =J46-(J46*$B$6) -> 361.4625 | L46: =K46-(K46*$B$7) -> 353.00428 | M46: =L46-(L46*$B$8) -> 346.12069
A47: EB Price / Unit | B47: =B46/B43 -> 10.239409 | C47: Total | D47: =SUM(D42:D46) -> 33600 | H47: C4 | I47: =SUM('Energy Schedule'!P47:P78)/4 -> 2 | J47: =I47*1000 -> 2000 | K47: =J47-(J47*$B$6) -> 1927.8 | L47: =K47-(K47*$B$7) -> 1882.6895 | M47: =L47-(L47*$B$8) -> 1845.977
A48: Cost Saving | B48: =B46-B44 -> 24328.691 | H48: C2 | I48: =SUM('Energy Schedule'!P79:P94)/4 -> 4.5 | J48: =I48*1000 -> 4500 | K48: =J48-(J48*$B$6) -> 4337.55 | L48: =K48-(K48*$B$7) -> 4236.0513 | M48: =L48-(L48*$B$8) -> 4153.4483
A49: Cost Savings Unit | B49: =B47-B45 -> 1.9169895 | H49: C5 | I49: =SUM('Energy Schedule'!P95:P102)/4 -> 0.125 | J49: =I49*1000 -> 125 | K49: =J49-(J49*$B$6) -> 120.4875 | L49: =K49-(K49*$B$7) -> 117.66809 | M49: =L49-(L49*$B$8) -> 115.37356
I50: RTM
H51: C5 | I51: =SUM('Energy Schedule'!Q7:Q26)/4 -> 0 | J51: =I51*1000 -> 0 | K51: =J51-(J51*$B$6) -> 0 | L51: =K51-(K51*$B$7) -> 0 | M51: =L51-(L51*$B$8) -> 0
H52: C4 | I52: =SUM('Energy Schedule'!Q27:Q30)/4 -> 0 | J52: =I52*1000 -> 0 | K52: =J52-(J52*$B$6) -> 0 | L52: =K52-(K52*$B$7) -> 0 | M52: =L52-(L52*$B$8) -> 0
H53: C1 | I53: =SUM('Energy Schedule'!Q31:Q46)/4 -> 0 | J53: =I53*1000 -> 0 | K53: =J53-(J53*$B$6) -> 0 | L53: =K53-(K53*$B$7) -> 0 | M53: =L53-(L53*$B$8) -> 0
H54: C4 | I54: =SUM('Energy Schedule'!Q47:Q78)/4 -> 0 | J54: =I54*1000 -> 0 | K54: =J54-(J54*$B$6) -> 0 | L54: =K54-(K54*$B$7) -> 0 | M54: =L54-(L54*$B$8) -> 0
H55: C2 | I55: =SUM('Energy Schedule'!Q79:Q94)/4 -> 3.75 | J55: =I55*1000 -> 3750 | K55: =J55-(J55*$B$6) -> 3614.625 | L55: =K55-(K55*$B$7) -> 3530.0428 | M55: =L55-(L55*$B$8) -> 3461.2069
H56: C5 | I56: =SUM('Energy Schedule'!Q95:Q102)/4 -> 0 | J56: =I56*1000 -> 0 | K56: =J56-(J56*$B$6) -> 0 | L56: =K56-(K56*$B$7) -> 0 | M56: =L56-(L56*$B$8) -> 0

Sheet 06
C2: G-DAM | D2: DAM | E2: RTM
A3: Unit Purchased in MWh | C3: ='Energy Schedule'!R$103 -> 0 | D3: ='Energy Schedule'!S$103 -> 13 | E3: ='Energy Schedule'!T$103 -> 2.75
A4: IEX Payout | C4: ='Energy Schedule'!R$5 -> 0 | D4: ='Energy Schedule'!S$5 -> 54907.277 | E4: ='Energy Schedule'!T$5 -> 13002.64
A5: Total Units in kWh | C5: =C3*1000 -> 0 | D5: =D3*1000 -> 13000 | E5: =E3*1000 -> 2750 | I5: IEX Delivered | J5: Consumption | K5: Balance
A6: CTU | B6: ='Energy Schedule'!S3 -> 0.0361 | C6: =C5-(C5*$B$6) -> 0 | D6: =D5-(D5*$B$6) -> 12530.7 | E6: =E5-(E5*$B$6) -> 2650.725 | H6: C1 | I6: =D33 -> 115.37356 | J6: ='Consumption Details'!$B8 -> 1850 | K6: =J6-I6 -> 1734.6264
A7: STU | B7: ='TNEB Charges'!B1 -> 0.0234 | C7: =C6-(C6*$B$7) -> 0 | D7: =D6-(D6*$B$7) -> 12237.482 | E7: =E6-(E6*$B$7) -> 2588.698 | H7: C2 | I7: =D34 -> 8306.8967 | J7: ='Consumption Details'!$C8 -> 9050 | K7: =J7-I7 -> 743.10334
A8: Discom Losses | B8: ='TNEB Charges'!B2 -> 0.0195 | C8: =C7-(C7*$B$8) -> 0 | D8: =D7-(D7*$B$8) -> 11998.851 | E8: =E7-(E7*$B$8) -> 2538.2184 | H8: C4 | I8: =D35 -> 3691.9541 | J8: ='Consumption Details'!$D8 -> 17550 | K8: =J8-I8 -> 13858.046
A9: Delivered @ Bus | B9: ='TNEB Charges'!B3 -> 0 | C9: =C8 -> 0 | D9: =D8 -> 11998.851 | E9: =E8 -> 2538.2184 | H9: C5 | I9: =D36 -> 2422.8449 | J9: ='Consumption Details'!$E8 -> 3350 | K9: =J9-I9 -> 927.15514
A10: IEX Payout / Unit | B10: ='TNEB Charges'!B4 -> 0 | C10: =C4/C9 -> #DIV/0! | D10: =D4/D9 -> 4.5760447 | E10: =E4/E9 -> 5.1227427
A11: IEX Transaction Charges | B11: ='TNEB Charges'!B5 -> 0.02 | C11: =(C3*1000*$B$11)+(C3*1000*$B$11*18%) -> 0 | D11: =(D3*1000*$B$11)+(D3*1000*$B$11*18%) -> 306.8 | E11: =(E3*1000*$B$11)+(E3*1000*$B$11*18%) -> 64.9
A12: NLDC Application fee | B12: ='TNEB Charges'!B6 -> 0 | C12: ='Energy Schedule'!R$6 -> 0 | D12: ='Energy Schedule'!S$6 -> 8.35 | E12: ='Energy Schedule'!T$6 -> 12.53
A13: CTU Transmission Charges | B13: ='TNEB Charges'!B7 -> 457.6 | C13: =C3*$B$13 -> 0 | D13: =D3*$B$13 -> 5948.8 | E13: =E3*$B$13 -> 1258.4
A14: NLDC Sched & Oprn Charges | B14: ='TNEB Charges'!B8 -> 1 | C14: =C3*$B$14 -> 0 | D14: =D3*$B$14 -> 13 | E14: =E3*$B$14 -> 2.75
A15: STU Transmission Charges | B15: ='TNEB Charges'!B9 -> 260 | C15: =C3*$B$15 -> 0 | D15: =D3*$B$15 -> 3380 | E15: =E3*$B$15 -> 715
A16: STU Scheduling | B16: ='TNEB Charges'!B10 -> 170 | C16: =IF(C3>0,$B$16,0) -> 0 | D16: =IF(D3>0,$B$16,0) -> 170 | E16: =IF(E3>0,$B$16,0) -> 170
A17: STU System Operating Charge | B17: ='TNEB Charges'!B11 -> 33.74 | C17: =C3*$B$17/24 -> 0 | D17: =D3*$B$17/24 -> 18.275833 | E17: =E3*$B$17/24 -> 3.8660417
A18: TPTCL Margin | B18: ='TNEB Charges'!B12 -> 0.02 | C18: =C3*$B$18*1000 -> 0 | D18: =D3*$B$18*1000 -> 260 | E18: =E3*$B$18*1000 -> 55
A19: CSS | B19: ='TNEB Charges'!B13 -> 1.99 | C19: =C9*$B$19 -> 0 | D19: =D9*$B$19 -> 23877.713 | E19: =E9*$B$19 -> 5051.0547
A20: ASC | B20: ='TNEB Charges'!B14 -> 0 | C20: =C9*$B$20 -> 0 | D20: =D9*$B$20 -> 0 | E20: =E9*$B$20 -> 0
A21: Wheeling Charges | B21: ='TNEB Charges'!B15 -> 1.04 | C21: =C8*$B$21 -> 0 | D21: =D8*$B$21 -> 12478.805 | E21: =E8*$B$21 -> 2639.7472
A22: E-Tax | B22: ='TNEB Charges'!B16 -> 0 | C22: =C9*$B$22 -> 0 | D22: =D9*$B$22 -> 0 | E22: =E9*$B$22 -> 0
A23: Solar RPO Charges | B23: ='TNEB Charges'!B17 -> 0.12 | C23: 0 | D23: =D9*$B$23*10.5% -> 151.18552 | E23: =E9*$B$23*10.5% -> 31.981552
A24: Non-Solar RPO Charges | B24: ='TNEB Charges'!B18 -> 0.12 | C24: 0 | D24: =D9*$B$24*10.5% -> 151.18552 | E24: =E9*$B$24*10.5% -> 31.981552
A25: Total Statutory Charges | C25: =SUM(C11:C24) -> 0 | D25: =SUM(D11:D24) -> 46764.115 | E25: =SUM(E11:E24) -> 10037.211
C26: =C25/C9 -> #DIV/0! | D26: =D25/D9 -> 3.8973828 | E26: =E25/E9 -> 3.9544315
A27: Total Cost incurred in IEX Purchase | C27: =C4+C25 -> 0 | D27: =D4+D25 -> 101671.39 | E27: =E4+E25 -> 23039.851
A28: Cost per Unit incurred | C28: =C27/C9 -> #DIV/0! | D28: =D27/D9 -> 8.4734275 | E28: =E27/E9 -> 9.0771743
I29: Slot | J29: Morning peak | K29: Evening peak | L29: Normal hour | M29: Normal hour | N29: Night Hour | O29: RTC
A30: EQUIVALENT EB PRICE TO THE UNITS PURCHASED FROM IEX | J30: C1 | K30: C2 | L30: C4 | M30: C5 | N30: C24
A31: DAM | I31: TNEB Tariff | J31: =$L$31+($L$31*25%) -> 10.625 | K31: =$L$31+($L$31*25%) -> 10.625 | L31: 8.5 | M31: =$L$31-($L$31*5%) -> 8.075 | N31: 6.03 | O31: =AVERAGE(J31:M31) -> 9.45625
A32: Slot | B32: Price | C32: Purchase | D32: Delivered | E32: EB Cost | I32: E-Tax | J32: 0.05 | K32: 0.05 | L32: 0.05 | M32: 0.05 | N32: 0.05 | O32: 0.05
A33: C1 | B33: =J33 -> 11.15625 | C33: =J39+J46+J53 -> 125 | D33: =M39+M46+M53 -> 115.37356 | E33: =D33*B33 -> 1287.1363 | I33: Total price/Unit | J33: =J31+(J31*J32) -> 11.15625 | K33: =K31+(K31*K32) -> 11.15625 | L33: =L31+(L31*L32) -> 8.925 | M33: =M31+(M31*M32) -> 8.47875 | N33: =N31+(N31*N32) -> 6.3315 | O33: =AVERAGE(J33:M33) -> 9.9290625
A34: C2 | B34: =K33 -> 11.15625 | C34: =J41+J48+J55 -> 9000 | D34: =M41+M48+M55 -> 8306.8967 | E34: =D34*B34 -> 92673.816
A35: C4 | B35: =L33 -> 8.925 | C35: =J38+J40+J45+J47+J52+J54 -> 4000 | D35: =M38+M40+M45+M47+M52+M54 -> 3691.9541 | E35: =D35*B35 -> 32950.69
A36: C5 | B36: =M33 -> 8.47875 | C36: =J37+J42+J44+J49+J51+J56 -> 2625 | D36: =M37+M42+M44+M49+M51+M56 -> 2422.8449 | E36: =D36*B36 -> 20542.696 | I36: GDAM
A37: Total | C37: =SUM(C33:C36) -> 15750 | D37: =SUM(D33:D36) -> 14537.069 | E37: =SUM(E33:E36) -> 147454.34 | H37: C5 | I37: =SUM('Energy Schedule'!R7:R26)/4 -> 0 | J37: =I37*1000 -> 0 | K37: =J37-(J37*$B$6) -> 0 | L37: =K37-(K37*$B$7) -> 0 | M37: =L37-(L37*$B$8) -> 0
H38: C4 | I38: =SUM('Energy Schedule'!R27:R30)/4 -> 0 | J38: =I38*1000 -> 0 | K38: =J38-(J38*$B$6) -> 0 | L38: =K38-(K38*$B$7) -> 0 | M38: =L38-(L38*$B$8) -> 0
H39: C1 | I39: =SUM('Energy Schedule'!R31:R46)/4 -> 0 | J39: =I39*1000 -> 0 | K39: =J39-(J39*$B$6) -> 0 | L39: =K39-(K39*$B$7) -> 0 | M39: =L39-(L39*$B$8) -> 0
H40: C4 | I40: =SUM('Energy Schedule'!R47:R78)/4 -> 0 | J40: =I40*1000 -> 0 | K40: =J40-(J40*$B$6) -> 0 | L40: =K40-(K40*$B$7) -> 0 | M40: =L40-(L40*$B$8) -> 0
H41: C2 | I41: =SUM('Energy Schedule'!R79:R94)/4 -> 0 | J41: =I41*1000 -> 0 | K41: =J41-(J41*$B$6) -> 0 | L41: =K41-(K41*$B$7) -> 0 | M41: =L41-(L41*$B$8) -> 0
A42: Total Purchase | B42: =C37 -> 15750 | C42: C1 | D42: 700 | H42: C5 | I42: =SUM('Energy Schedule'!R95:R102)/4 -> 0 | J42: =I42*1000 -> 0 | K42: =J42-(J42*$B$6) -> 0 | L42: =K42-(K42*$B$7) -> 0 | M42: =L42-(L42*$B$8) -> 0
A43: Delivered | B43: =D37 -> 14537.069 | C43: C2 | D43: 7850 | I43: DAM
A44: IEX Price | B44: =C27+D27+E27 -> 124711.24 | C44: C3 | D44: 2000 | H44: C5 | I44: =SUM('Energy Schedule'!S7:S26)/4 -> 2.5 | J44: =I44*1000 -> 2500 | K44: =J44-(J44*$B$6) -> 2409.75 | L44: =K44-(K44*$B$7) -> 2353.3618 | M44: =L44-(L44*$B$8) -> 2307.4713
A45: IEX Price / Unit | B45: =B44/B43 -> 8.5788436 | C45: C4 | D45: 20100 | H45: C4 | I45: =SUM('Energy Schedule'!S27:S30)/4 -> 0.5 | J45: =I45*1000 -> 500 | K45: =J45-(J45*$B$6) -> 481.95 | L45: =K45-(K45*$B$7) -> 470.67237 | M45: =L45-(L45*$B$8) -> 461.49426
A46: EB Price | B46: =E37 -> 147454.34 | C46: C5 | D46: 2950 | H46: C1 | I46: =SUM('Energy Schedule'!S31:S46)/4 -> 0.125 | J46: =I46*1000 -> 125 | K46: =J46-(J46*$B$6) -> 120.4875 | L46: =K46-(K46*$B$7) -> 117.66809 | M46: =L46-(L46*$B$8) -> 115.37356
A47: EB Price / Unit | B47: =B46/B43 -> 10.143333 | C47: Total | D47: =SUM(D42:D46) -> 33600 | H47: C4 | I47: =SUM('Energy Schedule'!S47:S78)/4 -> 3 | J47: =I47*1000 -> 3000 | K47: =J47-(J47*$B$6) -> 2891.7 | L47: =K47-(K47*$B$7) -> 2824.0342 | M47: =L47-(L47*$B$8) -> 2768.9656
A48: Cost Saving | B48: =B46-B44 -> 22743.096 | H48: C2 | I48: =SUM('Energy Schedule'!S79:S94)/4 -> 6.75 | J48: =I48*1000 -> 6750 | K48: =J48-(J48*$B$6) -> 6506.325 | L48: =K48-(K48*$B$7) -> 6354.077 | M48: =L48-(L48*$B$8) -> 6230.1725
A49: Cost Savings Unit | B49: =B47-B45 -> 1.5644897 | H49: C5 | I49: =SUM('Energy Schedule'!S95:S102)/4 -> 0.125 | J49: =I49*1000 -> 125 | K49: =J49-(J49*$B$6) -> 120.4875 | L49: =K49-(K49*$B$7) -> 117.66809 | M49: =L49-(L49*$B$8) -> 115.37356
I50: RTM
H51: C5 | I51: =SUM('Energy Schedule'!T7:T26)/4 -> 0 | J51: =I51*1000 -> 0 | K51: =J51-(J51*$B$6) -> 0 | L51: =K51-(K51*$B$7) -> 0 | M51: =L51-(L51*$B$8) -> 0
H52: C4 | I52: =SUM('Energy Schedule'!T27:T30)/4 -> 0 | J52: =I52*1000 -> 0 | K52: =J52-(J52*$B$6) -> 0 | L52: =K52-(K52*$B$7) -> 0 | M52: =L52-(L52*$B$8) -> 0
H53: C1 | I53: =SUM('Energy Schedule'!T31:T46)/4 -> 0 | J53: =I53*1000 -> 0 | K53: =J53-(J53*$B$6) -> 0 | L53: =K53-(K53*$B$7) -> 0 | M53: =L53-(L53*$B$8) -> 0
H54: C4 | I54: =SUM('Energy Schedule'!T47:T78)/4 -> 0.5 | J54: =I54*1000 -> 500 | K54: =J54-(J54*$B$6) -> 481.95 | L54: =K54-(K54*$B$7) -> 470.67237 | M54: =L54-(L54*$B$8) -> 461.49426
H55: C2 | I55: =SUM('Energy Schedule'!T79:T94)/4 -> 2.25 | J55: =I55*1000 -> 2250 | K55: =J55-(J55*$B$6) -> 2168.775 | L55: =K55-(K55*$B$7) -> 2118.0257 | M55: =L55-(L55*$B$8) -> 2076.7242
H56: C5 | I56: =SUM('Energy Schedule'!T95:T102)/4 -> 0 | J56: =I56*1000 -> 0 | K56: =J56-(J56*$B$6) -> 0 | L56: =K56-(K56*$B$7) -> 0 | M56: =L56-(L56*$B$8) -> 0

Sheet 07
C2: G-DAM | D2: DAM | E2: RTM
A3: Unit Purchased in MWh | C3: ='Energy Schedule'!U$103 -> 0 | D3: ='Energy Schedule'!V$103 -> 8.415 | E3: ='Energy Schedule'!W$103 -> 5.45
A4: IEX Payout | C4: ='Energy Schedule'!U$5 -> 0 | D4: ='Energy Schedule'!V$5 -> 33736.898 | E4: ='Energy Schedule'!W$5 -> 22760.98
A5: Total Units in kWh | C5: =C3*1000 -> 0 | D5: =D3*1000 -> 8415 | E5: =E3*1000 -> 5450 | I5: IEX Delivered | J5: Consumption | K5: Balance
A6: CTU | B6: ='Energy Schedule'!V3 -> 0.0361 | C6: =C5-(C5*$B$6) -> 0 | D6: =D5-(D5*$B$6) -> 8111.2185 | E6: =E5-(E5*$B$6) -> 5253.255 | H6: C1 | I6: =D33 -> 0 | J6: ='Consumption Details'!$B9 -> 1950 | K6: =J6-I6 -> 1950
A7: STU | B7: ='TNEB Charges'!B1 -> 0.0234 | C7: =C6-(C6*$B$7) -> 0 | D7: =D6-(D6*$B$7) -> 7921.416 | E7: =E6-(E6*$B$7) -> 5130.3288 | H7: C2 | I7: =D34 -> 6922.4139 | J7: ='Consumption Details'!$C9 -> 9450 | K7: =J7-I7 -> 2527.5861
A8: Discom Losses | B8: ='TNEB Charges'!B2 -> 0.0195 | C8: =C7-(C7*$B$8) -> 0 | D8: =D7-(D7*$B$8) -> 7766.9484 | E8: =E7-(E7*$B$8) -> 5030.2874 | H8: C4 | I8: =D35 -> 3345.8334 | J8: ='Consumption Details'!$D9 -> 17950 | K8: =J8-I8 -> 14604.167
A9: Delivered @ Bus | B9: ='TNEB Charges'!B3 -> 0 | C9: =C8 -> 0 | D9: =D8 -> 7766.9484 | E9: =E8 -> 5030.2874 | H9: C5 | I9: =D36 -> 2528.9885 | J9: ='Consumption Details'!$E9 -> 3200 | K9: =J9-I9 -> 671.01146
A10: IEX Payout / Unit | B10: ='TNEB Charges'!B4 -> 0 | C10: =C4/C9 -> #DIV/0! | D10: =D4/D9 -> 4.343649 | E10: =E4/E9 -> 4.5247872
A11: IEX Transaction Charges | B11: ='TNEB Charges'!B5 -> 0.02 | C11: =(C3*1000*$B$11)+(C3*1000*$B$11*18%) -> 0 | D11: =(D3*1000*$B$11)+(D3*1000*$B$11*18%) -> 198.594 | E11: =(E3*1000*$B$11)+(E3*1000*$B$11*18%) -> 128.62
A12: NLDC Application fee | B12: ='TNEB Charges'!B6 -> 0 | C12: ='Energy Schedule'!U$6 -> 0 | D12: ='Energy Schedule'!V$6 -> 8.61 | E12: ='Energy Schedule'!W$6 -> 12.89
A13: CTU Transmission Charges | B13: ='TNEB Charges'!B7 -> 457.6 | C13: =C3*$B$13 -> 0 | D13: =D3*$B$13 -> 3850.704 | E13: =E3*$B$13 -> 2493.92
A14: NLDC Sched & Oprn Charges | B14: ='TNEB Charges'!B8 -> 1 | C14: =C3*$B$14 -> 0 | D14: =D3*$B$14 -> 8.415 | E14: =E3*$B$14 -> 5.45
A15: STU Transmission Charges | B15: ='TNEB Charges'!B9 -> 260 | C15: =C3*$B$15 -> 0 | D15: =D3*$B$15 -> 2187.9 | E15: =E3*$B$15 -> 1417
A16: STU Scheduling | B16: ='TNEB Charges'!B10 -> 170 | C16: =IF(C3>0,$B$16,0) -> 0 | D16: =IF(D3>0,$B$16,0) -> 170 | E16: =IF(E3>0,$B$16,0) -> 170
A17: STU System Operating Charge | B17: ='TNEB Charges'!B11 -> 33.74 | C17: =C3*$B$17/24 -> 0 | D17: =D3*$B$17/24 -> 11.830087 | E17: =E3*$B$17/24 -> 7.6617917
A18: TPTCL Margin | B18: ='TNEB Charges'!B12 -> 0.02 | C18: =C3*$B$18*1000 -> 0 | D18: =D3*$B$18*1000 -> 168.3 | E18: =E3*$B$18*1000 -> 109
A19: CSS | B19: ='TNEB Charges'!B13 -> 1.99 | C19: =C9*$B$19 -> 0 | D19: =D9*$B$19 -> 15456.227 | E19: =E9*$B$19 -> 10010.272
A20: ASC | B20: ='TNEB Charges'!B14 -> 0 | C20: =C9*$B$20 -> 0 | D20: =D9*$B$20 -> 0 | E20: =E9*$B$20 -> 0
A21: Wheeling Charges | B21: ='TNEB Charges'!B15 -> 1.04 | C21: =C8*$B$21 -> 0 | D21: =D8*$B$21 -> 8077.6263 | E21: =E8*$B$21 -> 5231.4989
A22: E-Tax | B22: ='TNEB Charges'!B16 -> 0 | C22: =C9*$B$22 -> 0 | D22: =D9*$B$22 -> 0 | E22: =E9*$B$22 -> 0
A23: Solar RPO Charges | B23: ='TNEB Charges'!B17 -> 0.12 | C23: 0 | D23: =D9*$B$23*10.5% -> 97.86355 | E23: =E9*$B$23*10.5% -> 63.381622
A24: Non-Solar RPO Charges | B24: ='TNEB Charges'!B18 -> 0.12 | C24: 0 | D24: =D9*$B$24*10.5% -> 97.86355 | E24: =E9*$B$24*10.5% -> 63.381622
A25: Total Statutory Charges | C25: =SUM(C11:C24) -> 0 | D25: =SUM(D11:D24) -> 30333.934 | E25: =SUM(E11:E24) -> 19713.076
C26: =C25/C9 -> #DIV/0! | D26: =D25/D9 -> 3.905515 | E26: =E25/E9 -> 3.9188767
A27: Total Cost incurred in IEX Purchase | C27: =C4+C25 -> 0 | D27: =D4+D25 -> 64070.832 | E27: =E4+E25 -> 42474.056
A28: Cost per Unit incurred | C28: =C27/C9 -> #DIV/0! | D28: =D27/D9 -> 8.2491641 | E28: =E27/E9 -> 8.4436638
I29: Slot | J29: Morning peak | K29: Evening peak | L29: Normal hour | M29: Normal hour | N29: Night Hour | O29: RTC
A30: EQUIVALENT EB PRICE TO THE UNITS PURCHASED FROM IEX | J30: C1 | K30: C2 | L30: C4 | M30: C5 | N30: C24
A31: DAM | I31: TNEB Tariff | J31: =$L$31+($L$31*25%) -> 10.625 | K31: =$L$31+($L$31*25%) -> 10.625 | L31: 8.5 | M31: =$L$31-($L$31*5%) -> 8.075 | N31: 6.03 | O31: =AVERAGE(J31:M31) -> 9.45625
A32: Slot | B32: Price | C32: Purchase | D32: Delivered | E32: EB Cost | I32: E-Tax | J32: 0.05 | K32: 0.05 | L32: 0.05 | M32: 0.05 | N32: 0.05 | O32: 0.05
A33: C1 | B33: =J33 -> 11.15625 | C33: =J39+J46+J53 -> 0 | D33: =M39+M46+M53 -> 0 | E33: =D33*B33 -> 0 | I33: Total price/Unit | J33: =J31+(J31*J32) -> 11.15625 | K33: =K31+(K31*K32) -> 11.15625 | L33: =L31+(L31*L32) -> 8.925 | M33: =M31+(M31*M32) -> 8.47875 | N33: =N31+(N31*N32) -> 6.3315 | O33: =AVERAGE(J33:M33) -> 9.9290625
A34: C2 | B34: =K33 -> 11.15625 | C34: =J41+J48+J55 -> 7500 | D34: =M41+M48+M55 -> 6922.4139 | E34: =D34*B34 -> 77228.18
A35: C4 | B35: =L33 -> 8.925 | C35: =J38+J40+J45+J47+J52+J54 -> 3625 | D35: =M38+M40+M45+M47+M52+M54 -> 3345.8334 | E35: =D35*B35 -> 29861.563
A36: C5 | B36: =M33 -> 8.47875 | C36: =J37+J42+J44+J49+J51+J56 -> 2740 | D36: =M37+M42+M44+M49+M51+M56 -> 2528.9885 | E36: =D36*B36 -> 21442.662 | I36: GDAM
A37: Total | C37: =SUM(C33:C36) -> 13865 | D37: =SUM(D33:D36) -> 12797.236 | E37: =SUM(E33:E36) -> 128532.4 | H37: C5 | I37: =SUM('Energy Schedule'!U7:U26)/4 -> 0 | J37: =I37*1000 -> 0 | K37: =J37-(J37*$B$6) -> 0 | L37: =K37-(K37*$B$7) -> 0 | M37: =L37-(L37*$B$8) -> 0
H38: C4 | I38: =SUM('Energy Schedule'!U27:U30)/4 -> 0 | J38: =I38*1000 -> 0 | K38: =J38-(J38*$B$6) -> 0 | L38: =K38-(K38*$B$7) -> 0 | M38: =L38-(L38*$B$8) -> 0
H39: C1 | I39: =SUM('Energy Schedule'!U31:U46)/4 -> 0 | J39: =I39*1000 -> 0 | K39: =J39-(J39*$B$6) -> 0 | L39: =K39-(K39*$B$7) -> 0 | M39: =L39-(L39*$B$8) -> 0
H40: C4 | I40: =SUM('Energy Schedule'!U47:U78)/4 -> 0 | J40: =I40*1000 -> 0 | K40: =J40-(J40*$B$6) -> 0 | L40: =K40-(K40*$B$7) -> 0 | M40: =L40-(L40*$B$8) -> 0
H41: C2 | I41: =SUM('Energy Schedule'!U79:U94)/4 -> 0 | J41: =I41*1000 -> 0 | K41: =J41-(J41*$B$6) -> 0 | L41: =K41-(K41*$B$7) -> 0 | M41: =L41-(L41*$B$8) -> 0
A42: Total Purchase | B42: =C37 -> 13865 | C42: C1 | D42: 700 | H42: C5 | I42: =SUM('Energy Schedule'!U95:U102)/4 -> 0 | J42: =I42*1000 -> 0 | K42: =J42-(J42*$B$6) -> 0 | L42: =K42-(K42*$B$7) -> 0 | M42: =L42-(L42*$B$8) -> 0
A43: Delivered | B43: =D37 -> 12797.236 | C43: C2 | D43: 7850 | I43: DAM
A44: IEX Price | B44: =C27+D27+E27 -> 106544.89 | C44: C3 | D44: 2000 | H44: C5 | I44: =SUM('Energy Schedule'!V7:V26)/4 -> 2.5 | J44: =I44*1000 -> 2500 | K44: =J44-(J44*$B$6) -> 2409.75 | L44: =K44-(K44*$B$7) -> 2353.3618 | M44: =L44-(L44*$B$8) -> 2307.4713
A45: IEX Price / Unit | B45: =B44/B43 -> 8.3256173 | C45: C4 | D45: 20100 | H45: C4 | I45: =SUM('Energy Schedule'!V27:V30)/4 -> 0.375 | J45: =I45*1000 -> 375 | K45: =J45-(J45*$B$6) -> 361.4625 | L45: =K45-(K45*$B$7) -> 353.00428 | M45: =L45-(L45*$B$8) -> 346.12069
A46: EB Price | B46: =E37 -> 128532.4 | C46: C5 | D46: 2950 | H46: C1 | I46: =SUM('Energy Schedule'!V31:V46)/4 -> 0 | J46: =I46*1000 -> 0 | K46: =J46-(J46*$B$6) -> 0 | L46: =K46-(K46*$B$7) -> 0 | M46: =L46-(L46*$B$8) -> 0
A47: EB Price / Unit | B47: =B46/B43 -> 10.043763 | C47: Total | D47: =SUM(D42:D46) -> 33600 | H47: C4 | I47: =SUM('Energy Schedule'!V47:V78)/4 -> 2.5 | J47: =I47*1000 -> 2500 | K47: =J47-(J47*$B$6) -> 2409.75 | L47: =K47-(K47*$B$7) -> 2353.3618 | M47: =L47-(L47*$B$8) -> 2307.4713
A48: Cost Saving | B48: =B46-B44 -> 21987.517 | H48: C2 | I48: =SUM('Energy Schedule'!V79:V94)/4 -> 3 | J48: =I48*1000 -> 3000 | K48: =J48-(J48*$B$6) -> 2891.7 | L48: =K48-(K48*$B$7) -> 2824.0342 | M48: =L48-(L48*$B$8) -> 2768.9656
A49: Cost Savings Unit | B49: =B47-B45 -> 1.7181458 | H49: C5 | I49: =SUM('Energy Schedule'!V95:V102)/4 -> 0.04 | J49: =I49*1000 -> 40 | K49: =J49-(J49*$B$6) -> 38.556 | L49: =K49-(K49*$B$7) -> 37.65379 | M49: =L49-(L49*$B$8) -> 36.919541
I50: RTM
H51: C5 | I51: =SUM('Energy Schedule'!W7:W26)/4 -> 0 | J51: =I51*1000 -> 0 | K51: =J51-(J51*$B$6) -> 0 | L51: =K51-(K51*$B$7) -> 0 | M51: =L51-(L51*$B$8) -> 0
H52: C4 | I52: =SUM('Energy Schedule'!W27:W30)/4 -> 0 | J52: =I52*1000 -> 0 | K52: =J52-(J52*$B$6) -> 0 | L52: =K52-(K52*$B$7) -> 0 | M52: =L52-(L52*$B$8) -> 0
H53: C1 | I53: =SUM('Energy Schedule'!W31:W46)/4 -> 0 | J53: =I53*1000 -> 0 | K53: =J53-(J53*$B$6) -> 0 | L53: =K53-(K53*$B$7) -> 0 | M53: =L53-(L53*$B$8) -> 0
H54: C4 | I54: =SUM('Energy Schedule'!W47:W78)/4 -> 0.75 | J54: =I54*1000 -> 750 | K54: =J54-(J54*$B$6) -> 722.925 | L54: =K54-(K54*$B$7) -> 706.00856 | M54: =L54-(L54*$B$8) -> 692.24139
H55: C2 | I55: =SUM('Energy Schedule'!W79:W94)/4 -> 4.5 | J55: =I55*1000 -> 4500 | K55: =J55-(J55*$B$6) -> 4337.55 | L55: =K55-(K55*$B$7) -> 4236.0513 | M55: =L55-(L55*$B$8) -> 4153.4483
H56: C5 | I56: =SUM('Energy Schedule'!W95:W102)/4 -> 0.2 | J56: =I56*1000 -> 200 | K56: =J56-(J56*$B$6) -> 192.78 | L56: =K56-(K56*$B$7) -> 188.26895 | M56: =L56-(L56*$B$8) -> 184.5977

Sheet 08
C2: G-DAM | D2: DAM | E2: RTM
A3: Unit Purchased in MWh | C3: ='Energy Schedule'!X$103 -> 0 | D3: ='Energy Schedule'!Y$103 -> 12 | E3: ='Energy Schedule'!Z$103 -> 7
A4: IEX Payout | C4: ='Energy Schedule'!X$5 -> 0 | D4: ='Energy Schedule'!Y$5 -> 51549.744 | E4: ='Energy Schedule'!Z$5 -> 32714.22
A5: Total Units in kWh | C5: =C3*1000 -> 0 | D5: =D3*1000 -> 12000 | E5: =E3*1000 -> 7000 | I5: IEX Delivered | J5: Consumption | K5: Balance
A6: CTU | B6: ='Energy Schedule'!Y3 -> 0.0361 | C6: =C5-(C5*$B$6) -> 0 | D6: =D5-(D5*$B$6) -> 11566.8 | E6: =E5-(E5*$B$6) -> 6747.3 | H6: C1 | I6: =D33 -> 0 | J6: ='Consumption Details'!$B10 -> 1800 | K6: =J6-I6 -> 1800
A7: STU | B7: ='TNEB Charges'!B1 -> 0.0234 | C7: =C6-(C6*$B$7) -> 0 | D7: =D6-(D6*$B$7) -> 11296.137 | E7: =E6-(E6*$B$7) -> 6589.4132 | H7: C2 | I7: =D34 -> 9691.3794 | J7: ='Consumption Details'!$C10 -> 9100 | K7: =J7-I7 -> -591.37943
A8: Discom Losses | B8: ='TNEB Charges'!B2 -> 0.0195 | C8: =C7-(C7*$B$8) -> 0 | D8: =D7-(D7*$B$8) -> 11075.862 | E8: =E7-(E7*$B$8) -> 6460.9196 | H8: C4 | I8: =D35 -> 5191.8104 | J8: ='Consumption Details'!$D10 -> 17800 | K8: =J8-I8 -> 12608.19
A9: Delivered @ Bus | B9: ='TNEB Charges'!B3 -> 0 | C9: =C8 -> 0 | D9: =D8 -> 11075.862 | E9: =E8 -> 6460.9196 | H9: C5 | I9: =D36 -> 2653.592 | J9: ='Consumption Details'!$E10 -> 3400 | K9: =J9-I9 -> 746.40801
A10: IEX Payout / Unit | B10: ='TNEB Charges'!B4 -> 0 | C10: =C4/C9 -> #DIV/0! | D10: =D4/D9 -> 4.6542421 | E10: =E4/E9 -> 5.0633999
A11: IEX Transaction Charges | B11: ='TNEB Charges'!B5 -> 0.02 | C11: =(C3*1000*$B$11)+(C3*1000*$B$11*18%) -> 0 | D11: =(D3*1000*$B$11)+(D3*1000*$B$11*18%) -> 283.2 | E11: =(E3*1000*$B$11)+(E3*1000*$B$11*18%) -> 165.2
A12: NLDC Application fee | B12: ='TNEB Charges'!B6 -> 0 | C12: ='Energy Schedule'!X$6 -> 0 | D12: ='Energy Schedule'!Y$6 -> 8.61 | E12: ='Energy Schedule'!Z$6 -> 12.53
A13: CTU Transmission Charges | B13: ='TNEB Charges'!B7 -> 457.6 | C13: =C3*$B$13 -> 0 | D13: =D3*$B$13 -> 5491.2 | E13: =E3*$B$13 -> 3203.2
A14: NLDC Sched & Oprn Charges | B14: ='TNEB Charges'!B8 -> 1 | C14: =C3*$B$14 -> 0 | D14: =D3*$B$14 -> 12 | E14: =E3*$B$14 -> 7
A15: STU Transmission Charges | B15: ='TNEB Charges'!B9 -> 260 | C15: =C3*$B$15 -> 0 | D15: =D3*$B$15 -> 3120 | E15: =E3*$B$15 -> 1820
A16: STU Scheduling | B16: ='TNEB Charges'!B10 -> 170 | C16: =IF(C3>0,$B$16,0) -> 0 | D16: =IF(D3>0,$B$16,0) -> 170 | E16: =IF(E3>0,$B$16,0) -> 170
A17: STU System Operating Charge | B17: ='TNEB Charges'!B11 -> 33.74 | C17: =C3*$B$17/24 -> 0 | D17: =D3*$B$17/24 -> 16.87 | E17: =E3*$B$17/24 -> 9.8408333
A18: TPTCL Margin | B18: ='TNEB Charges'!B12 -> 0.02 | C18: =C3*$B$18*1000 -> 0 | D18: =D3*$B$18*1000 -> 240 | E18: =E3*$B$18*1000 -> 140
A19: CSS | B19: ='TNEB Charges'!B13 -> 1.99 | C19: =C9*$B$19 -> 0 | D19: =D9*$B$19 -> 22040.966 | E19: =E9*$B$19 -> 12857.23
A20: ASC | B20: ='TNEB Charges'!B14 -> 0 | C20: =C9*$B$20 -> 0 | D20: =D9*$B$20 -> 0 | E20: =E9*$B$20 -> 0
A21: Wheeling Charges | B21: ='TNEB Charges'!B15 -> 1.04 | C21: =C8*$B$21 -> 0 | D21: =D8*$B$21 -> 11518.897 | E21: =E8*$B$21 -> 6719.3564
A22: E-Tax | B22: ='TNEB Charges'!B16 -> 0 | C22: =C9*$B$22 -> 0 | D22: =D9*$B$22 -> 0 | E22: =E9*$B$22 -> 0
A23: Solar RPO Charges | B23: ='TNEB Charges'!B17 -> 0.12 | C23: 0 | D23: =D9*$B$23*10.5% -> 139.55586 | E23: =E9*$B$23*10.5% -> 81.407587
A24: Non-Solar RPO Charges | B24: ='TNEB Charges'!B18 -> 0.12 | C24: 0 | D24: =D9*$B$24*10.5% -> 139.55586 | E24: =E9*$B$24*10.5% -> 81.407587
A25: Total Statutory Charges | C25: =SUM(C11:C24) -> 0 | D25: =SUM(D11:D24) -> 43180.854 | E25: =SUM(E11:E24) -> 25267.172
C26: =C25/C9 -> #DIV/0! | D26: =D25/D9 -> 3.8986449 | E26: =E25/E9 -> 3.9107703
A27: Total Cost incurred in IEX Purchase | C27: =C4+C25 -> 0 | D27: =D4+D25 -> 94730.598 | E27: =E4+E25 -> 57981.392
A28: Cost per Unit incurred | C28: =C27/C9 -> #DIV/0! | D28: =D27/D9 -> 8.552887 | E28: =E27/E9 -> 8.9741702
I29: Slot | J29: Morning peak | K29: Evening peak | L29: Normal hour | M29: Normal hour | N29: Night Hour | O29: RTC
A30: EQUIVALENT EB PRICE TO THE UNITS PURCHASED FROM IEX | J30: C1 | K30: C2 | L30: C4 | M30: C5 | N30: C24
A31: DAM | I31: TNEB Tariff | J31: =$L$31+($L$31*25%) -> 10.625 | K31: =$L$31+($L$31*25%) -> 10.625 | L31: 8.5 | M31: =$L$31-($L$31*5%) -> 8.075 | N31: 6.03 | O31: =AVERAGE(J31:M31) -> 9.45625
A32: Slot | B32: Price | C32: Purchase | D32: Delivered | E32: EB Cost | I32: E-Tax | J32: 0.05 | K32: 0.05 | L32: 0.05 | M32: 0.05 | N32: 0.05 | O32: 0.05
A33: C1 | B33: =J33 -> 11.15625 | C33: =J39+J46+J53 -> 0 | D33: =M39+M46+M53 -> 0 | E33: =D33*B33 -> 0 | I33: Total price/Unit | J33: =J31+(J31*J32) -> 11.15625 | K33: =K31+(K31*K32) -> 11.15625 | L33: =L31+(L31*L32) -> 8.925 | M33: =M31+(M31*M32) -> 8.47875 | N33: =N31+(N31*N32) -> 6.3315 | O33: =AVERAGE(J33:M33) -> 9.9290625
A34: C2 | B34: =K33 -> 11.15625 | C34: =J41+J48+J55 -> 10500 | D34: =M41+M48+M55 -> 9691.3794 | E34: =D34*B34 -> 108119.45
A35: C4 | B35: =L33 -> 8.925 | C35: =J38+J40+J45+J47+J52+J54 -> 5625 | D35: =M38+M40+M45+M47+M52+M54 -> 5191.8104 | E35: =D35*B35 -> 46336.908
A36: C5 | B36: =M33 -> 8.47875 | C36: =J37+J42+J44+J49+J51+J56 -> 2875 | D36: =M37+M42+M44+M49+M51+M56 -> 2653.592 | E36: =D36*B36 -> 22499.143 | I36: GDAM
A37: Total | C37: =SUM(C33:C36) -> 19000 | D37: =SUM(D33:D36) -> 17536.782 | E37: =SUM(E33:E36) -> 176955.5 | H37: C5 | I37: =SUM('Energy Schedule'!X7:X26)/4 -> 0 | J37: =I37*1000 -> 0 | K37: =J37-(J37*$B$6) -> 0 | L37: =K37-(K37*$B$7) -> 0 | M37: =L37-(L37*$B$8) -> 0
H38: C4 | I38: =SUM('Energy Schedule'!X27:X30)/4 -> 0 | J38: =I38*1000 -> 0 | K38: =J38-(J38*$B$6) -> 0 | L38: =K38-(K38*$B$7) -> 0 | M38: =L38-(L38*$B$8) -> 0
H39: C1 | I39: =SUM('Energy Schedule'!X31:X46)/4 -> 0 | J39: =I39*1000 -> 0 | K39: =J39-(J39*$B$6) -> 0 | L39: =K39-(K39*$B$7) -> 0 | M39: =L39-(L39*$B$8) -> 0
H40: C4 | I40: =SUM('Energy Schedule'!X47:X78)/4 -> 0 | J40: =I40*1000 -> 0 | K40: =J40-(J40*$B$6) -> 0 | L40: =K40-(K40*$B$7) -> 0 | M40: =L40-(L40*$B$8) -> 0
H41: C2 | I41: =SUM('Energy Schedule'!X79:X94)/4 -> 0 | J41: =I41*1000 -> 0 | K41: =J41-(J41*$B$6) -> 0 | L41: =K41-(K41*$B$7) -> 0 | M41: =L41-(L41*$B$8) -> 0
A42: Total Purchase | B42: =C37 -> 19000 | C42: C1 | D42: 700 | H42: C5 | I42: =SUM('Energy Schedule'!X95:X102)/4 -> 0 | J42: =I42*1000 -> 0 | K42: =J42-(J42*$B$6) -> 0 | L42: =K42-(K42*$B$7) -> 0 | M42: =L42-(L42*$B$8) -> 0
A43: Delivered | B43: =D37 -> 17536.782 | C43: C2 | D43: 7850 | I43: DAM
A44: IEX Price | B44: =C27+D27+E27 -> 152711.99 | C44: C3 | D44: 2000 | H44: C5 | I44: =SUM('Energy Schedule'!Y7:Y26)/4 -> 2.5 | J44: =I44*1000 -> 2500 | K44: =J44-(J44*$B$6) -> 2409.75 | L44: =K44-(K44*$B$7) -> 2353.3618 | M44: =L44-(L44*$B$8) -> 2307.4713
A45: IEX Price / Unit | B45: =B44/B43 -> 8.7080966 | C45: C4 | D45: 20100 | H45: C4 | I45: =SUM('Energy Schedule'!Y27:Y30)/4 -> 0.375 | J45: =I45*1000 -> 375 | K45: =J45-(J45*$B$6) -> 361.4625 | L45: =K45-(K45*$B$7) -> 353.00428 | M45: =L45-(L45*$B$8) -> 346.12069
A46: EB Price | B46: =E37 -> 176955.5 | C46: C5 | D46: 2950 | H46: C1 | I46: =SUM('Energy Schedule'!Y31:Y46)/4 -> 0 | J46: =I46*1000 -> 0 | K46: =J46-(J46*$B$6) -> 0 | L46: =K46-(K46*$B$7) -> 0 | M46: =L46-(L46*$B$8) -> 0
A47: EB Price / Unit | B47: =B46/B43 -> 10.090535 | C47: Total | D47: =SUM(D42:D46) -> 33600 | H47: C4 | I47: =SUM('Energy Schedule'!Y47:Y78)/4 -> 2 | J47: =I47*1000 -> 2000 | K47: =J47-(J47*$B$6) -> 1927.8 | L47: =K47-(K47*$B$7) -> 1882.6895 | M47: =L47-(L47*$B$8) -> 1845.977
A48: Cost Saving | B48: =B46-B44 -> 24243.512 | H48: C2 | I48: =SUM('Energy Schedule'!Y79:Y94)/4 -> 6.75 | J48: =I48*1000 -> 6750 | K48: =J48-(J48*$B$6) -> 6506.325 | L48: =K48-(K48*$B$7) -> 6354.077 | M48: =L48-(L48*$B$8) -> 6230.1725
A49: Cost Savings Unit | B49: =B47-B45 -> 1.3824379 | H49: C5 | I49: =SUM('Energy Schedule'!Y95:Y102)/4 -> 0.375 | J49: =I49*1000 -> 375 | K49: =J49-(J49*$B$6) -> 361.4625 | L49: =K49-(K49*$B$7) -> 353.00428 | M49: =L49-(L49*$B$8) -> 346.12069
I50: RTM
H51: C5 | I51: =SUM('Energy Schedule'!Z7:Z26)/4 -> 0 | J51: =I51*1000 -> 0 | K51: =J51-(J51*$B$6) -> 0 | L51: =K51-(K51*$B$7) -> 0 | M51: =L51-(L51*$B$8) -> 0
H52: C4 | I52: =SUM('Energy Schedule'!Z27:Z30)/4 -> 0 | J52: =I52*1000 -> 0 | K52: =J52-(J52*$B$6) -> 0 | L52: =K52-(K52*$B$7) -> 0 | M52: =L52-(L52*$B$8) -> 0
H53: C1 | I53: =SUM('Energy Schedule'!Z31:Z46)/4 -> 0 | J53: =I53*1000 -> 0 | K53: =J53-(J53*$B$6) -> 0 | L53: =K53-(K53*$B$7) -> 0 | M53: =L53-(L53*$B$8) -> 0
H54: C4 | I54: =SUM('Energy Schedule'!Z47:Z78)/4 -> 3.25 | J54: =I54*1000 -> 3250 | K54: =J54-(J54*$B$6) -> 3132.675 | L54: =K54-(K54*$B$7) -> 3059.3704 | M54: =L54-(L54*$B$8) -> 2999.7127
H55: C2 | I55: =SUM('Energy Schedule'!Z79:Z94)/4 -> 3.75 | J55: =I55*1000 -> 3750 | K55: =J55-(J55*$B$6) -> 3614.625 | L55: =K55-(K55*$B$7) -> 3530.0428 | M55: =L55-(L55*$B$8) -> 3461.2069
H56: C5 | I56: =SUM('Energy Schedule'!Z95:Z102)/4 -> 0 | J56: =I56*1000 -> 0 | K56: =J56-(J56*$B$6) -> 0 | L56: =K56-(K56*$B$7) -> 0 | M56: =L56-(L56*$B$8) -> 0

Sheet 09
C2: G-DAM | D2: DAM | E2: RTM
A3: Unit Purchased in MWh | C3: ='Energy Schedule'!AA$103 -> 0 | D3: ='Energy Schedule'!AB$103 -> 13.375 | E3: ='Energy Schedule'!AC$103 -> 6.575
A4: IEX Payout | C4: ='Energy Schedule'!AA$5 -> 0 | D4: ='Energy Schedule'!AB$5 -> 55906.487 | E4: ='Energy Schedule'!AC$5 -> 28235.38
A5: Total Units in kWh | C5: =C3*1000 -> 0 | D5: =D3*1000 -> 13375 | E5: =E3*1000 -> 6575 | I5: IEX Delivered | J5: Consumption | K5: Balance
A6: CTU | B6: ='Energy Schedule'!AB3 -> 0.0361 | C6: =C5-(C5*$B$6) -> 0 | D6: =D5-(D5*$B$6) -> 12892.163 | E6: =E5-(E5*$B$6) -> 6337.6425 | H6: C1 | I6: =D33 -> 0 | J6: ='Consumption Details'!$B11 -> 1550 | K6: =J6-I6 -> 1550
A7: STU | B7: ='TNEB Charges'!B1 -> 0.0234 | C7: =C6-(C6*$B$7) -> 0 | D7: =D6-(D6*$B$7) -> 12590.486 | E7: =E6-(E6*$B$7) -> 6189.3417 | H7: C2 | I7: =D34 -> 10383.621 | J7: ='Consumption Details'!$C11 -> 8950 | K7: =J7-I7 -> -1433.6208
A8: Discom Losses | B8: ='TNEB Charges'!B2 -> 0.0195 | C8: =C7-(C7*$B$8) -> 0 | D8: =D7-(D7*$B$8) -> 12344.971 | E8: =E7-(E7*$B$8) -> 6068.6495 | H8: C4 | I8: =D35 -> 5145.661 | J8: ='Consumption Details'!$D11 -> 18050 | K8: =J8-I8 -> 12904.339
A9: Delivered @ Bus | B9: ='TNEB Charges'!B3 -> 0 | C9: =C8 -> 0 | D9: =D8 -> 12344.971 | E9: =E8 -> 6068.6495 | H9: C5 | I9: =D36 -> 2884.3391 | J9: ='Consumption Details'!$E11 -> 3550 | K9: =J9-I9 -> 665.66088
A10: IEX Payout / Unit | B10: ='TNEB Charges'!B4 -> 0 | C10: =C4/C9 -> #DIV/0! | D10: =D4/D9 -> 4.528685 | E10: =E4/E9 -> 4.6526628
A11: IEX Transaction Charges | B11: ='TNEB Charges'!B5 -> 0.02 | C11: =(C3*1000*$B$11)+(C3*1000*$B$11*18%) -> 0 | D11: =(D3*1000*$B$11)+(D3*1000*$B$11*18%) -> 315.65 | E11: =(E3*1000*$B$11)+(E3*1000*$B$11*18%) -> 155.17
A12: NLDC Application fee | B12: ='TNEB Charges'!B6 -> 0 | C12: ='Energy Schedule'!AA$6 -> 0 | D12: ='Energy Schedule'!AB$6 -> 8.28 | E12: ='Energy Schedule'!AC$6 -> 12.32
A13: CTU Transmission Charges | B13: ='TNEB Charges'!B7 -> 457.6 | C13: =C3*$B$13 -> 0 | D13: =D3*$B$13 -> 6120.4 | E13: =E3*$B$13 -> 3008.72
A14: NLDC Sched & Oprn Charges | B14: ='TNEB Charges'!B8 -> 1 | C14: =C3*$B$14 -> 0 | D14: =D3*$B$14 -> 13.375 | E14: =E3*$B$14 -> 6.575
A15: STU Transmission Charges | B15: ='TNEB Charges'!B9 -> 260 | C15: =C3*$B$15 -> 0 | D15: =D3*$B$15 -> 3477.5 | E15: =E3*$B$15 -> 1709.5
A16: STU Scheduling | B16: ='TNEB Charges'!B10 -> 170 | C16: =IF(C3>0,$B$16,0) -> 0 | D16: =IF(D3>0,$B$16,0) -> 170 | E16: =IF(E3>0,$B$16,0) -> 170
A17: STU System Operating Charge | B17: ='TNEB Charges'!B11 -> 33.74 | C17: =C3*$B$17/24 -> 0 | D17: =D3*$B$17/24 -> 18.803021 | E17: =E3*$B$17/24 -> 9.2433542
A18: TPTCL Margin | B18: ='TNEB Charges'!B12 -> 0.02 | C18: =C3*$B$18*1000 -> 0 | D18: =D3*$B$18*1000 -> 267.5 | E18: =E3*$B$18*1000 -> 131.5
A19: CSS | B19: ='TNEB Charges'!B13 -> 1.99 | C19: =C9*$B$19 -> 0 | D19: =D9*$B$19 -> 24566.493 | E19: =E9*$B$19 -> 12076.613
A20: ASC | B20: ='TNEB Charges'!B14 -> 0 | C20: =C9*$B$20 -> 0 | D20: =D9*$B$20 -> 0 | E20: =E9*$B$20 -> 0
A21: Wheeling Charges | B21: ='TNEB Charges'!B15 -> 1.04 | C21: =C8*$B$21 -> 0 | D21: =D8*$B$21 -> 12838.77 | E21: =E8*$B$21 -> 6311.3955
A22: E-Tax | B22: ='TNEB Charges'!B16 -> 0 | C22: =C9*$B$22 -> 0 | D22: =D9*$B$22 -> 0 | E22: =E9*$B$22 -> 0
A23: Solar RPO Charges | B23: ='TNEB Charges'!B17 -> 0.12 | C23: 0 | D23: =D9*$B$23*10.5% -> 155.54664 | E23: =E9*$B$23*10.5% -> 76.464984
A24: Non-Solar RPO Charges | B24: ='TNEB Charges'!B18 -> 0.12 | C24: 0 | D24: =D9*$B$24*10.5% -> 155.54664 | E24: =E9*$B$24*10.5% -> 76.464984
A25: Total Statutory Charges | C25: =SUM(C11:C24) -> 0 | D25: =SUM(D11:D24) -> 48107.865 | E25: =SUM(E11:E24) -> 23743.966
C26: =C25/C9 -> #DIV/0! | D26: =D25/D9 -> 3.8969604 | E26: =E25/E9 -> 3.9125618
A27: Total Cost incurred in IEX Purchase | C27: =C4+C25 -> 0 | D27: =D4+D25 -> 104014.35 | E27: =E4+E25 -> 51979.346
A28: Cost per Unit incurred | C28: =C27/C9 -> #DIV/0! | D28: =D27/D9 -> 8.4256454 | E28: =E27/E9 -> 8.5652247
I29: Slot | J29: Morning peak | K29: Evening peak | L29: Normal hour | M29: Normal hour | N29: Night Hour | O29: RTC
A30: EQUIVALENT EB PRICE TO THE UNITS PURCHASED FROM IEX | J30: C1 | K30: C2 | L30: C4 | M30: C5 | N30: C24
A31: DAM | I31: TNEB Tariff | J31: =$L$31+($L$31*25%) -> 10.625 | K31: =$L$31+($L$31*25%) -> 10.625 | L31: 8.5 | M31: =$L$31-($L$31*5%) -> 8.075 | N31: 6.03 | O31: =AVERAGE(J31:M31) -> 9.45625
A32: Slot | B32: Price | C32: Purchase | D32: Delivered | E32: EB Cost | I32: E-Tax | J32: 0.05 | K32: 0.05 | L32: 0.05 | M32: 0.05 | N32: 0.05 | O32: 0.05
A33: C1 | B33: =J33 -> 11.15625 | C33: =J39+J46+J53 -> 0 | D33: =M39+M46+M53 -> 0 | E33: =D33*B33 -> 0 | I33: Total price/Unit | J33: =J31+(J31*J32) -> 11.15625 | K33: =K31+(K31*K32) -> 11.15625 | L33: =L31+(L31*L32) -> 8.925 | M33: =M31+(M31*M32) -> 8.47875 | N33: =N31+(N31*N32) -> 6.3315 | O33: =AVERAGE(J33:M33) -> 9.9290625
A34: C2 | B34: =K33 -> 11.15625 | C34: =J41+J48+J55 -> 11250 | D34: =M41+M48+M55 -> 10383.621 | E34: =D34*B34 -> 115842.27
A35: C4 | B35: =L33 -> 8.925 | C35: =J38+J40+J45+J47+J52+J54 -> 5575 | D35: =M38+M40+M45+M47+M52+M54 -> 5145.661 | E35: =D35*B35 -> 45925.024
A36: C5 | B36: =M33 -> 8.47875 | C36: =J37+J42+J44+J49+J51+J56 -> 3125 | D36: =M37+M42+M44+M49+M51+M56 -> 2884.3391 | E36: =D36*B36 -> 24455.59 | I36: GDAM
A37: Total | C37: =SUM(C33:C36) -> 19950 | D37: =SUM(D33:D36) -> 18413.621 | E37: =SUM(E33:E36) -> 186222.88 | H37: C5 | I37: =SUM('Energy Schedule'!AA7:AA26)/4 -> 0 | J37: =I37*1000 -> 0 | K37: =J37-(J37*$B$6) -> 0 | L37: =K37-(K37*$B$7) -> 0 | M37: =L37-(L37*$B$8) -> 0
H38: C4 | I38: =SUM('Energy Schedule'!AA27:AA30)/4 -> 0 | J38: =I38*1000 -> 0 | K38: =J38-(J38*$B$6) -> 0 | L38: =K38-(K38*$B$7) -> 0 | M38: =L38-(L38*$B$8) -> 0
H39: C1 | I39: =SUM('Energy Schedule'!AA31:AA46)/4 -> 0 | J39: =I39*1000 -> 0 | K39: =J39-(J39*$B$6) -> 0 | L39: =K39-(K39*$B$7) -> 0 | M39: =L39-(L39*$B$8) -> 0
H40: C4 | I40: =SUM('Energy Schedule'!AA47:AA78)/4 -> 0 | J40: =I40*1000 -> 0 | K40: =J40-(J40*$B$6) -> 0 | L40: =K40-(K40*$B$7) -> 0 | M40: =L40-(L40*$B$8) -> 0
H41: C2 | I41: =SUM('Energy Schedule'!AA79:AA94)/4 -> 0 | J41: =I41*1000 -> 0 | K41: =J41-(J41*$B$6) -> 0 | L41: =K41-(K41*$B$7) -> 0 | M41: =L41-(L41*$B$8) -> 0
A42: Total Purchase | B42: =C37 -> 19950 | C42: C1 | D42: 700 | H42: C5 | I42: =SUM('Energy Schedule'!AA95:AA102)/4 -> 0 | J42: =I42*1000 -> 0 | K42: =J42-(J42*$B$6) -> 0 | L42: =K42-(K42*$B$7) -> 0 | M42: =L42-(L42*$B$8) -> 0
A43: Delivered | B43: =D37 -> 18413.621 | C43: C2 | D43: 7850 | I43: DAM
A44: IEX Price | B44: =C27+D27+E27 -> 155993.7 | C44: C3 | D44: 2000 | H44: C5 | I44: =SUM('Energy Schedule'!AB7:AB26)/4 -> 2.5 | J44: =I44*1000 -> 2500 | K44: =J44-(J44*$B$6) -> 2409.75 | L44: =K44-(K44*$B$7) -> 2353.3618 | M44: =L44-(L44*$B$8) -> 2307.4713
A45: IEX Price / Unit | B45: =B44/B43 -> 8.4716471 | C45: C4 | D45: 20100 | H45: C4 | I45: =SUM('Energy Schedule'!AB27:AB30)/4 -> 0.375 | J45: =I45*1000 -> 375 | K45: =J45-(J45*$B$6) -> 361.4625 | L45: =K45-(K45*$B$7) -> 353.00428 | M45: =L45-(L45*$B$8) -> 346.12069
A46: EB Price | B46: =E37 -> 186222.88 | C46: C5 | D46: 2950 | H46: C1 | I46: =SUM('Energy Schedule'!AB31:AB46)/4 -> 0 | J46: =I46*1000 -> 0 | K46: =J46-(J46*$B$6) -> 0 | L46: =K46-(K46*$B$7) -> 0 | M46: =L46-(L46*$B$8) -> 0
A47: EB Price / Unit | B47: =B46/B43 -> 10.113322 | C47: Total | D47: =SUM(D42:D46) -> 33600 | H47: C4 | I47: =SUM('Energy Schedule'!AB47:AB78)/4 -> 2.5 | J47: =I47*1000 -> 2500 | K47: =J47-(J47*$B$6) -> 2409.75 | L47: =K47-(K47*$B$7) -> 2353.3618 | M47: =L47-(L47*$B$8) -> 2307.4713
A48: Cost Saving | B48: =B46-B44 -> 30229.187 | H48: C2 | I48: =SUM('Energy Schedule'!AB79:AB94)/4 -> 7.5 | J48: =I48*1000 -> 7500 | K48: =J48-(J48*$B$6) -> 7229.25 | L48: =K48-(K48*$B$7) -> 7060.0855 | M48: =L48-(L48*$B$8) -> 6922.4139
A49: Cost Savings Unit | B49: =B47-B45 -> 1.6416753 | H49: C5 | I49: =SUM('Energy Schedule'!AB95:AB102)/4 -> 0.5 | J49: =I49*1000 -> 500 | K49: =J49-(J49*$B$6) -> 481.95 | L49: =K49-(K49*$B$7) -> 470.67237 | M49: =L49-(L49*$B$8) -> 461.49426
I50: RTM
H51: C5 | I51: =SUM('Energy Schedule'!AC7:AC26)/4 -> 0 | J51: =I51*1000 -> 0 | K51: =J51-(J51*$B$6) -> 0 | L51: =K51-(K51*$B$7) -> 0 | M51: =L51-(L51*$B$8) -> 0
H52: C4 | I52: =SUM('Energy Schedule'!AC27:AC30)/4 -> 0 | J52: =I52*1000 -> 0 | K52: =J52-(J52*$B$6) -> 0 | L52: =K52-(K52*$B$7) -> 0 | M52: =L52-(L52*$B$8) -> 0
H53: C1 | I53: =SUM('Energy Schedule'!AC31:AC46)/4 -> 0 | J53: =I53*1000 -> 0 | K53: =J53-(J53*$B$6) -> 0 | L53: =K53-(K53*$B$7) -> 0 | M53: =L53-(L53*$B$8) -> 0
H54: C4 | I54: =SUM('Energy Schedule'!AC47:AC78)/4 -> 2.7 | J54: =I54*1000 -> 2700 | K54: =J54-(J54*$B$6) -> 2602.53 | L54: =K54-(K54*$B$7) -> 2541.6308 | M54: =L54-(L54*$B$8) -> 2492.069
H55: C2 | I55: =SUM('Energy Schedule'!AC79:AC94)/4 -> 3.75 | J55: =I55*1000 -> 3750 | K55: =J55-(J55*$B$6) -> 3614.625 | L55: =K55-(K55*$B$7) -> 3530.0428 | M55: =L55-(L55*$B$8) -> 3461.2069
H56: C5 | I56: =SUM('Energy Schedule'!AC95:AC102)/4 -> 0.125 | J56: =I56*1000 -> 125 | K56: =J56-(J56*$B$6) -> 120.4875 | L56: =K56-(K56*$B$7) -> 117.66809 | M56: =L56-(L56*$B$8) -> 115.37356

Sheet 10
C2: G-DAM | D2: DAM | E2: RTM
A3: Unit Purchased in MWh | C3: ='Energy Schedule'!AD$103 -> 0 | D3: ='Energy Schedule'!AE$103 -> 17.125 | E3: ='Energy Schedule'!AF$103 -> 0
A4: IEX Payout | C4: ='Energy Schedule'!AD$5 -> 0 | D4: ='Energy Schedule'!AE$5 -> 70274.661 | E4: ='Energy Schedule'!AF$5 -> 0
A5: Total Units in kWh | C5: =C3*1000 -> 0 | D5: =D3*1000 -> 17125 | E5: =E3*1000 -> 0 | I5: IEX Delivered | J5: Consumption | K5: Balance
A6: CTU | B6: ='Energy Schedule'!AE3 -> 0.0361 | C6: =C5-(C5*$B$6) -> 0 | D6: =D5-(D5*$B$6) -> 16506.787 | E6: =E5-(E5*$B$6) -> 0 | H6: C1 | I6: =D33 -> 230.74713 | J6: ='Consumption Details'!$B12 -> 2300 | K6: =J6-I6 -> 2069.2529
A7: STU | B7: ='TNEB Charges'!B1 -> 0.0234 | C7: =C6-(C6*$B$7) -> 0 | D7: =D6-(D6*$B$7) -> 16120.529 | E7: =E6-(E6*$B$7) -> 0 | H7: C2 | I7: =D34 -> 8306.8967 | J7: ='Consumption Details'!$C12 -> 9350 | K7: =J7-I7 -> 1043.1033
A8: Discom Losses | B8: ='TNEB Charges'!B2 -> 0.0195 | C8: =C7-(C7*$B$8) -> 0 | D8: =D7-(D7*$B$8) -> 15806.178 | E8: =E7-(E7*$B$8) -> 0 | H8: C4 | I8: =D35 -> 4153.4483 | J8: ='Consumption Details'!$D12 -> 20250 | K8: =J8-I8 -> 16096.552
A9: Delivered @ Bus | B9: ='TNEB Charges'!B3 -> 0 | C9: =C8 -> 0 | D9: =D8 -> 15806.178 | E9: =E8 -> 0 | H9: C5 | I9: =D36 -> 3115.0862 | J9: ='Consumption Details'!$E12 -> 3650 | K9: =J9-I9 -> 534.91375
A10: IEX Payout / Unit | B10: ='TNEB Charges'!B4 -> 0 | C10: =C4/C9 -> #DIV/0! | D10: =D4/D9 -> 4.4460248 | E10: =E4/E9 -> #DIV/0!
A11: IEX Transaction Charges | B11: ='TNEB Charges'!B5 -> 0.02 | C11: =(C3*1000*$B$11)+(C3*1000*$B$11*18%) -> 0 | D11: =(D3*1000*$B$11)+(D3*1000*$B$11*18%) -> 404.15 | E11: =(E3*1000*$B$11)+(E3*1000*$B$11*18%) -> 0
A12: NLDC Application fee | B12: ='TNEB Charges'!B6 -> 0 | C12: ='Energy Schedule'!AD$6 -> 0 | D12: ='Energy Schedule'!AE$6 -> 7.91 | E12: ='Energy Schedule'!AF$6 -> 0
A13: CTU Transmission Charges | B13: ='TNEB Charges'!B7 -> 457.6 | C13: =C3*$B$13 -> 0 | D13: =D3*$B$13 -> 7836.4 | E13: =E3*$B$13 -> 0
A14: NLDC Sched & Oprn Charges | B14: ='TNEB Charges'!B8 -> 1 | C14: =C3*$B$14 -> 0 | D14: =D3*$B$14 -> 17.125 | E14: =E3*$B$14 -> 0
A15: STU Transmission Charges | B15: ='TNEB Charges'!B9 -> 260 | C15: =C3*$B$15 -> 0 | D15: =D3*$B$15 -> 4452.5 | E15: =E3*$B$15 -> 0
A16: STU Scheduling | B16: ='TNEB Charges'!B10 -> 170 | C16: =IF(C3>0,$B$16,0) -> 0 | D16: =IF(D3>0,$B$16,0) -> 170 | E16: =IF(E3>0,$B$16,0) -> 0
A17: STU System Operating Charge | B17: ='TNEB Charges'!B11 -> 33.74 | C17: =C3*$B$17/24 -> 0 | D17: =D3*$B$17/24 -> 24.074896 | E17: =E3*$B$17/24 -> 0
A18: TPTCL Margin | B18: ='TNEB Charges'!B12 -> 0.02 | C18: =C3*$B$18*1000 -> 0 | D18: =D3*$B$18*1000 -> 342.5 | E18: =E3*$B$18*1000 -> 0
A19: CSS | B19: ='TNEB Charges'!B13 -> 1.99 | C19: =C9*$B$19 -> 0 | D19: =D9*$B$19 -> 31454.295 | E19: =E9*$B$19 -> 0
A20: ASC | B20: ='TNEB Charges'!B14 -> 0 | C20: =C9*$B$20 -> 0 | D20: =D9*$B$20 -> 0 | E20: =E9*$B$20 -> 0
A21: Wheeling Charges | B21: ='TNEB Charges'!B15 -> 1.04 | C21: =C8*$B$21 -> 0 | D21: =D8*$B$21 -> 16438.425 | E21: =E8*$B$21 -> 0
A22: E-Tax | B22: ='TNEB Charges'!B16 -> 0 | C22: =C9*$B$22 -> 0 | D22: =D9*$B$22 -> 0 | E22: =E9*$B$22 -> 0
A23: Solar RPO Charges | B23: ='TNEB Charges'!B17 -> 0.12 | C23: 0 | D23: =D9*$B$23*10.5% -> 199.15785 | E23: =E9*$B$23*10.5% -> 0
A24: Non-Solar RPO Charges | B24: ='TNEB Charges'!B18 -> 0.12 | C24: 0 | D24: =D9*$B$24*10.5% -> 199.15785 | E24: =E9*$B$24*10.5% -> 0
A25: Total Statutory Charges | C25: =SUM(C11:C24) -> 0 | D25: =SUM(D11:D24) -> 61545.696 | E25: =SUM(E11:E24) -> 0
C26: =C25/C9 -> #DIV/0! | D26: =D25/D9 -> 3.8937746 | E26: =E25/E9 -> #DIV/0!
A27: Total Cost incurred in IEX Purchase | C27: =C4+C25 -> 0 | D27: =D4+D25 -> 131820.36 | E27: =E4+E25 -> 0
A28: Cost per Unit incurred | C28: =C27/C9 -> #DIV/0! | D28: =D27/D9 -> 8.3397994 | E28: =E27/E9 -> #DIV/0!
I29: Slot | J29: Morning peak | K29: Evening peak | L29: Normal hour | M29: Normal hour | N29: Night Hour | O29: RTC
A30: EQUIVALENT EB PRICE TO THE UNITS PURCHASED FROM IEX | J30: C1 | K30: C2 | L30: C4 | M30: C5 | N30: C24
A31: DAM | I31: TNEB Tariff | J31: =$L$31+($L$31*25%) -> 10.625 | K31: =$L$31+($L$31*25%) -> 10.625 | L31: 8.5 | M31: =$L$31-($L$31*5%) -> 8.075 | N31: 6.03 | O31: =AVERAGE(J31:M31) -> 9.45625
A32: Slot | B32: Price | C32: Purchase | D32: Delivered | E32: EB Cost | I32: E-Tax | J32: 0.05 | K32: 0.05 | L32: 0.05 | M32: 0.05 | N32: 0.05 | O32: 0.05
A33: C1 | B33: =J33 -> 11.15625 | C33: =J39+J46+J53 -> 250 | D33: =M39+M46+M53 -> 230.74713 | E33: =D33*B33 -> 2574.2727 | I33: Total price/Unit | J33: =J31+(J31*J32) -> 11.15625 | K33: =K31+(K31*K32) -> 11.15625 | L33: =L31+(L31*L32) -> 8.925 | M33: =M31+(M31*M32) -> 8.47875 | N33: =N31+(N31*N32) -> 6.3315 | O33: =AVERAGE(J33:M33) -> 9.9290625
A34: C2 | B34: =K33 -> 11.15625 | C34: =J41+J48+J55 -> 9000 | D34: =M41+M48+M55 -> 8306.8967 | E34: =D34*B34 -> 92673.816
A35: C4 | B35: =L33 -> 8.925 | C35: =J38+J40+J45+J47+J52+J54 -> 4500 | D35: =M38+M40+M45+M47+M52+M54 -> 4153.4483 | E35: =D35*B35 -> 37069.526
A36: C5 | B36: =M33 -> 8.47875 | C36: =J37+J42+J44+J49+J51+J56 -> 3375 | D36: =M37+M42+M44+M49+M51+M56 -> 3115.0862 | E36: =D36*B36 -> 26412.038 | I36: GDAM
A37: Total | C37: =SUM(C33:C36) -> 17125 | D37: =SUM(D33:D36) -> 15806.178 | E37: =SUM(E33:E36) -> 158729.65 | H37: C5 | I37: =SUM('Energy Schedule'!AD7:AD26)/4 -> 0 | J37: =I37*1000 -> 0 | K37: =J37-(J37*$B$6) -> 0 | L37: =K37-(K37*$B$7) -> 0 | M37: =L37-(L37*$B$8) -> 0
H38: C4 | I38: =SUM('Energy Schedule'!AD27:AD30)/4 -> 0 | J38: =I38*1000 -> 0 | K38: =J38-(J38*$B$6) -> 0 | L38: =K38-(K38*$B$7) -> 0 | M38: =L38-(L38*$B$8) -> 0
H39: C1 | I39: =SUM('Energy Schedule'!AD31:AD46)/4 -> 0 | J39: =I39*1000 -> 0 | K39: =J39-(J39*$B$6) -> 0 | L39: =K39-(K39*$B$7) -> 0 | M39: =L39-(L39*$B$8) -> 0
H40: C4 | I40: =SUM('Energy Schedule'!AD47:AD78)/4 -> 0 | J40: =I40*1000 -> 0 | K40: =J40-(J40*$B$6) -> 0 | L40: =K40-(K40*$B$7) -> 0 | M40: =L40-(L40*$B$8) -> 0
H41: C2 | I41: =SUM('Energy Schedule'!AD79:AD94)/4 -> 0 | J41: =I41*1000 -> 0 | K41: =J41-(J41*$B$6) -> 0 | L41: =K41-(K41*$B$7) -> 0 | M41: =L41-(L41*$B$8) -> 0
A42: Total Purchase | B42: =C37 -> 17125 | C42: C1 | D42: 700 | H42: C5 | I42: =SUM('Energy Schedule'!AD95:AD102)/4 -> 0 | J42: =I42*1000 -> 0 | K42: =J42-(J42*$B$6) -> 0 | L42: =K42-(K42*$B$7) -> 0 | M42: =L42-(L42*$B$8) -> 0
A43: Delivered | B43: =D37 -> 15806.178 | C43: C2 | D43: 7850 | I43: DAM
A44: IEX Price | B44: =C27+D27+E27 -> 131820.36 | C44: C3 | D44: 2000 | H44: C5 | I44: =SUM('Energy Schedule'!AE7:AE26)/4 -> 2.5 | J44: =I44*1000 -> 2500 | K44: =J44-(J44*$B$6) -> 2409.75 | L44: =K44-(K44*$B$7) -> 2353.3618 | M44: =L44-(L44*$B$8) -> 2307.4713
A45: IEX Price / Unit | B45: =B44/B43 -> 8.3397994 | C45: C4 | D45: 20100 | H45: C4 | I45: =SUM('Energy Schedule'!AE27:AE30)/4 -> 0.5 | J45: =I45*1000 -> 500 | K45: =J45-(J45*$B$6) -> 481.95 | L45: =K45-(K45*$B$7) -> 470.67237 | M45: =L45-(L45*$B$8) -> 461.49426
A46: EB Price | B46: =E37 -> 158729.65 | C46: C5 | D46: 2950 | H46: C1 | I46: =SUM('Energy Schedule'!AE31:AE46)/4 -> 0.25 | J46: =I46*1000 -> 250 | K46: =J46-(J46*$B$6) -> 240.975 | L46: =K46-(K46*$B$7) -> 235.33619 | M46: =L46-(L46*$B$8) -> 230.74713
A47: EB Price / Unit | B47: =B46/B43 -> 10.042254 | C47: Total | D47: =SUM(D42:D46) -> 33600 | H47: C4 | I47: =SUM('Energy Schedule'!AE47:AE78)/4 -> 4 | J47: =I47*1000 -> 4000 | K47: =J47-(J47*$B$6) -> 3855.6 | L47: =K47-(K47*$B$7) -> 3765.379 | M47: =L47-(L47*$B$8) -> 3691.9541
A48: Cost Saving | B48: =B46-B44 -> 26909.296 | H48: C2 | I48: =SUM('Energy Schedule'!AE79:AE94)/4 -> 9 | J48: =I48*1000 -> 9000 | K48: =J48-(J48*$B$6) -> 8675.1 | L48: =K48-(K48*$B$7) -> 8472.1027 | M48: =L48-(L48*$B$8) -> 8306.8967
A49: Cost Savings Unit | B49: =B47-B45 -> 1.7024543 | H49: C5 | I49: =SUM('Energy Schedule'!AE95:AE102)/4 -> 0.875 | J49: =I49*1000 -> 875 | K49: =J49-(J49*$B$6) -> 843.4125 | L49: =K49-(K49*$B$7) -> 823.67665 | M49: =L49-(L49*$B$8) -> 807.61495
I50: RTM
H51: C5 | I51: =SUM('Energy Schedule'!AF7:AF26)/4 -> 0 | J51: =I51*1000 -> 0 | K51: =J51-(J51*$B$6) -> 0 | L51: =K51-(K51*$B$7) -> 0 | M51: =L51-(L51*$B$8) -> 0
H52: C4 | I52: =SUM('Energy Schedule'!AF27:AF30)/4 -> 0 | J52: =I52*1000 -> 0 | K52: =J52-(J52*$B$6) -> 0 | L52: =K52-(K52*$B$7) -> 0 | M52: =L52-(L52*$B$8) -> 0
H53: C1 | I53: =SUM('Energy Schedule'!AF31:AF46)/4 -> 0 | J53: =I53*1000 -> 0 | K53: =J53-(J53*$B$6) -> 0 | L53: =K53-(K53*$B$7) -> 0 | M53: =L53-(L53*$B$8) -> 0
H54: C4 | I54: =SUM('Energy Schedule'!AF47:AF78)/4 -> 0 | J54: =I54*1000 -> 0 | K54: =J54-(J54*$B$6) -> 0 | L54: =K54-(K54*$B$7) -> 0 | M54: =L54-(L54*$B$8) -> 0
H55: C2 | I55: =SUM('Energy Schedule'!AF79:AF94)/4 -> 0 | J55: =I55*1000 -> 0 | K55: =J55-(J55*$B$6) -> 0 | L55: =K55-(K55*$B$7) -> 0 | M55: =L55-(L55*$B$8) -> 0
H56: C5 | I56: =SUM('Energy Schedule'!AF95:AF102)/4 -> 0 | J56: =I56*1000 -> 0 | K56: =J56-(J56*$B$6) -> 0 | L56: =K56-(K56*$B$7) -> 0 | M56: =L56-(L56*$B$8) -> 0

Sheet 11
C2: G-DAM | D2: DAM | E2: RTM
A3: Unit Purchased in MWh | C3: ='Energy Schedule'!AG$103 -> 0 | D3: ='Energy Schedule'!AH$103 -> 26.625 | E3: ='Energy Schedule'!AI$103 -> 7.6
A4: IEX Payout | C4: ='Energy Schedule'!AG$5 -> 0 | D4: ='Energy Schedule'!AH$5 -> 98538.321 | E4: ='Energy Schedule'!AI$5 -> 27909.59
A5: Total Units in kWh | C5: =C3*1000 -> 0 | D5: =D3*1000 -> 26625 | E5: =E3*1000 -> 7600 | I5: IEX Delivered | J5: Consumption | K5: Balance
A6: CTU | B6: ='Energy Schedule'!AH3 -> 0.0361 | C6: =C5-(C5*$B$6) -> 0 | D6: =D5-(D5*$B$6) -> 25663.838 | E6: =E5-(E5*$B$6) -> 7325.64 | H6: C1 | I6: =D33 -> 576.86782 | J6: ='Consumption Details'!$B13 -> 2000 | K6: =J6-I6 -> 1423.1322
A7: STU | B7: ='TNEB Charges'!B1 -> 0.0234 | C7: =C6-(C6*$B$7) -> 0 | D7: =D6-(D6*$B$7) -> 25063.304 | E7: =E6-(E6*$B$7) -> 7154.22 | H7: C2 | I7: =D34 -> 12183.448 | J7: ='Consumption Details'!$C13 -> 10850 | K7: =J7-I7 -> -1333.4484
A8: Discom Losses | B8: ='TNEB Charges'!B2 -> 0.0195 | C8: =C7-(C7*$B$8) -> 0 | D8: =D7-(D7*$B$8) -> 24574.569 | E8: =E7-(E7*$B$8) -> 7014.7127 | H8: C4 | I8: =D35 -> 15413.908 | J8: ='Consumption Details'!$D13 -> 20650 | K8: =J8-I8 -> 5236.0918
A9: Delivered @ Bus | B9: ='TNEB Charges'!B3 -> 0 | C9: =C8 -> 0 | D9: =D8 -> 24574.569 | E9: =E8 -> 7014.7127 | H9: C5 | I9: =D36 -> 3415.0575 | J9: ='Consumption Details'!$E13 -> 3650 | K9: =J9-I9 -> 234.94248
A10: IEX Payout / Unit | B10: ='TNEB Charges'!B4 -> 0 | C10: =C4/C9 -> #DIV/0! | D10: =D4/D9 -> 4.009768 | E10: =E4/E9 -> 3.9787217
A11: IEX Transaction Charges | B11: ='TNEB Charges'!B5 -> 0.02 | C11: =(C3*1000*$B$11)+(C3*1000*$B$11*18%) -> 0 | D11: =(D3*1000*$B$11)+(D3*1000*$B$11*18%) -> 628.35 | E11: =(E3*1000*$B$11)+(E3*1000*$B$11*18%) -> 179.36
A12: NLDC Application fee | B12: ='TNEB Charges'!B6 -> 0 | C12: ='Energy Schedule'!AG$6 -> 0 | D12: ='Energy Schedule'!AH$6 -> 7.36 | E12: ='Energy Schedule'!AI$6 -> 12.92
A13: CTU Transmission Charges | B13: ='TNEB Charges'!B7 -> 457.6 | C13: =C3*$B$13 -> 0 | D13: =D3*$B$13 -> 12183.6 | E13: =E3*$B$13 -> 3477.76
A14: NLDC Sched & Oprn Charges | B14: ='TNEB Charges'!B8 -> 1 | C14: =C3*$B$14 -> 0 | D14: =D3*$B$14 -> 26.625 | E14: =E3*$B$14 -> 7.6
A15: STU Transmission Charges | B15: ='TNEB Charges'!B9 -> 260 | C15: =C3*$B$15 -> 0 | D15: =D3*$B$15 -> 6922.5 | E15: =E3*$B$15 -> 1976
A16: STU Scheduling | B16: ='TNEB Charges'!B10 -> 170 | C16: =IF(C3>0,$B$16,0) -> 0 | D16: =IF(D3>0,$B$16,0) -> 170 | E16: =IF(E3>0,$B$16,0) -> 170
A17: STU System Operating Charge | B17: ='TNEB Charges'!B11 -> 33.74 | C17: =C3*$B$17/24 -> 0 | D17: =D3*$B$17/24 -> 37.430313 | E17: =E3*$B$17/24 -> 10.684333
A18: TPTCL Margin | B18: ='TNEB Charges'!B12 -> 0.02 | C18: =C3*$B$18*1000 -> 0 | D18: =D3*$B$18*1000 -> 532.5 | E18: =E3*$B$18*1000 -> 152
A19: CSS | B19: ='TNEB Charges'!B13 -> 1.99 | C19: =C9*$B$19 -> 0 | D19: =D9*$B$19 -> 48903.393 | E19: =E9*$B$19 -> 13959.278
A20: ASC | B20: ='TNEB Charges'!B14 -> 0 | C20: =C9*$B$20 -> 0 | D20: =D9*$B$20 -> 0 | E20: =E9*$B$20 -> 0
A21: Wheeling Charges | B21: ='TNEB Charges'!B15 -> 1.04 | C21: =C8*$B$21 -> 0 | D21: =D8*$B$21 -> 25557.552 | E21: =E8*$B$21 -> 7295.3012
A22: E-Tax | B22: ='TNEB Charges'!B16 -> 0 | C22: =C9*$B$22 -> 0 | D22: =D9*$B$22 -> 0 | E22: =E9*$B$22 -> 0
A23: Solar RPO Charges | B23: ='TNEB Charges'!B17 -> 0.12 | C23: 0 | D23: =D9*$B$23*10.5% -> 309.63957 | E23: =E9*$B$23*10.5% -> 88.38538
A24: Non-Solar RPO Charges | B24: ='TNEB Charges'!B18 -> 0.12 | C24: 0 | D24: =D9*$B$24*10.5% -> 309.63957 | E24: =E9*$B$24*10.5% -> 88.38538
A25: Total Statutory Charges | C25: =SUM(C11:C24) -> 0 | D25: =SUM(D11:D24) -> 95588.589 | E25: =SUM(E11:E24) -> 27417.675
C26: =C25/C9 -> #DIV/0! | D26: =D25/D9 -> 3.8897361 | E26: =E25/E9 -> 3.9085955
A27: Total Cost incurred in IEX Purchase | C27: =C4+C25 -> 0 | D27: =D4+D25 -> 194126.91 | E27: =E4+E25 -> 55327.265
A28: Cost per Unit incurred | C28: =C27/C9 -> #DIV/0! | D28: =D27/D9 -> 7.8995041 | E28: =E27/E9 -> 7.8873172
I29: Slot | J29: Morning peak | K29: Evening peak | L29: Normal hour | M29: Normal hour | N29: Night Hour | O29: RTC
A30: EQUIVALENT EB PRICE TO THE UNITS PURCHASED FROM IEX | J30: C1 | K30: C2 | L30: C4 | M30: C5 | N30: C24
A31: DAM | I31: TNEB Tariff | J31: =$L$31+($L$31*25%) -> 10.625 | K31: =$L$31+($L$31*25%) -> 10.625 | L31: 8.5 | M31: =$L$31-($L$31*5%) -> 8.075 | N31: 6.03 | O31: =AVERAGE(J31:M31) -> 9.45625
A32: Slot | B32: Price | C32: Purchase | D32: Delivered | E32: EB Cost | I32: E-Tax | J32: 0.05 | K32: 0.05 | L32: 0.05 | M32: 0.05 | N32: 0.05 | O32: 0.05
A33: C1 | B33: =J33 -> 11.15625 | C33: =J39+J46+J53 -> 625 | D33: =M39+M46+M53 -> 576.86782 | E33: =D33*B33 -> 6435.6817 | I33: Total price/Unit | J33: =J31+(J31*J32) -> 11.15625 | K33: =K31+(K31*K32) -> 11.15625 | L33: =L31+(L31*L32) -> 8.925 | M33: =M31+(M31*M32) -> 8.47875 | N33: =N31+(N31*N32) -> 6.3315 | O33: =AVERAGE(J33:M33) -> 9.9290625
A34: C2 | B34: =K33 -> 11.15625 | C34: =J41+J48+J55 -> 13200 | D34: =M41+M48+M55 -> 12183.448 | E34: =D34*B34 -> 135921.6
A35: C4 | B35: =L33 -> 8.925 | C35: =J38+J40+J45+J47+J52+J54 -> 16700 | D35: =M38+M40+M45+M47+M52+M54 -> 15413.908 | E35: =D35*B35 -> 137569.13
A36: C5 | B36: =M33 -> 8.47875 | C36: =J37+J42+J44+J49+J51+J56 -> 3700 | D36: =M37+M42+M44+M49+M51+M56 -> 3415.0575 | E36: =D36*B36 -> 28955.419 | I36: GDAM
A37: Total | C37: =SUM(C33:C36) -> 34225 | D37: =SUM(D33:D36) -> 31589.282 | E37: =SUM(E33:E36) -> 308881.83 | H37: C5 | I37: =SUM('Energy Schedule'!AG7:AG26)/4 -> 0 | J37: =I37*1000 -> 0 | K37: =J37-(J37*$B$6) -> 0 | L37: =K37-(K37*$B$7) -> 0 | M37: =L37-(L37*$B$8) -> 0
H38: C4 | I38: =SUM('Energy Schedule'!AG27:AG30)/4 -> 0 | J38: =I38*1000 -> 0 | K38: =J38-(J38*$B$6) -> 0 | L38: =K38-(K38*$B$7) -> 0 | M38: =L38-(L38*$B$8) -> 0
H39: C1 | I39: =SUM('Energy Schedule'!AG31:AG46)/4 -> 0 | J39: =I39*1000 -> 0 | K39: =J39-(J39*$B$6) -> 0 | L39: =K39-(K39*$B$7) -> 0 | M39: =L39-(L39*$B$8) -> 0
H40: C4 | I40: =SUM('Energy Schedule'!AG47:AG78)/4 -> 0 | J40: =I40*1000 -> 0 | K40: =J40-(J40*$B$6) -> 0 | L40: =K40-(K40*$B$7) -> 0 | M40: =L40-(L40*$B$8) -> 0
H41: C2 | I41: =SUM('Energy Schedule'!AG79:AG94)/4 -> 0 | J41: =I41*1000 -> 0 | K41: =J41-(J41*$B$6) -> 0 | L41: =K41-(K41*$B$7) -> 0 | M41: =L41-(L41*$B$8) -> 0
A42: Total Purchase | B42: =C37 -> 34225 | C42: C1 | D42: 700 | H42: C5 | I42: =SUM('Energy Schedule'!AG95:AG102)/4 -> 0 | J42: =I42*1000 -> 0 | K42: =J42-(J42*$B$6) -> 0 | L42: =K42-(K42*$B$7) -> 0 | M42: =L42-(L42*$B$8) -> 0
A43: Delivered | B43: =D37 -> 31589.282 | C43: C2 | D43: 7850 | I43: DAM
A44: IEX Price | B44: =C27+D27+E27 -> 249454.18 | C44: C3 | D44: 2000 | H44: C5 | I44: =SUM('Energy Schedule'!AH7:AH26)/4 -> 2.5 | J44: =I44*1000 -> 2500 | K44: =J44-(J44*$B$6) -> 2409.75 | L44: =K44-(K44*$B$7) -> 2353.3618 | M44: =L44-(L44*$B$8) -> 2307.4713
A45: IEX Price / Unit | B45: =B44/B43 -> 7.8967979 | C45: C4 | D45: 20100 | H45: C4 | I45: =SUM('Energy Schedule'!AH27:AH30)/4 -> 0.5 | J45: =I45*1000 -> 500 | K45: =J45-(J45*$B$6) -> 481.95 | L45: =K45-(K45*$B$7) -> 470.67237 | M45: =L45-(L45*$B$8) -> 461.49426
A46: EB Price | B46: =E37 -> 308881.83 | C46: C5 | D46: 2950 | H46: C1 | I46: =SUM('Energy Schedule'!AH31:AH46)/4 -> 0.625 | J46: =I46*1000 -> 625 | K46: =J46-(J46*$B$6) -> 602.4375 | L46: =K46-(K46*$B$7) -> 588.34046 | M46: =L46-(L46*$B$8) -> 576.86782
A47: EB Price / Unit | B47: =B46/B43 -> 9.7780579 | C47: Total | D47: =SUM(D42:D46) -> 33600 | H47: C4 | I47: =SUM('Energy Schedule'!AH47:AH78)/4 -> 10 | J47: =I47*1000 -> 10000 | K47: =J47-(J47*$B$6) -> 9639 | L47: =K47-(K47*$B$7) -> 9413.4474 | M47: =L47-(L47*$B$8) -> 9229.8852
A48: Cost Saving | B48: =B46-B44 -> 59427.653 | H48: C2 | I48: =SUM('Energy Schedule'!AH79:AH94)/4 -> 12 | J48: =I48*1000 -> 12000 | K48: =J48-(J48*$B$6) -> 11566.8 | L48: =K48-(K48*$B$7) -> 11296.137 | M48: =L48-(L48*$B$8) -> 11075.862
A49: Cost Savings Unit | B49: =B47-B45 -> 1.88126 | H49: C5 | I49: =SUM('Energy Schedule'!AH95:AH102)/4 -> 1 | J49: =I49*1000 -> 1000 | K49: =J49-(J49*$B$6) -> 963.9 | L49: =K49-(K49*$B$7) -> 941.34474 | M49: =L49-(L49*$B$8) -> 922.98852
I50: RTM
H51: C5 | I51: =SUM('Energy Schedule'!AI7:AI26)/4 -> 0 | J51: =I51*1000 -> 0 | K51: =J51-(J51*$B$6) -> 0 | L51: =K51-(K51*$B$7) -> 0 | M51: =L51-(L51*$B$8) -> 0
H52: C4 | I52: =SUM('Energy Schedule'!AI27:AI30)/4 -> 0 | J52: =I52*1000 -> 0 | K52: =J52-(J52*$B$6) -> 0 | L52: =K52-(K52*$B$7) -> 0 | M52: =L52-(L52*$B$8) -> 0
H53: C1 | I53: =SUM('Energy Schedule'!AI31:AI46)/4 -> 0 | J53: =I53*1000 -> 0 | K53: =J53-(J53*$B$6) -> 0 | L53: =K53-(K53*$B$7) -> 0 | M53: =L53-(L53*$B$8) -> 0
H54: C4 | I54: =SUM('Energy Schedule'!AI47:AI78)/4 -> 6.2 | J54: =I54*1000 -> 6200 | K54: =J54-(J54*$B$6) -> 5976.18 | L54: =K54-(K54*$B$7) -> 5836.3374 | M54: =L54-(L54*$B$8) -> 5722.5288
H55: C2 | I55: =SUM('Energy Schedule'!AI79:AI94)/4 -> 1.2 | J55: =I55*1000 -> 1200 | K55: =J55-(J55*$B$6) -> 1156.68 | L55: =K55-(K55*$B$7) -> 1129.6137 | M55: =L55-(L55*$B$8) -> 1107.5862
H56: C5 | I56: =SUM('Energy Schedule'!AI95:AI102)/4 -> 0.2 | J56: =I56*1000 -> 200 | K56: =J56-(J56*$B$6) -> 192.78 | L56: =K56-(K56*$B$7) -> 188.26895 | M56: =L56-(L56*$B$8) -> 184.5977

Sheet 12
C2: G-DAM | D2: DAM | E2: RTM
A3: Unit Purchased in MWh | C3: ='Energy Schedule'!AJ$103 -> 0 | D3: ='Energy Schedule'!AK$103 -> 16.75 | E3: ='Energy Schedule'!AL$103 -> 5.2
A4: IEX Payout | C4: ='Energy Schedule'!AJ$5 -> 0 | D4: ='Energy Schedule'!AK$5 -> 63830.988 | E4: ='Energy Schedule'!AL$5 -> 24341.29
A5: Total Units in kWh | C5: =C3*1000 -> 0 | D5: =D3*1000 -> 16750 | E5: =E3*1000 -> 5200 | I5: IEX Delivered | J5: Consumption | K5: Balance
A6: CTU | B6: ='Savings Sheet'!B5 -> 0.0343 | C6: =C5-(C5*$B$6) -> 0 | D6: =D5-(D5*$B$6) -> 16175.475 | E6: =E5-(E5*$B$6) -> 5021.64 | H6: C1 | I6: =D33 -> 786.0053 | J6: ='Consumption Details'!$B14 -> 2700 | K6: =J6-I6 -> 1913.9947
A7: STU | B7: ='TNEB Charges'!B1 -> 0.0234 | C7: =C6-(C6*$B$7) -> 0 | D7: =D6-(D6*$B$7) -> 15796.969 | E7: =E6-(E6*$B$7) -> 4904.1336 | H7: C2 | I7: =D34 -> 11096.545 | J7: ='Consumption Details'!$C14 -> 9150 | K7: =J7-I7 -> -1946.5454
A8: Discom Losses | B8: ='TNEB Charges'!B2 -> 0.0195 | C8: =C7-(C7*$B$8) -> 0 | D8: =D7-(D7*$B$8) -> 15488.928 | E8: =E7-(E7*$B$8) -> 4808.503 | H8: C4 | I8: =D35 -> 5178.3879 | J8: ='Consumption Details'!$D14 -> 15600 | K8: =J8-I8 -> 10421.612
A9: Delivered @ Bus | B9: ='TNEB Charges'!B3 -> 0 | C9: =C8 -> 0 | D9: =D8 -> 15488.928 | E9: =E8 -> 4808.503 | H9: C5 | I9: =D36 -> 3236.4924 | J9: ='Consumption Details'!$E14 -> 3200 | K9: =J9-I9 -> -36.492416
A10: IEX Payout / Unit | B10: ='TNEB Charges'!B4 -> 0 | C10: =C4/C9 -> #DIV/0! | D10: =D4/D9 -> 4.1210721 | E10: =E4/E9 -> 5.0621347
A11: IEX Transaction Charges | B11: ='TNEB Charges'!B5 -> 0.02 | C11: =(C3*1000*$B$11)+(C3*1000*$B$11*18%) -> 0 | D11: =(D3*1000*$B$11)+(D3*1000*$B$11*18%) -> 395.3 | E11: =(E3*1000*$B$11)+(E3*1000*$B$11*18%) -> 122.72
A12: NLDC Application fee | B12: ='TNEB Charges'!B6 -> 0 | C12: ='Energy Schedule'!AJ$6 -> 0 | D12: ='Energy Schedule'!AK$6 -> 7.44 | E12: ='Energy Schedule'!AL$6 -> 11.74
A13: CTU Transmission Charges | B13: ='TNEB Charges'!B7 -> 457.6 | C13: =C3*$B$13 -> 0 | D13: =D3*$B$13 -> 7664.8 | E13: =E3*$B$13 -> 2379.52
A14: NLDC Sched & Oprn Charges | B14: ='TNEB Charges'!B8 -> 1 | C14: =C3*$B$14 -> 0 | D14: =D3*$B$14 -> 16.75 | E14: =E3*$B$14 -> 5.2
A15: STU Transmission Charges | B15: ='TNEB Charges'!B9 -> 260 | C15: =C3*$B$15 -> 0 | D15: =D3*$B$15 -> 4355 | E15: =E3*$B$15 -> 1352
A16: STU Scheduling | B16: ='TNEB Charges'!B10 -> 170 | C16: =IF(C3>0,$B$16,0) -> 0 | D16: =IF(D3>0,$B$16,0) -> 170 | E16: =IF(E3>0,$B$16,0) -> 170
A17: STU System Operating Charge | B17: ='TNEB Charges'!B11 -> 33.74 | C17: =C3*$B$17/24 -> 0 | D17: =D3*$B$17/24 -> 23.547708 | E17: =E3*$B$17/24 -> 7.3103333
A18: TPTCL Margin | B18: ='TNEB Charges'!B12 -> 0.02 | C18: =C3*$B$18*1000 -> 0 | D18: =D3*$B$18*1000 -> 335 | E18: =E3*$B$18*1000 -> 104
A19: CSS | B19: ='TNEB Charges'!B13 -> 1.99 | C19: =C9*$B$19 -> 0 | D19: =D9*$B$19 -> 30822.967 | E19: =E9*$B$19 -> 9568.921
A20: ASC | B20: ='TNEB Charges'!B14 -> 0 | C20: =C9*$B$20 -> 0 | D20: =D9*$B$20 -> 0 | E20: =E9*$B$20 -> 0
A21: Wheeling Charges | B21: ='TNEB Charges'!B15 -> 1.04 | C21: =C8*$B$21 -> 0 | D21: =D8*$B$21 -> 16108.485 | E21: =E8*$B$21 -> 5000.8431
A22: E-Tax | B22: ='TNEB Charges'!B16 -> 0 | C22: =C9*$B$22 -> 0 | D22: =D9*$B$22 -> 0 | E22: =E9*$B$22 -> 0
A23: Solar RPO Charges | B23: ='TNEB Charges'!B17 -> 0.12 | C23: 0 | D23: =D9*$B$23*10.5% -> 195.16049 | E23: =E9*$B$23*10.5% -> 60.587138
A24: Non-Solar RPO Charges | B24: ='TNEB Charges'!B18 -> 0.12 | C24: 0 | D24: =D9*$B$24*10.5% -> 195.16049 | E24: =E9*$B$24*10.5% -> 60.587138
A25: Total Statutory Charges | C25: =SUM(C11:C24) -> 0 | D25: =SUM(D11:D24) -> 60289.611 | E25: =SUM(E11:E24) -> 18843.429
C26: =C25/C9 -> #DIV/0! | D26: =D25/D9 -> 3.8924327 | E26: =E25/E9 -> 3.9187724
A27: Total Cost incurred in IEX Purchase | C27: =C4+C25 -> 0 | D27: =D4+D25 -> 124120.6 | E27: =E4+E25 -> 43184.719
A28: Cost per Unit incurred | C28: =C27/C9 -> #DIV/0! | D28: =D27/D9 -> 8.0135048 | E28: =E27/E9 -> 8.9809071
I29: Slot | J29: Morning peak | K29: Evening peak | L29: Normal hour | M29: Normal hour | N29: Night Hour | O29: RTC
A30: EQUIVALENT EB PRICE TO THE UNITS PURCHASED FROM IEX | J30: C1 | K30: C2 | L30: C4 | M30: C5 | N30: C24
A31: DAM | I31: TNEB Tariff | J31: =$L$31+($L$31*25%) -> 10.625 | K31: =$L$31+($L$31*25%) -> 10.625 | L31: 8.5 | M31: =$L$31-($L$31*5%) -> 8.075 | N31: 6.03 | O31: =AVERAGE(J31:M31) -> 9.45625
A32: Slot | B32: Price | C32: Purchase | D32: Delivered | E32: EB Cost | I32: E-Tax | J32: 0.05 | K32: 0.05 | L32: 0.05 | M32: 0.05 | N32: 0.05 | O32: 0.05
A33: C1 | B33: =J33 -> 11.15625 | C33: =J39+J46+J53 -> 850 | D33: =M39+M46+M53 -> 786.0053 | E33: =D33*B33 -> 8768.8716 | I33: Total price/Unit | J33: =J31+(J31*J32) -> 11.15625 | K33: =K31+(K31*K32) -> 11.15625 | L33: =L31+(L31*L32) -> 8.925 | M33: =M31+(M31*M32) -> 8.47875 | N33: =N31+(N31*N32) -> 6.3315 | O33: =AVERAGE(J33:M33) -> 9.9290625
A34: C2 | B34: =K33 -> 11.15625 | C34: =J41+J48+J55 -> 12000 | D34: =M41+M48+M55 -> 11096.545 | E34: =D34*B34 -> 123795.83
A35: C4 | B35: =L33 -> 8.925 | C35: =J38+J40+J45+J47+J52+J54 -> 5600 | D35: =M38+M40+M45+M47+M52+M54 -> 5178.3879 | E35: =D35*B35 -> 46217.112
A36: C5 | B36: =M33 -> 8.47875 | C36: =J37+J42+J44+J49+J51+J56 -> 3500 | D36: =M37+M42+M44+M49+M51+M56 -> 3236.4924 | E36: =D36*B36 -> 27441.41 | I36: GDAM
A37: Total | C37: =SUM(C33:C36) -> 21950 | D37: =SUM(D33:D36) -> 20297.431 | E37: =SUM(E33:E36) -> 206223.23 | H37: C5 | I37: =SUM('Energy Schedule'!AJ7:AJ26)/4 -> 0 | J37: =I37*1000 -> 0 | K37: =J37-(J37*$B$6) -> 0 | L37: =K37-(K37*$B$7) -> 0 | M37: =L37-(L37*$B$8) -> 0
H38: C4 | I38: =SUM('Energy Schedule'!AJ27:AJ30)/4 -> 0 | J38: =I38*1000 -> 0 | K38: =J38-(J38*$B$6) -> 0 | L38: =K38-(K38*$B$7) -> 0 | M38: =L38-(L38*$B$8) -> 0
H39: C1 | I39: =SUM('Energy Schedule'!AJ31:AJ46)/4 -> 0 | J39: =I39*1000 -> 0 | K39: =J39-(J39*$B$6) -> 0 | L39: =K39-(K39*$B$7) -> 0 | M39: =L39-(L39*$B$8) -> 0
H40: C4 | I40: =SUM('Energy Schedule'!AJ47:AJ78)/4 -> 0 | J40: =I40*1000 -> 0 | K40: =J40-(J40*$B$6) -> 0 | L40: =K40-(K40*$B$7) -> 0 | M40: =L40-(L40*$B$8) -> 0
H41: C2 | I41: =SUM('Energy Schedule'!AJ79:AJ94)/4 -> 0 | J41: =I41*1000 -> 0 | K41: =J41-(J41*$B$6) -> 0 | L41: =K41-(K41*$B$7) -> 0 | M41: =L41-(L41*$B$8) -> 0
A42: Total Purchase | B42: =C37 -> 21950 | C42: C1 | D42: 700 | H42: C5 | I42: =SUM('Energy Schedule'!AJ95:AJ102)/4 -> 0 | J42: =I42*1000 -> 0 | K42: =J42-(J42*$B$6) -> 0 | L42: =K42-(K42*$B$7) -> 0 | M42: =L42-(L42*$B$8) -> 0
A43: Delivered | B43: =D37 -> 20297.431 | C43: C2 | D43: 7850 | I43: DAM
A44: IEX Price | B44: =C27+D27+E27 -> 167305.32 | C44: C3 | D44: 2000 | H44: C5 | I44: =SUM('Energy Schedule'!AK7:AK26)/4 -> 2.5 | J44: =I44*1000 -> 2500 | K44: =J44-(J44*$B$6) -> 2414.25 | L44: =K44-(K44*$B$7) -> 2357.7566 | M44: =L44-(L44*$B$8) -> 2311.7803
A45: IEX Price / Unit | B45: =B44/B43 -> 8.2426844 | C45: C4 | D45: 20100 | H45: C4 | I45: =SUM('Energy Schedule'!AK27:AK30)/4 -> 0.5 | J45: =I45*1000 -> 500 | K45: =J45-(J45*$B$6) -> 482.85 | L45: =K45-(K45*$B$7) -> 471.55131 | M45: =L45-(L45*$B$8) -> 462.35606
A46: EB Price | B46: =E37 -> 206223.23 | C46: C5 | D46: 2950 | H46: C1 | I46: =SUM('Energy Schedule'!AK31:AK46)/4 -> 0.25 | J46: =I46*1000 -> 250 | K46: =J46-(J46*$B$6) -> 241.425 | L46: =K46-(K46*$B$7) -> 235.77566 | M46: =L46-(L46*$B$8) -> 231.17803
A47: EB Price / Unit | B47: =B46/B43 -> 10.160065 | C47: Total | D47: =SUM(D42:D46) -> 33600 | H47: C4 | I47: =SUM('Energy Schedule'!AK47:AK78)/4 -> 3.5 | J47: =I47*1000 -> 3500 | K47: =J47-(J47*$B$6) -> 3379.95 | L47: =K47-(K47*$B$7) -> 3300.8592 | M47: =L47-(L47*$B$8) -> 3236.4924
A48: Cost Saving | B48: =B46-B44 -> 38917.911 | H48: C2 | I48: =SUM('Energy Schedule'!AK79:AK94)/4 -> 9 | J48: =I48*1000 -> 9000 | K48: =J48-(J48*$B$6) -> 8691.3 | L48: =K48-(K48*$B$7) -> 8487.9236 | M48: =L48-(L48*$B$8) -> 8322.4091
A49: Cost Savings Unit | B49: =B47-B45 -> 1.9173811 | H49: C5 | I49: =SUM('Energy Schedule'!AK95:AK102)/4 -> 1 | J49: =I49*1000 -> 1000 | K49: =J49-(J49*$B$6) -> 965.7 | L49: =K49-(K49*$B$7) -> 943.10262 | M49: =L49-(L49*$B$8) -> 924.71212
I50: RTM
H51: C5 | I51: =SUM('Energy Schedule'!AL7:AL26)/4 -> 0 | J51: =I51*1000 -> 0 | K51: =J51-(J51*$B$6) -> 0 | L51: =K51-(K51*$B$7) -> 0 | M51: =L51-(L51*$B$8) -> 0
H52: C4 | I52: =SUM('Energy Schedule'!AL27:AL30)/4 -> 0 | J52: =I52*1000 -> 0 | K52: =J52-(J52*$B$6) -> 0 | L52: =K52-(K52*$B$7) -> 0 | M52: =L52-(L52*$B$8) -> 0
H53: C1 | I53: =SUM('Energy Schedule'!AL31:AL46)/4 -> 0.6 | J53: =I53*1000 -> 600 | K53: =J53-(J53*$B$6) -> 579.42 | L53: =K53-(K53*$B$7) -> 565.86157 | M53: =L53-(L53*$B$8) -> 554.82727
H54: C4 | I54: =SUM('Energy Schedule'!AL47:AL78)/4 -> 1.6 | J54: =I54*1000 -> 1600 | K54: =J54-(J54*$B$6) -> 1545.12 | L54: =K54-(K54*$B$7) -> 1508.9642 | M54: =L54-(L54*$B$8) -> 1479.5394
H55: C2 | I55: =SUM('Energy Schedule'!AL79:AL94)/4 -> 3 | J55: =I55*1000 -> 3000 | K55: =J55-(J55*$B$6) -> 2897.1 | L55: =K55-(K55*$B$7) -> 2829.3079 | M55: =L55-(L55*$B$8) -> 2774.1364
H56: C5 | I56: =SUM('Energy Schedule'!AL95:AL102)/4 -> 0 | J56: =I56*1000 -> 0 | K56: =J56-(J56*$B$6) -> 0 | L56: =K56-(K56*$B$7) -> 0 | M56: =L56-(L56*$B$8) -> 0

Sheet 13
C2: G-DAM | D2: DAM | E2: RTM
A3: Unit Purchased in MWh | C3: ='Energy Schedule'!AM$103 -> 0 | D3: ='Energy Schedule'!AN$103 -> 17.625 | E3: ='Energy Schedule'!AO$103 -> 2.15
A4: IEX Payout | C4: ='Energy Schedule'!AM$5 -> 0 | D4: ='Energy Schedule'!AN$5 -> 64149.079 | E4: ='Energy Schedule'!AO$5 -> 8811.53
A5: Total Units in kWh | C5: =C3*1000 -> 0 | D5: =D3*1000 -> 17625 | E5: =E3*1000 -> 2150 | I5: IEX Delivered | J5: Consumption | K5: Balance
A6: CTU | B6: ='Savings Sheet'!B5 -> 0.0343 | C6: =C5-(C5*$B$6) -> 0 | D6: =D5-(D5*$B$6) -> 17020.463 | E6: =E5-(E5*$B$6) -> 2076.255 | H6: C1 | I6: =D33 -> 508.59167 | J6: ='Consumption Details'!$B15 -> 1750 | K6: =J6-I6 -> 1241.4083
A7: STU | B7: ='TNEB Charges'!B1 -> 0.0234 | C7: =C6-(C6*$B$7) -> 0 | D7: =D6-(D6*$B$7) -> 16622.184 | E7: =E6-(E6*$B$7) -> 2027.6706 | H7: C2 | I7: =D34 -> 7513.286 | J7: ='Consumption Details'!$C15 -> 9150 | K7: =J7-I7 -> 1636.714
A8: Discom Losses | B8: ='TNEB Charges'!B2 -> 0.0195 | C8: =C7-(C7*$B$8) -> 0 | D8: =D7-(D7*$B$8) -> 16298.051 | E8: =E7-(E7*$B$8) -> 1988.1311 | H8: C4 | I8: =D35 -> 7027.8121 | J8: ='Consumption Details'!$D16 -> 17200 | K8: =J8-I8 -> 10172.188
A9: Delivered @ Bus | B9: ='TNEB Charges'!B3 -> 0 | C9: =C8 -> 0 | D9: =D8 -> 16298.051 | E9: =E8 -> 1988.1311 | H9: C5 | I9: =D36 -> 3236.4924 | J9: ='Consumption Details'!$E15 -> 3300 | K9: =J9-I9 -> 63.507584
A10: IEX Payout / Unit | B10: ='TNEB Charges'!B4 -> 0 | C10: =C4/C9 -> #DIV/0! | D10: =D4/D9 -> 3.9359969 | E10: =E4/E9 -> 4.432067
A11: IEX Transaction Charges | B11: ='TNEB Charges'!B5 -> 0.02 | C11: =(C3*1000*$B$11)+(C3*1000*$B$11*18%) -> 0 | D11: =(D3*1000*$B$11)+(D3*1000*$B$11*18%) -> 415.95 | E11: =(E3*1000*$B$11)+(E3*1000*$B$11*18%) -> 50.74
A12: NLDC Application fee | B12: ='TNEB Charges'!B6 -> 0 | C12: ='Energy Schedule'!AM$6 -> 0 | D12: ='Energy Schedule'!AN$6 -> 7.69 | E12: ='Energy Schedule'!AO$6 -> 12.56
A13: CTU Transmission Charges | B13: ='TNEB Charges'!B7 -> 457.6 | C13: =C3*$B$13 -> 0 | D13: =D3*$B$13 -> 8065.2 | E13: =E3*$B$13 -> 983.84
A14: NLDC Sched & Oprn Charges | B14: ='TNEB Charges'!B8 -> 1 | C14: =C3*$B$14 -> 0 | D14: =D3*$B$14 -> 17.625 | E14: =E3*$B$14 -> 2.15
A15: STU Transmission Charges | B15: ='TNEB Charges'!B9 -> 260 | C15: =C3*$B$15 -> 0 | D15: =D3*$B$15 -> 4582.5 | E15: =E3*$B$15 -> 559
A16: STU Scheduling | B16: ='TNEB Charges'!B10 -> 170 | C16: =IF(C3>0,$B$16,0) -> 0 | D16: =IF(D3>0,$B$16,0) -> 170 | E16: =IF(E3>0,$B$16,0) -> 170
A17: STU System Operating Charge | B17: ='TNEB Charges'!B11 -> 33.74 | C17: =C3*$B$17/24 -> 0 | D17: =D3*$B$17/24 -> 24.777812 | E17: =E3*$B$17/24 -> 3.0225417
A18: TPTCL Margin | B18: ='TNEB Charges'!B12 -> 0.02 | C18: =C3*$B$18*1000 -> 0 | D18: =D3*$B$18*1000 -> 352.5 | E18: =E3*$B$18*1000 -> 43
A19: CSS | B19: ='TNEB Charges'!B13 -> 1.99 | C19: =C9*$B$19 -> 0 | D19: =D9*$B$19 -> 32433.122 | E19: =E9*$B$19 -> 3956.3808
A20: ASC | B20: ='TNEB Charges'!B14 -> 0 | C20: =C9*$B$20 -> 0 | D20: =D9*$B$20 -> 0 | E20: =E9*$B$20 -> 0
A21: Wheeling Charges | B21: ='TNEB Charges'!B15 -> 1.04 | C21: =C8*$B$21 -> 0 | D21: =D8*$B$21 -> 16949.973 | E21: =E8*$B$21 -> 2067.6563
A22: E-Tax | B22: ='TNEB Charges'!B16 -> 0 | C22: =C9*$B$22 -> 0 | D22: =D9*$B$22 -> 0 | E22: =E9*$B$22 -> 0
A23: Solar RPO Charges | B23: ='TNEB Charges'!B17 -> 0.12 | C23: 0 | D23: =D9*$B$23*10.5% -> 205.35544 | E23: =E9*$B$23*10.5% -> 25.050451
A24: Non-Solar RPO Charges | B24: ='TNEB Charges'!B18 -> 0.12 | C24: 0 | D24: =D9*$B$24*10.5% -> 205.35544 | E24: =E9*$B$24*10.5% -> 25.050451
A25: Total Statutory Charges | C25: =SUM(C11:C24) -> 0 | D25: =SUM(D11:D24) -> 63430.049 | E25: =SUM(E11:E24) -> 7898.4505
C26: =C25/C9 -> #DIV/0! | D26: =D25/D9 -> 3.8918794 | E26: =E25/E9 -> 3.9728018
A27: Total Cost incurred in IEX Purchase | C27: =C4+C25 -> 0 | D27: =D4+D25 -> 127579.13 | E27: =E4+E25 -> 16709.981
A28: Cost per Unit incurred | C28: =C27/C9 -> #DIV/0! | D28: =D27/D9 -> 7.8278763 | E28: =E27/E9 -> 8.4048687
I29: Slot | J29: Morning peak | K29: Evening peak | L29: Normal hour | M29: Normal hour | N29: Night Hour | O29: RTC
A30: EQUIVALENT EB PRICE TO THE UNITS PURCHASED FROM IEX | J30: C1 | K30: C2 | L30: C4 | M30: C5 | N30: C24
A31: DAM | I31: TNEB Tariff | J31: =$L$31+($L$31*25%) -> 10.625 | K31: =$L$31+($L$31*25%) -> 10.625 | L31: 8.5 | M31: =$L$31-($L$31*5%) -> 8.075 | N31: 6.03 | O31: =AVERAGE(J31:M31) -> 9.45625
A32: Slot | B32: Price | C32: Purchase | D32: Delivered | E32: EB Cost | I32: E-Tax | J32: 0.05 | K32: 0.05 | L32: 0.05 | M32: 0.05 | N32: 0.05 | O32: 0.05
A33: C1 | B33: =J33 -> 11.15625 | C33: =J39+J46+J53 -> 550 | D33: =M39+M46+M53 -> 508.59167 | E33: =D33*B33 -> 5673.9758 | I33: Total price/Unit | J33: =J31+(J31*J32) -> 11.15625 | K33: =K31+(K31*K32) -> 11.15625 | L33: =L31+(L31*L32) -> 8.925 | M33: =M31+(M31*M32) -> 8.47875 | N33: =N31+(N31*N32) -> 6.3315 | O33: =AVERAGE(J33:M33) -> 9.9290625
A34: C2 | B34: =K33 -> 11.15625 | C34: =J41+J48+J55 -> 8125 | D34: =M41+M48+M55 -> 7513.286 | E34: =D34*B34 -> 83820.097
A35: C4 | B35: =L33 -> 8.925 | C35: =J38+J40+J45+J47+J52+J54 -> 7600 | D35: =M38+M40+M45+M47+M52+M54 -> 7027.8121 | E35: =D35*B35 -> 62723.223
A36: C5 | B36: =M33 -> 8.47875 | C36: =J37+J42+J44+J49+J51+J56 -> 3500 | D36: =M37+M42+M44+M49+M51+M56 -> 3236.4924 | E36: =D36*B36 -> 27441.41 | I36: GDAM
A37: Total | C37: =SUM(C33:C36) -> 19775 | D37: =SUM(D33:D36) -> 18286.182 | E37: =SUM(E33:E36) -> 179658.71 | H37: C5 | I37: =SUM('Energy Schedule'!AM7:AM26)/4 -> 0 | J37: =I37*1000 -> 0 | K37: =J37-(J37*$B$6) -> 0 | L37: =K37-(K37*$B$7) -> 0 | M37: =L37-(L37*$B$8) -> 0
H38: C4 | I38: =SUM('Energy Schedule'!AM27:AM30)/4 -> 0 | J38: =I38*1000 -> 0 | K38: =J38-(J38*$B$6) -> 0 | L38: =K38-(K38*$B$7) -> 0 | M38: =L38-(L38*$B$8) -> 0
H39: C1 | I39: =SUM('Energy Schedule'!AM31:AM46)/4 -> 0 | J39: =I39*1000 -> 0 | K39: =J39-(J39*$B$6) -> 0 | L39: =K39-(K39*$B$7) -> 0 | M39: =L39-(L39*$B$8) -> 0
H40: C4 | I40: =SUM('Energy Schedule'!AM47:AM78)/4 -> 0 | J40: =I40*1000 -> 0 | K40: =J40-(J40*$B$6) -> 0 | L40: =K40-(K40*$B$7) -> 0 | M40: =L40-(L40*$B$8) -> 0
H41: C2 | I41: =SUM('Energy Schedule'!AM79:AM94)/4 -> 0 | J41: =I41*1000 -> 0 | K41: =J41-(J41*$B$6) -> 0 | L41: =K41-(K41*$B$7) -> 0 | M41: =L41-(L41*$B$8) -> 0
A42: Total Purchase | B42: =C37 -> 19775 | C42: C1 | D42: 700 | H42: C5 | I42: =SUM('Energy Schedule'!AM95:AM102)/4 -> 0 | J42: =I42*1000 -> 0 | K42: =J42-(J42*$B$6) -> 0 | L42: =K42-(K42*$B$7) -> 0 | M42: =L42-(L42*$B$8) -> 0
A43: Delivered | B43: =D37 -> 18286.182 | C43: C2 | D43: 7850 | I43: DAM
A44: IEX Price | B44: =C27+D27+E27 -> 144289.11 | C44: C3 | D44: 2000 | H44: C5 | I44: =SUM('Energy Schedule'!AN7:AN26)/4 -> 2.5 | J44: =I44*1000 -> 2500 | K44: =J44-(J44*$B$6) -> 2414.25 | L44: =K44-(K44*$B$7) -> 2357.7566 | M44: =L44-(L44*$B$8) -> 2311.7803
A45: IEX Price / Unit | B45: =B44/B43 -> 7.8906087 | C45: C4 | D45: 20100 | H45: C4 | I45: =SUM('Energy Schedule'!AN27:AN30)/4 -> 0.5 | J45: =I45*1000 -> 500 | K45: =J45-(J45*$B$6) -> 482.85 | L45: =K45-(K45*$B$7) -> 471.55131 | M45: =L45-(L45*$B$8) -> 462.35606
A46: EB Price | B46: =E37 -> 179658.71 | C46: C5 | D46: 2950 | H46: C1 | I46: =SUM('Energy Schedule'!AN31:AN46)/4 -> 0.25 | J46: =I46*1000 -> 250 | K46: =J46-(J46*$B$6) -> 241.425 | L46: =K46-(K46*$B$7) -> 235.77566 | M46: =L46-(L46*$B$8) -> 231.17803
A47: EB Price / Unit | B47: =B46/B43 -> 9.8248341 | C47: Total | D47: =SUM(D42:D46) -> 33600 | H47: C4 | I47: =SUM('Energy Schedule'!AN47:AN78)/4 -> 6.5 | J47: =I47*1000 -> 6500 | K47: =J47-(J47*$B$6) -> 6277.05 | L47: =K47-(K47*$B$7) -> 6130.167 | M47: =L47-(L47*$B$8) -> 6010.6288
A48: Cost Saving | B48: =B46-B44 -> 35369.598 | H48: C2 | I48: =SUM('Energy Schedule'!AN79:AN94)/4 -> 6.875 | J48: =I48*1000 -> 6875 | K48: =J48-(J48*$B$6) -> 6639.1875 | L48: =K48-(K48*$B$7) -> 6483.8305 | M48: =L48-(L48*$B$8) -> 6357.3958
A49: Cost Savings Unit | B49: =B47-B45 -> 1.9342254 | H49: C5 | I49: =SUM('Energy Schedule'!AN95:AN102)/4 -> 1 | J49: =I49*1000 -> 1000 | K49: =J49-(J49*$B$6) -> 965.7 | L49: =K49-(K49*$B$7) -> 943.10262 | M49: =L49-(L49*$B$8) -> 924.71212
I50: RTM
H51: C5 | I51: =SUM('Energy Schedule'!AO7:AO26)/4 -> 0 | J51: =I51*1000 -> 0 | K51: =J51-(J51*$B$6) -> 0 | L51: =K51-(K51*$B$7) -> 0 | M51: =L51-(L51*$B$8) -> 0
H52: C4 | I52: =SUM('Energy Schedule'!AO27:AO30)/4 -> 0 | J52: =I52*1000 -> 0 | K52: =J52-(J52*$B$6) -> 0 | L52: =K52-(K52*$B$7) -> 0 | M52: =L52-(L52*$B$8) -> 0
H53: C1 | I53: =SUM('Energy Schedule'!AO31:AO46)/4 -> 0.3 | J53: =I53*1000 -> 300 | K53: =J53-(J53*$B$6) -> 289.71 | L53: =K53-(K53*$B$7) -> 282.93079 | M53: =L53-(L53*$B$8) -> 277.41364
H54: C4 | I54: =SUM('Energy Schedule'!AO47:AO78)/4 -> 0.6 | J54: =I54*1000 -> 600 | K54: =J54-(J54*$B$6) -> 579.42 | L54: =K54-(K54*$B$7) -> 565.86157 | M54: =L54-(L54*$B$8) -> 554.82727
H55: C2 | I55: =SUM('Energy Schedule'!AO79:AO94)/4 -> 1.25 | J55: =I55*1000 -> 1250 | K55: =J55-(J55*$B$6) -> 1207.125 | L55: =K55-(K55*$B$7) -> 1178.8783 | M55: =L55-(L55*$B$8) -> 1155.8901
H56: C5 | I56: =SUM('Energy Schedule'!AO95:AO102)/4 -> 0 | J56: =I56*1000 -> 0 | K56: =J56-(J56*$B$6) -> 0 | L56: =K56-(K56*$B$7) -> 0 | M56: =L56-(L56*$B$8) -> 0

Sheet 14
C2: G-DAM | D2: DAM | E2: RTM
A3: Unit Purchased in MWh | C3: ='Energy Schedule'!AP$103 -> 0 | D3: ='Energy Schedule'!AQ$103 -> 11.15 | E3: ='Energy Schedule'!AR$103 -> 6.475
A4: IEX Payout | C4: ='Energy Schedule'!AP$5 -> 0 | D4: ='Energy Schedule'!AQ$5 -> 43154.523 | E4: ='Energy Schedule'!AR$5 -> 24088.83
A5: Total Units in kWh | C5: =C3*1000 -> 0 | D5: =D3*1000 -> 11150 | E5: =E3*1000 -> 6475 | I5: IEX Delivered | J5: Consumption | K5: Balance
A6: CTU | B6: ='Savings Sheet'!B5 -> 0.0343 | C6: =C5-(C5*$B$6) -> 0 | D6: =D5-(D5*$B$6) -> 10767.555 | E6: =E5-(E5*$B$6) -> 6252.9075 | H6: C1 | I6: =D33 -> 577.94507 | J6: ='Consumption Details'!$B16 -> 2100 | K6: =J6-I6 -> 1522.0549
A7: STU | B7: ='TNEB Charges'!B1 -> 0.0234 | C7: =C6-(C6*$B$7) -> 0 | D7: =D6-(D6*$B$7) -> 10515.594 | E7: =E6-(E6*$B$7) -> 6106.5895 | H7: C2 | I7: =D34 -> 7282.1079 | J7: ='Consumption Details'!$C16 -> 9350 | K7: =J7-I7 -> 2067.8921
A8: Discom Losses | B8: ='TNEB Charges'!B2 -> 0.0195 | C8: =C7-(C7*$B$8) -> 0 | D8: =D7-(D7*$B$8) -> 10310.54 | E8: =E7-(E7*$B$8) -> 5987.511 | H8: C4 | I8: =D35 -> 5247.7413 | J8: ='Consumption Details'!$D17 -> 16150 | K8: =J8-I8 -> 10902.259
A9: Delivered @ Bus | B9: ='TNEB Charges'!B3 -> 0 | C9: =C8 -> 0 | D9: =D8 -> 10310.54 | E9: =E8 -> 5987.511 | H9: C5 | I9: =D36 -> 3190.2568 | J9: ='Consumption Details'!$E16 -> 3250 | K9: =J9-I9 -> 59.74319
A10: IEX Payout / Unit | B10: ='TNEB Charges'!B4 -> 0 | C10: =C4/C9 -> #DIV/0! | D10: =D4/D9 -> 4.1854765 | E10: =E4/E9 -> 4.0231793
A11: IEX Transaction Charges | B11: ='TNEB Charges'!B5 -> 0.02 | C11: =(C3*1000*$B$11)+(C3*1000*$B$11*18%) -> 0 | D11: =(D3*1000*$B$11)+(D3*1000*$B$11*18%) -> 263.14 | E11: =(E3*1000*$B$11)+(E3*1000*$B$11*18%) -> 152.81
A12: NLDC Application fee | B12: ='TNEB Charges'!B6 -> 0 | C12: ='Energy Schedule'!AP$6 -> 0 | D12: ='Energy Schedule'!AQ$6 -> 7.62 | E12: ='Energy Schedule'!AR$6 -> 12.92
A13: CTU Transmission Charges | B13: ='TNEB Charges'!B7 -> 457.6 | C13: =C3*$B$13 -> 0 | D13: =D3*$B$13 -> 5102.24 | E13: =E3*$B$13 -> 2962.96
A14: NLDC Sched & Oprn Charges | B14: ='TNEB Charges'!B8 -> 1 | C14: =C3*$B$14 -> 0 | D14: =D3*$B$14 -> 11.15 | E14: =E3*$B$14 -> 6.475
A15: STU Transmission Charges | B15: ='TNEB Charges'!B9 -> 260 | C15: =C3*$B$15 -> 0 | D15: =D3*$B$15 -> 2899 | E15: =E3*$B$15 -> 1683.5
A16: STU Scheduling | B16: ='TNEB Charges'!B10 -> 170 | C16: =IF(C3>0,$B$16,0) -> 0 | D16: =IF(D3>0,$B$16,0) -> 170 | E16: =IF(E3>0,$B$16,0) -> 170
A17: STU System Operating Charge | B17: ='TNEB Charges'!B11 -> 33.74 | C17: =C3*$B$17/24 -> 0 | D17: =D3*$B$17/24 -> 15.675042 | E17: =E3*$B$17/24 -> 9.1027708
A18: TPTCL Margin | B18: ='TNEB Charges'!B12 -> 0.02 | C18: =C3*$B$18*1000 -> 0 | D18: =D3*$B$18*1000 -> 223 | E18: =E3*$B$18*1000 -> 129.5
A19: CSS | B19: ='TNEB Charges'!B13 -> 1.99 | C19: =C9*$B$19 -> 0 | D19: =D9*$B$19 -> 20517.975 | E19: =E9*$B$19 -> 11915.147
A20: ASC | B20: ='TNEB Charges'!B14 -> 0 | C20: =C9*$B$20 -> 0 | D20: =D9*$B$20 -> 0 | E20: =E9*$B$20 -> 0
A21: Wheeling Charges | B21: ='TNEB Charges'!B15 -> 1.04 | C21: =C8*$B$21 -> 0 | D21: =D8*$B$21 -> 10722.962 | E21: =E8*$B$21 -> 6227.0114
A22: E-Tax | B22: ='TNEB Charges'!B16 -> 0 | C22: =C9*$B$22 -> 0 | D22: =D9*$B$22 -> 0 | E22: =E9*$B$22 -> 0
A23: Solar RPO Charges | B23: ='TNEB Charges'!B17 -> 0.12 | C23: 0 | D23: =D9*$B$23*10.5% -> 129.91281 | E23: =E9*$B$23*10.5% -> 75.442638
A24: Non-Solar RPO Charges | B24: ='TNEB Charges'!B18 -> 0.12 | C24: 0 | D24: =D9*$B$24*10.5% -> 129.91281 | E24: =E9*$B$24*10.5% -> 75.442638
A25: Total Statutory Charges | C25: =SUM(C11:C24) -> 0 | D25: =SUM(D11:D24) -> 40192.587 | E25: =SUM(E11:E24) -> 23420.311
C26: =C25/C9 -> #DIV/0! | D26: =D25/D9 -> 3.8982039 | E26: =E25/E9 -> 3.9115271
A27: Total Cost incurred in IEX Purchase | C27: =C4+C25 -> 0 | D27: =D4+D25 -> 83347.111 | E27: =E4+E25 -> 47509.141
A28: Cost per Unit incurred | C28: =C27/C9 -> #DIV/0! | D28: =D27/D9 -> 8.0836803 | E28: =E27/E9 -> 7.9347063
I29: Slot | J29: Morning peak | K29: Evening peak | L29: Normal hour | M29: Normal hour | N29: Night Hour | O29: RTC
A30: EQUIVALENT EB PRICE TO THE UNITS PURCHASED FROM IEX | J30: C1 | K30: C2 | L30: C4 | M30: C5 | N30: C24
A31: DAM | I31: TNEB Tariff | J31: =$L$31+($L$31*25%) -> 10.625 | K31: =$L$31+($L$31*25%) -> 10.625 | L31: 8.5 | M31: =$L$31-($L$31*5%) -> 8.075 | N31: 6.03 | O31: =AVERAGE(J31:M31) -> 9.45625
A32: Slot | B32: Price | C32: Purchase | D32: Delivered | E32: EB Cost | I32: E-Tax | J32: 0.05 | K32: 0.05 | L32: 0.05 | M32: 0.05 | N32: 0.05 | O32: 0.05
A33: C1 | B33: =J33 -> 11.15625 | C33: =J39+J46+J53 -> 625 | D33: =M39+M46+M53 -> 577.94507 | E33: =D33*B33 -> 6447.6997 | I33: Total price/Unit | J33: =J31+(J31*J32) -> 11.15625 | K33: =K31+(K31*K32) -> 11.15625 | L33: =L31+(L31*L32) -> 8.925 | M33: =M31+(M31*M32) -> 8.47875 | N33: =N31+(N31*N32) -> 6.3315 | O33: =AVERAGE(J33:M33) -> 9.9290625
A34: C2 | B34: =K33 -> 11.15625 | C34: =J41+J48+J55 -> 7875 | D34: =M41+M48+M55 -> 7282.1079 | E34: =D34*B34 -> 81241.017
A35: C4 | B35: =L33 -> 8.925 | C35: =J38+J40+J45+J47+J52+J54 -> 5675 | D35: =M38+M40+M45+M47+M52+M54 -> 5247.7413 | E35: =D35*B35 -> 46836.091
A36: C5 | B36: =M33 -> 8.47875 | C36: =J37+J42+J44+J49+J51+J56 -> 3450 | D36: =M37+M42+M44+M49+M51+M56 -> 3190.2568 | E36: =D36*B36 -> 27049.39 | I36: GDAM
A37: Total | C37: =SUM(C33:C36) -> 17625 | D37: =SUM(D33:D36) -> 16298.051 | E37: =SUM(E33:E36) -> 161574.2 | H37: C5 | I37: =SUM('Energy Schedule'!AP7:AP26)/4 -> 0 | J37: =I37*1000 -> 0 | K37: =J37-(J37*$B$6) -> 0 | L37: =K37-(K37*$B$7) -> 0 | M37: =L37-(L37*$B$8) -> 0
H38: C4 | I38: =SUM('Energy Schedule'!AP27:AP30)/4 -> 0 | J38: =I38*1000 -> 0 | K38: =J38-(J38*$B$6) -> 0 | L38: =K38-(K38*$B$7) -> 0 | M38: =L38-(L38*$B$8) -> 0
H39: C1 | I39: =SUM('Energy Schedule'!AP31:AP46)/4 -> 0 | J39: =I39*1000 -> 0 | K39: =J39-(J39*$B$6) -> 0 | L39: =K39-(K39*$B$7) -> 0 | M39: =L39-(L39*$B$8) -> 0
H40: C4 | I40: =SUM('Energy Schedule'!AP47:AP78)/4 -> 0 | J40: =I40*1000 -> 0 | K40: =J40-(J40*$B$6) -> 0 | L40: =K40-(K40*$B$7) -> 0 | M40: =L40-(L40*$B$8) -> 0
H41: C2 | I41: =SUM('Energy Schedule'!AP79:AP94)/4 -> 0 | J41: =I41*1000 -> 0 | K41: =J41-(J41*$B$6) -> 0 | L41: =K41-(K41*$B$7) -> 0 | M41: =L41-(L41*$B$8) -> 0
A42: Total Purchase | B42: =C37 -> 17625 | C42: C1 | D42: 700 | H42: C5 | I42: =SUM('Energy Schedule'!AP95:AP102)/4 -> 0 | J42: =I42*1000 -> 0 | K42: =J42-(J42*$B$6) -> 0 | L42: =K42-(K42*$B$7) -> 0 | M42: =L42-(L42*$B$8) -> 0
A43: Delivered | B43: =D37 -> 16298.051 | C43: C2 | D43: 7850 | I43: DAM
A44: IEX Price | B44: =C27+D27+E27 -> 130856.25 | C44: C3 | D44: 2000 | H44: C5 | I44: =SUM('Energy Schedule'!AQ7:AQ26)/4 -> 1.5 | J44: =I44*1000 -> 1500 | K44: =J44-(J44*$B$6) -> 1448.55 | L44: =K44-(K44*$B$7) -> 1414.6539 | M44: =L44-(L44*$B$8) -> 1387.0682
A45: IEX Price / Unit | B45: =B44/B43 -> 8.0289509 | C45: C4 | D45: 20100 | H45: C4 | I45: =SUM('Energy Schedule'!AQ27:AQ30)/4 -> 0.5 | J45: =I45*1000 -> 500 | K45: =J45-(J45*$B$6) -> 482.85 | L45: =K45-(K45*$B$7) -> 471.55131 | M45: =L45-(L45*$B$8) -> 462.35606
A46: EB Price | B46: =E37 -> 161574.2 | C46: C5 | D46: 2950 | H46: C1 | I46: =SUM('Energy Schedule'!AQ31:AQ46)/4 -> 0.25 | J46: =I46*1000 -> 250 | K46: =J46-(J46*$B$6) -> 241.425 | L46: =K46-(K46*$B$7) -> 235.77566 | M46: =L46-(L46*$B$8) -> 231.17803
A47: EB Price / Unit | B47: =B46/B43 -> 9.9137128 | C47: Total | D47: =SUM(D42:D46) -> 33600 | H47: C4 | I47: =SUM('Energy Schedule'!AQ47:AQ78)/4 -> 1.5 | J47: =I47*1000 -> 1500 | K47: =J47-(J47*$B$6) -> 1448.55 | L47: =K47-(K47*$B$7) -> 1414.6539 | M47: =L47-(L47*$B$8) -> 1387.0682
A48: Cost Saving | B48: =B46-B44 -> 30717.945 | H48: C2 | I48: =SUM('Energy Schedule'!AQ79:AQ94)/4 -> 6.875 | J48: =I48*1000 -> 6875 | K48: =J48-(J48*$B$6) -> 6639.1875 | L48: =K48-(K48*$B$7) -> 6483.8305 | M48: =L48-(L48*$B$8) -> 6357.3958
A49: Cost Savings Unit | B49: =B47-B45 -> 1.8847619 | H49: C5 | I49: =SUM('Energy Schedule'!AQ95:AQ102)/4 -> 0.525 | J49: =I49*1000 -> 525 | K49: =J49-(J49*$B$6) -> 506.9925 | L49: =K49-(K49*$B$7) -> 495.12888 | M49: =L49-(L49*$B$8) -> 485.47386
I50: RTM
H51: C5 | I51: =SUM('Energy Schedule'!AR7:AR26)/4 -> 1.425 | J51: =I51*1000 -> 1425 | K51: =J51-(J51*$B$6) -> 1376.1225 | L51: =K51-(K51*$B$7) -> 1343.9212 | M51: =L51-(L51*$B$8) -> 1317.7148
H52: C4 | I52: =SUM('Energy Schedule'!AR27:AR30)/4 -> 0.125 | J52: =I52*1000 -> 125 | K52: =J52-(J52*$B$6) -> 120.7125 | L52: =K52-(K52*$B$7) -> 117.88783 | M52: =L52-(L52*$B$8) -> 115.58901
H53: C1 | I53: =SUM('Energy Schedule'!AR31:AR46)/4 -> 0.375 | J53: =I53*1000 -> 375 | K53: =J53-(J53*$B$6) -> 362.1375 | L53: =K53-(K53*$B$7) -> 353.66348 | M53: =L53-(L53*$B$8) -> 346.76704
H54: C4 | I54: =SUM('Energy Schedule'!AR47:AR78)/4 -> 3.55 | J54: =I54*1000 -> 3550 | K54: =J54-(J54*$B$6) -> 3428.235 | L54: =K54-(K54*$B$7) -> 3348.0143 | M54: =L54-(L54*$B$8) -> 3282.728
H55: C2 | I55: =SUM('Energy Schedule'!AR79:AR94)/4 -> 1 | J55: =I55*1000 -> 1000 | K55: =J55-(J55*$B$6) -> 965.7 | L55: =K55-(K55*$B$7) -> 943.10262 | M55: =L55-(L55*$B$8) -> 924.71212
H56: C5 | I56: =SUM('Energy Schedule'!AR95:AR102)/4 -> 0 | J56: =I56*1000 -> 0 | K56: =J56-(J56*$B$6) -> 0 | L56: =K56-(K56*$B$7) -> 0 | M56: =L56-(L56*$B$8) -> 0

Sheet 15
C2: G-DAM | D2: DAM | E2: RTM
A3: Unit Purchased in MWh | C3: ='Energy Schedule'!AS$103 -> 0 | D3: ='Energy Schedule'!AT$103 -> 12.325 | E3: ='Energy Schedule'!AU$103 -> 3.1575
A4: IEX Payout | C4: ='Energy Schedule'!AS$5 -> 0 | D4: ='Energy Schedule'!AT$5 -> 49631.555 | E4: ='Energy Schedule'!AU$5 -> 12125.1
A5: Total Units in kWh | C5: =C3*1000 -> 0 | D5: =D3*1000 -> 12325 | E5: =E3*1000 -> 3157.5 | I5: IEX Delivered | J5: Consumption | K5: Balance
A6: CTU | B6: ='Savings Sheet'!B5 -> 0.0343 | C6: =C5-(C5*$B$6) -> 0 | D6: =D5-(D5*$B$6) -> 11902.253 | E6: =E5-(E5*$B$6) -> 3049.1977 | H6: C1 | I6: =D33 -> 115.58901 | J6: ='Consumption Details'!$B17 -> 1750 | K6: =J6-I6 -> 1634.411
A7: STU | B7: ='TNEB Charges'!B1 -> 0.0234 | C7: =C6-(C6*$B$7) -> 0 | D7: =D6-(D6*$B$7) -> 11623.74 | E7: =E6-(E6*$B$7) -> 2977.8465 | H7: C2 | I7: =D34 -> 6387.449 | J7: ='Consumption Details'!$C17 -> 9200 | K7: =J7-I7 -> 2812.551
A8: Discom Losses | B8: ='TNEB Charges'!B2 -> 0.0195 | C8: =C7-(C7*$B$8) -> 0 | D8: =D7-(D7*$B$8) -> 11397.077 | E8: =E7-(E7*$B$8) -> 2919.7785 | H8: C4 | I8: =D35 -> 5409.5659 | J8: ='Consumption Details'!D17 -> 16150 | K8: =J8-I8 -> 10740.434
A9: Delivered @ Bus | B9: ='TNEB Charges'!B3 -> 0 | C9: =C8 -> 0 | D9: =D8 -> 11397.077 | E9: =E8 -> 2919.7785 | H9: C5 | I9: =D36 -> 2404.2515 | J9: ='Consumption Details'!$E17 -> 3550 | K9: =J9-I9 -> 1145.7485
A10: IEX Payout / Unit | B10: ='TNEB Charges'!B4 -> 0 | C10: =C4/C9 -> #DIV/0! | D10: =D4/D9 -> 4.3547618 | E10: =E4/E9 -> 4.1527465
A11: IEX Transaction Charges | B11: ='TNEB Charges'!B5 -> 0.02 | C11: =(C3*1000*$B$11)+(C3*1000*$B$11*18%) -> 0 | D11: =(D3*1000*$B$11)+(D3*1000*$B$11*18%) -> 290.87 | E11: =(E3*1000*$B$11)+(E3*1000*$B$11*18%) -> 74.517
A12: NLDC Application fee | B12: ='TNEB Charges'!B6 -> 0 | C12: ='Energy Schedule'!AS$6 -> 0 | D12: ='Energy Schedule'!AT$6 -> 8.04 | E12: ='Energy Schedule'!AU$6 -> 15.43
A13: CTU Transmission Charges | B13: ='TNEB Charges'!B7 -> 457.6 | C13: =C3*$B$13 -> 0 | D13: =D3*$B$13 -> 5639.92 | E13: =E3*$B$13 -> 1444.872
A14: NLDC Sched & Oprn Charges | B14: ='TNEB Charges'!B8 -> 1 | C14: =C3*$B$14 -> 0 | D14: =D3*$B$14 -> 12.325 | E14: =E3*$B$14 -> 3.1575
A15: STU Transmission Charges | B15: ='TNEB Charges'!B9 -> 260 | C15: =C3*$B$15 -> 0 | D15: =D3*$B$15 -> 3204.5 | E15: =E3*$B$15 -> 820.95
A16: STU Scheduling | B16: ='TNEB Charges'!B10 -> 170 | C16: =IF(C3>0,$B$16,0) -> 0 | D16: =IF(D3>0,$B$16,0) -> 170 | E16: =IF(E3>0,$B$16,0) -> 170
A17: STU System Operating Charge | B17: ='TNEB Charges'!B11 -> 33.74 | C17: =C3*$B$17/24 -> 0 | D17: =D3*$B$17/24 -> 17.326896 | E17: =E3*$B$17/24 -> 4.4389188
A18: TPTCL Margin | B18: ='TNEB Charges'!B12 -> 0.02 | C18: =C3*$B$18*1000 -> 0 | D18: =D3*$B$18*1000 -> 246.5 | E18: =E3*$B$18*1000 -> 63.15
A19: CSS | B19: ='TNEB Charges'!B13 -> 1.99 | C19: =C9*$B$19 -> 0 | D19: =D9*$B$19 -> 22680.183 | E19: =E9*$B$19 -> 5810.3592
A20: ASC | B20: ='TNEB Charges'!B14 -> 0 | C20: =C9*$B$20 -> 0 | D20: =D9*$B$20 -> 0 | E20: =E9*$B$20 -> 0
A21: Wheeling Charges | B21: ='TNEB Charges'!B15 -> 1.04 | C21: =C8*$B$21 -> 0 | D21: =D8*$B$21 -> 11852.96 | E21: =E8*$B$21 -> 3036.5697
A22: E-Tax | B22: ='TNEB Charges'!B16 -> 0 | C22: =C9*$B$22 -> 0 | D22: =D9*$B$22 -> 0 | E22: =E9*$B$22 -> 0
A23: Solar RPO Charges | B23: ='TNEB Charges'!B17 -> 0.12 | C23: 0 | D23: =D9*$B$23*10.5% -> 143.60317 | E23: =E9*$B$23*10.5% -> 36.789209
A24: Non-Solar RPO Charges | B24: ='TNEB Charges'!B18 -> 0.12 | C24: 0 | D24: =D9*$B$24*10.5% -> 143.60317 | E24: =E9*$B$24*10.5% -> 36.789209
A25: Total Statutory Charges | C25: =SUM(C11:C24) -> 0 | D25: =SUM(D11:D24) -> 44409.831 | E25: =SUM(E11:E24) -> 11517.023
C26: =C25/C9 -> #DIV/0! | D26: =D25/D9 -> 3.8965984 | E26: =E25/E9 -> 3.9444851
A27: Total Cost incurred in IEX Purchase | C27: =C4+C25 -> 0 | D27: =D4+D25 -> 94041.386 | E27: =E4+E25 -> 23642.123
A28: Cost per Unit incurred | C28: =C27/C9 -> #DIV/0! | D28: =D27/D9 -> 8.2513601 | E28: =E27/E9 -> 8.0972316
I29: Slot | J29: Morning peak | K29: Evening peak | L29: Normal hour | M29: Normal hour | N29: Night Hour | O29: RTC
A30: EQUIVALENT EB PRICE TO THE UNITS PURCHASED FROM IEX | J30: C1 | K30: C2 | L30: C4 | M30: C5 | N30: C24
A31: DAM | I31: TNEB Tariff | J31: =$L$31+($L$31*25%) -> 10.625 | K31: =$L$31+($L$31*25%) -> 10.625 | L31: 8.5 | M31: =$L$31-($L$31*5%) -> 8.075 | N31: 6.03 | O31: =AVERAGE(J31:M31) -> 9.45625
A32: Slot | B32: Price | C32: Purchase | D32: Delivered | E32: EB Cost | I32: E-Tax | J32: 0.05 | K32: 0.05 | L32: 0.05 | M32: 0.05 | N32: 0.05 | O32: 0.05
A33: C1 | B33: =J33 -> 11.15625 | C33: =J39+J46+J53 -> 125 | D33: =M39+M46+M53 -> 115.58901 | E33: =D33*B33 -> 1289.5399 | I33: Total price/Unit | J33: =J31+(J31*J32) -> 11.15625 | K33: =K31+(K31*K32) -> 11.15625 | L33: =L31+(L31*L32) -> 8.925 | M33: =M31+(M31*M32) -> 8.47875 | N33: =N31+(N31*N32) -> 6.3315 | O33: =AVERAGE(J33:M33) -> 9.9290625
A34: C2 | B34: =K33 -> 11.15625 | C34: =J41+J48+J55 -> 6907.5 | D34: =M41+M48+M55 -> 6387.449 | E34: =D34*B34 -> 71259.977
A35: C4 | B35: =L33 -> 8.925 | C35: =J38+J40+J45+J47+J52+J54 -> 5850 | D35: =M38+M40+M45+M47+M52+M54 -> 5409.5659 | E35: =D35*B35 -> 48280.376
A36: C5 | B36: =M33 -> 8.47875 | C36: =J37+J42+J44+J49+J51+J56 -> 2600 | D36: =M37+M42+M44+M49+M51+M56 -> 2404.2515 | E36: =D36*B36 -> 20385.047 | I36: GDAM
A37: Total | C37: =SUM(C33:C36) -> 15482.5 | D37: =SUM(D33:D36) -> 14316.855 | E37: =SUM(E33:E36) -> 141214.94 | H37: C5 | I37: =SUM('Energy Schedule'!AS7:AS26)/4 -> 0 | J37: =I37*1000 -> 0 | K37: =J37-(J37*$B$6) -> 0 | L37: =K37-(K37*$B$7) -> 0 | M37: =L37-(L37*$B$8) -> 0
H38: C4 | I38: =SUM('Energy Schedule'!AS27:AS30)/4 -> 0 | J38: =I38*1000 -> 0 | K38: =J38-(J38*$B$6) -> 0 | L38: =K38-(K38*$B$7) -> 0 | M38: =L38-(L38*$B$8) -> 0
H39: C1 | I39: =SUM('Energy Schedule'!AS31:AS46)/4 -> 0 | J39: =I39*1000 -> 0 | K39: =J39-(J39*$B$6) -> 0 | L39: =K39-(K39*$B$7) -> 0 | M39: =L39-(L39*$B$8) -> 0
H40: C4 | I40: =SUM('Energy Schedule'!AS47:AS78)/4 -> 0 | J40: =I40*1000 -> 0 | K40: =J40-(J40*$B$6) -> 0 | L40: =K40-(K40*$B$7) -> 0 | M40: =L40-(L40*$B$8) -> 0
H41: C2 | I41: =SUM('Energy Schedule'!AS79:AS94)/4 -> 0 | J41: =I41*1000 -> 0 | K41: =J41-(J41*$B$6) -> 0 | L41: =K41-(K41*$B$7) -> 0 | M41: =L41-(L41*$B$8) -> 0
A42: Total Purchase | B42: =C37 -> 15482.5 | C42: C1 | D42: 700 | H42: C5 | I42: =SUM('Energy Schedule'!AS95:AS102)/4 -> 0 | J42: =I42*1000 -> 0 | K42: =J42-(J42*$B$6) -> 0 | L42: =K42-(K42*$B$7) -> 0 | M42: =L42-(L42*$B$8) -> 0
A43: Delivered | B43: =D37 -> 14316.855 | C43: C2 | D43: 7850 | I43: DAM
A44: IEX Price | B44: =C27+D27+E27 -> 117683.51 | C44: C3 | D44: 2000 | H44: C5 | I44: =SUM('Energy Schedule'!AT7:AT26)/4 -> 1.5 | J44: =I44*1000 -> 1500 | K44: =J44-(J44*$B$6) -> 1448.55 | L44: =K44-(K44*$B$7) -> 1414.6539 | M44: =L44-(L44*$B$8) -> 1387.0682
A45: IEX Price / Unit | B45: =B44/B43 -> 8.2199272 | C45: C4 | D45: 20100 | H45: C4 | I45: =SUM('Energy Schedule'!AT27:AT30)/4 -> 0.5 | J45: =I45*1000 -> 500 | K45: =J45-(J45*$B$6) -> 482.85 | L45: =K45-(K45*$B$7) -> 471.55131 | M45: =L45-(L45*$B$8) -> 462.35606
A46: EB Price | B46: =E37 -> 141214.94 | C46: C5 | D46: 2950 | H46: C1 | I46: =SUM('Energy Schedule'!AT31:AT46)/4 -> 0.125 | J46: =I46*1000 -> 125 | K46: =J46-(J46*$B$6) -> 120.7125 | L46: =K46-(K46*$B$7) -> 117.88783 | M46: =L46-(L46*$B$8) -> 115.58901
A47: EB Price / Unit | B47: =B46/B43 -> 9.8635445 | C47: Total | D47: =SUM(D42:D46) -> 33600 | H47: C4 | I47: =SUM('Energy Schedule'!AT47:AT78)/4 -> 3.5 | J47: =I47*1000 -> 3500 | K47: =J47-(J47*$B$6) -> 3379.95 | L47: =K47-(K47*$B$7) -> 3300.8592 | M47: =L47-(L47*$B$8) -> 3236.4924
A48: Cost Saving | B48: =B46-B44 -> 23531.432 | H48: C2 | I48: =SUM('Energy Schedule'!AT79:AT94)/4 -> 6.25 | J48: =I48*1000 -> 6250 | K48: =J48-(J48*$B$6) -> 6035.625 | L48: =K48-(K48*$B$7) -> 5894.3914 | M48: =L48-(L48*$B$8) -> 5779.4507
A49: Cost Savings Unit | B49: =B47-B45 -> 1.6436174 | H49: C5 | I49: =SUM('Energy Schedule'!AT95:AT102)/4 -> 0.45 | J49: =I49*1000 -> 450 | K49: =J49-(J49*$B$6) -> 434.565 | L49: =K49-(K49*$B$7) -> 424.39618 | M49: =L49-(L49*$B$8) -> 416.12045
I50: RTM
H51: C5 | I51: =SUM('Energy Schedule'!AU7:AU26)/4 -> 0.65 | J51: =I51*1000 -> 650 | K51: =J51-(J51*$B$6) -> 627.705 | L51: =K51-(K51*$B$7) -> 613.0167 | M51: =L51-(L51*$B$8) -> 601.06288
H52: C4 | I52: =SUM('Energy Schedule'!AU27:AU30)/4 -> 0.15 | J52: =I52*1000 -> 150 | K52: =J52-(J52*$B$6) -> 144.855 | L52: =K52-(K52*$B$7) -> 141.46539 | M52: =L52-(L52*$B$8) -> 138.70682
H53: C1 | I53: =SUM('Energy Schedule'!AU31:AU46)/4 -> 0 | J53: =I53*1000 -> 0 | K53: =J53-(J53*$B$6) -> 0 | L53: =K53-(K53*$B$7) -> 0 | M53: =L53-(L53*$B$8) -> 0
H54: C4 | I54: =SUM('Energy Schedule'!AU47:AU78)/4 -> 1.7 | J54: =I54*1000 -> 1700 | K54: =J54-(J54*$B$6) -> 1641.69 | L54: =K54-(K54*$B$7) -> 1603.2745 | M54: =L54-(L54*$B$8) -> 1572.0106
H55: C2 | I55: =SUM('Energy Schedule'!AU79:AU94)/4 -> 0.6575 | J55: =I55*1000 -> 657.5 | K55: =J55-(J55*$B$6) -> 634.94775 | L55: =K55-(K55*$B$7) -> 620.08997 | M55: =L55-(L55*$B$8) -> 607.99822
H56: C5 | I56: =SUM('Energy Schedule'!AU95:AU102)/4 -> 0 | J56: =I56*1000 -> 0 | K56: =J56-(J56*$B$6) -> 0 | L56: =K56-(K56*$B$7) -> 0 | M56: =L56-(L56*$B$8) -> 0

Sheet 16
C2: G-DAM | D2: DAM | E2: RTM
A3: Unit Purchased in MWh | C3: ='Energy Schedule'!AV$103 -> 0 | D3: ='Energy Schedule'!AW$103 -> 6.925 | E3: ='Energy Schedule'!AX$103 -> 1.025
A4: IEX Payout | C4: ='Energy Schedule'!AV$5 -> 0 | D4: ='Energy Schedule'!AW$5 -> 28682.671 | E4: ='Energy Schedule'!AX$5 -> 4361.8
A5: Total Units in kWh | C5: =C3*1000 -> 0 | D5: =D3*1000 -> 6925 | E5: =E3*1000 -> 1025 | I5: IEX Delivered | J5: Consumption | K5: Balance
A6: CTU | B6: ='Savings Sheet'!B5 -> 0.0343 | C6: =C5-(C5*$B$6) -> 0 | D6: =D5-(D5*$B$6) -> 6687.4725 | E6: =E5-(E5*$B$6) -> 989.8425 | H6: C1 | I6: =D33 -> 0 | J6: ='Consumption Details'!$B18 -> 1750 | K6: =J6-I6 -> 1750
A7: STU | B7: ='TNEB Charges'!B1 -> 0.0234 | C7: =C6-(C6*$B$7) -> 0 | D7: =D6-(D6*$B$7) -> 6530.9856 | E7: =E6-(E6*$B$7) -> 966.68019 | H7: C2 | I7: =D34 -> 3930.0265 | J7: ='Consumption Details'!$C18 -> 9500 | K7: =J7-I7 -> 5569.9735
A8: Discom Losses | B8: ='TNEB Charges'!B2 -> 0.0195 | C8: =C7-(C7*$B$8) -> 0 | D8: =D7-(D7*$B$8) -> 6403.6314 | E8: =E7-(E7*$B$8) -> 947.82992 | H8: C4 | I8: =D35 -> 1410.186 | J8: ='Consumption Details'!$D18 -> 17200 | K8: =J8-I8 -> 15789.814
A9: Delivered @ Bus | B9: ='TNEB Charges'!B3 -> 0 | C9: =C8 -> 0 | D9: =D8 -> 6403.6314 | E9: =E8 -> 947.82992 | H9: C5 | I9: =D36 -> 2011.2489 | J9: ='Consumption Details'!$E18 -> 3900 | K9: =J9-I9 -> 1888.7511
A10: IEX Payout / Unit | B10: ='TNEB Charges'!B4 -> 0 | C10: =C4/C9 -> #DIV/0! | D10: =D4/D9 -> 4.4791258 | E10: =E4/E9 -> 4.6018805
A11: IEX Transaction Charges | B11: ='TNEB Charges'!B5 -> 0.02 | C11: =(C3*1000*$B$11)+(C3*1000*$B$11*18%) -> 0 | D11: =(D3*1000*$B$11)+(D3*1000*$B$11*18%) -> 163.43 | E11: =(E3*1000*$B$11)+(E3*1000*$B$11*18%) -> 24.19
A12: NLDC Application fee | B12: ='TNEB Charges'!B6 -> 0 | C12: ='Energy Schedule'!AV$6 -> 0 | D12: ='Energy Schedule'!AW$6 -> 8.59 | E12: ='Energy Schedule'!AX$6 -> 24.39
A13: CTU Transmission Charges | B13: ='TNEB Charges'!B7 -> 457.6 | C13: =C3*$B$13 -> 0 | D13: =D3*$B$13 -> 3168.88 | E13: =E3*$B$13 -> 469.04
A14: NLDC Sched & Oprn Charges | B14: ='TNEB Charges'!B8 -> 1 | C14: =C3*$B$14 -> 0 | D14: =D3*$B$14 -> 6.925 | E14: =E3*$B$14 -> 1.025
A15: STU Transmission Charges | B15: ='TNEB Charges'!B9 -> 260 | C15: =C3*$B$15 -> 0 | D15: =D3*$B$15 -> 1800.5 | E15: =E3*$B$15 -> 266.5
A16: STU Scheduling | B16: ='TNEB Charges'!B10 -> 170 | C16: =IF(C3>0,$B$16,0) -> 0 | D16: =IF(D3>0,$B$16,0) -> 170 | E16: =IF(E3>0,$B$16,0) -> 170
A17: STU System Operating Charge | B17: ='TNEB Charges'!B11 -> 33.74 | C17: =C3*$B$17/24 -> 0 | D17: =D3*$B$17/24 -> 9.7353958 | E17: =E3*$B$17/24 -> 1.4409792
A18: TPTCL Margin | B18: ='TNEB Charges'!B12 -> 0.02 | C18: =C3*$B$18*1000 -> 0 | D18: =D3*$B$18*1000 -> 138.5 | E18: =E3*$B$18*1000 -> 20.5
A19: CSS | B19: ='TNEB Charges'!B13 -> 1.99 | C19: =C9*$B$19 -> 0 | D19: =D9*$B$19 -> 12743.227 | E19: =E9*$B$19 -> 1886.1815
A20: ASC | B20: ='TNEB Charges'!B14 -> 0 | C20: =C9*$B$20 -> 0 | D20: =D9*$B$20 -> 0 | E20: =E9*$B$20 -> 0
A21: Wheeling Charges | B21: ='TNEB Charges'!B15 -> 1.04 | C21: =C8*$B$21 -> 0 | D21: =D8*$B$21 -> 6659.7767 | E21: =E8*$B$21 -> 985.74312
A22: E-Tax | B22: ='TNEB Charges'!B16 -> 0 | C22: =C9*$B$22 -> 0 | D22: =D9*$B$22 -> 0 | E22: =E9*$B$22 -> 0
A23: Solar RPO Charges | B23: ='TNEB Charges'!B17 -> 0.12 | C23: 0 | D23: =D9*$B$23*10.5% -> 80.685756 | E23: =E9*$B$23*10.5% -> 11.942657
A24: Non-Solar RPO Charges | B24: ='TNEB Charges'!B18 -> 0.12 | C24: 0 | D24: =D9*$B$24*10.5% -> 80.685756 | E24: =E9*$B$24*10.5% -> 11.942657
A25: Total Statutory Charges | C25: =SUM(C11:C24) -> 0 | D25: =SUM(D11:D24) -> 25030.935 | E25: =SUM(E11:E24) -> 3872.896
C26: =C25/C9 -> #DIV/0! | D26: =D25/D9 -> 3.9088657 | E26: =E25/E9 -> 4.0860664
A27: Total Cost incurred in IEX Purchase | C27: =C4+C25 -> 0 | D27: =D4+D25 -> 53713.606 | E27: =E4+E25 -> 8234.696
A28: Cost per Unit incurred | C28: =C27/C9 -> #DIV/0! | D28: =D27/D9 -> 8.3879915 | E28: =E27/E9 -> 8.6879468
I29: Slot | J29: Morning peak | K29: Evening peak | L29: Normal hour | M29: Normal hour | N29: Night Hour | O29: RTC
A30: EQUIVALENT EB PRICE TO THE UNITS PURCHASED FROM IEX | J30: C1 | K30: C2 | L30: C4 | M30: C5 | N30: C24
A31: DAM | I31: TNEB Tariff | J31: =$L$31+($L$31*25%) -> 10.625 | K31: =$L$31+($L$31*25%) -> 10.625 | L31: 8.5 | M31: =$L$31-($L$31*5%) -> 8.075 | N31: 6.03 | O31: =AVERAGE(J31:M31) -> 9.45625
A32: Slot | B32: Price | C32: Purchase | D32: Delivered | E32: EB Cost | I32: E-Tax | J32: 0.05 | K32: 0.05 | L32: 0.05 | M32: 0.05 | N32: 0.05 | O32: 0.05
A33: C1 | B33: =J33 -> 11.15625 | C33: =J39+J46+J53 -> 0 | D33: =M39+M46+M53 -> 0 | E33: =D33*B33 -> 0 | I33: Total price/Unit | J33: =J31+(J31*J32) -> 11.15625 | K33: =K31+(K31*K32) -> 11.15625 | L33: =L31+(L31*L32) -> 8.925 | M33: =M31+(M31*M32) -> 8.47875 | N33: =N31+(N31*N32) -> 6.3315 | O33: =AVERAGE(J33:M33) -> 9.9290625
A34: C2 | B34: =K33 -> 11.15625 | C34: =J41+J48+J55 -> 4250 | D34: =M41+M48+M55 -> 3930.0265 | E34: =D34*B34 -> 43844.358
A35: C4 | B35: =L33 -> 8.925 | C35: =J38+J40+J45+J47+J52+J54 -> 1525 | D35: =M38+M40+M45+M47+M52+M54 -> 1410.186 | E35: =D35*B35 -> 12585.91
A36: C5 | B36: =M33 -> 8.47875 | C36: =J37+J42+J44+J49+J51+J56 -> 2175 | D36: =M37+M42+M44+M49+M51+M56 -> 2011.2489 | E36: =D36*B36 -> 17052.876 | I36: GDAM
A37: Total | C37: =SUM(C33:C36) -> 7950 | D37: =SUM(D33:D36) -> 7351.4613 | E37: =SUM(E33:E36) -> 73483.144 | H37: C5 | I37: =SUM('Energy Schedule'!AV7:AV26)/4 -> 0 | J37: =I37*1000 -> 0 | K37: =J37-(J37*$B$6) -> 0 | L37: =K37-(K37*$B$7) -> 0 | M37: =L37-(L37*$B$8) -> 0
H38: C4 | I38: =SUM('Energy Schedule'!AV27:AV30)/4 -> 0 | J38: =I38*1000 -> 0 | K38: =J38-(J38*$B$6) -> 0 | L38: =K38-(K38*$B$7) -> 0 | M38: =L38-(L38*$B$8) -> 0
H39: C1 | I39: =SUM('Energy Schedule'!AV31:AV46)/4 -> 0 | J39: =I39*1000 -> 0 | K39: =J39-(J39*$B$6) -> 0 | L39: =K39-(K39*$B$7) -> 0 | M39: =L39-(L39*$B$8) -> 0
H40: C4 | I40: =SUM('Energy Schedule'!AV47:AV78)/4 -> 0 | J40: =I40*1000 -> 0 | K40: =J40-(J40*$B$6) -> 0 | L40: =K40-(K40*$B$7) -> 0 | M40: =L40-(L40*$B$8) -> 0
H41: C2 | I41: =SUM('Energy Schedule'!AV79:AV94)/4 -> 0 | J41: =I41*1000 -> 0 | K41: =J41-(J41*$B$6) -> 0 | L41: =K41-(K41*$B$7) -> 0 | M41: =L41-(L41*$B$8) -> 0
A42: Total Purchase | B42: =C37 -> 7950 | C42: C1 | D42: 700 | H42: C5 | I42: =SUM('Energy Schedule'!AV95:AV102)/4 -> 0 | J42: =I42*1000 -> 0 | K42: =J42-(J42*$B$6) -> 0 | L42: =K42-(K42*$B$7) -> 0 | M42: =L42-(L42*$B$8) -> 0
A43: Delivered | B43: =D37 -> 7351.4613 | C43: C2 | D43: 7850 | I43: DAM
A44: IEX Price | B44: =C27+D27+E27 -> 61948.302 | C44: C3 | D44: 2000 | H44: C5 | I44: =SUM('Energy Schedule'!AW7:AW26)/4 -> 1.5 | J44: =I44*1000 -> 1500 | K44: =J44-(J44*$B$6) -> 1448.55 | L44: =K44-(K44*$B$7) -> 1414.6539 | M44: =L44-(L44*$B$8) -> 1387.0682
A45: IEX Price / Unit | B45: =B44/B43 -> 8.426665 | C45: C4 | D45: 20100 | H45: C4 | I45: =SUM('Energy Schedule'!AW27:AW30)/4 -> 0.375 | J45: =I45*1000 -> 375 | K45: =J45-(J45*$B$6) -> 362.1375 | L45: =K45-(K45*$B$7) -> 353.66348 | M45: =L45-(L45*$B$8) -> 346.76704
A46: EB Price | B46: =E37 -> 73483.144 | C46: C5 | D46: 2950 | H46: C1 | I46: =SUM('Energy Schedule'!AW31:AW46)/4 -> 0 | J46: =I46*1000 -> 0 | K46: =J46-(J46*$B$6) -> 0 | L46: =K46-(K46*$B$7) -> 0 | M46: =L46-(L46*$B$8) -> 0
A47: EB Price / Unit | B47: =B46/B43 -> 9.9957193 | C47: Total | D47: =SUM(D42:D46) -> 33600 | H47: C4 | I47: =SUM('Energy Schedule'!AW47:AW78)/4 -> 1 | J47: =I47*1000 -> 1000 | K47: =J47-(J47*$B$6) -> 965.7 | L47: =K47-(K47*$B$7) -> 943.10262 | M47: =L47-(L47*$B$8) -> 924.71212
A48: Cost Saving | B48: =B46-B44 -> 11534.843 | H48: C2 | I48: =SUM('Energy Schedule'!AW79:AW94)/4 -> 3.75 | J48: =I48*1000 -> 3750 | K48: =J48-(J48*$B$6) -> 3621.375 | L48: =K48-(K48*$B$7) -> 3536.6348 | M48: =L48-(L48*$B$8) -> 3467.6704
A49: Cost Savings Unit | B49: =B47-B45 -> 1.5690544 | H49: C5 | I49: =SUM('Energy Schedule'!AW95:AW102)/4 -> 0.3 | J49: =I49*1000 -> 300 | K49: =J49-(J49*$B$6) -> 289.71 | L49: =K49-(K49*$B$7) -> 282.93079 | M49: =L49-(L49*$B$8) -> 277.41364
I50: RTM
H51: C5 | I51: =SUM('Energy Schedule'!AX7:AX26)/4 -> 0.375 | J51: =I51*1000 -> 375 | K51: =J51-(J51*$B$6) -> 362.1375 | L51: =K51-(K51*$B$7) -> 353.66348 | M51: =L51-(L51*$B$8) -> 346.76704
H52: C4 | I52: =SUM('Energy Schedule'!AX27:AX30)/4 -> 0 | J52: =I52*1000 -> 0 | K52: =J52-(J52*$B$6) -> 0 | L52: =K52-(K52*$B$7) -> 0 | M52: =L52-(L52*$B$8) -> 0
H53: C1 | I53: =SUM('Energy Schedule'!AX31:AX46)/4 -> 0 | J53: =I53*1000 -> 0 | K53: =J53-(J53*$B$6) -> 0 | L53: =K53-(K53*$B$7) -> 0 | M53: =L53-(L53*$B$8) -> 0
H54: C4 | I54: =SUM('Energy Schedule'!AX47:AX78)/4 -> 0.15 | J54: =I54*1000 -> 150 | K54: =J54-(J54*$B$6) -> 144.855 | L54: =K54-(K54*$B$7) -> 141.46539 | M54: =L54-(L54*$B$8) -> 138.70682
H55: C2 | I55: =SUM('Energy Schedule'!AX79:AX94)/4 -> 0.5 | J55: =I55*1000 -> 500 | K55: =J55-(J55*$B$6) -> 482.85 | L55: =K55-(K55*$B$7) -> 471.55131 | M55: =L55-(L55*$B$8) -> 462.35606
H56: C5 | I56: =SUM('Energy Schedule'!AX95:AX102)/4 -> 0 | J56: =I56*1000 -> 0 | K56: =J56-(J56*$B$6) -> 0 | L56: =K56-(K56*$B$7) -> 0 | M56: =L56-(L56*$B$8) -> 0

Sheet 17
C2: G-DAM | D2: DAM | E2: RTM
A3: Unit Purchased in MWh | C3: ='Energy Schedule'!AY$103 -> 0 | D3: ='Energy Schedule'!AZ$103 -> 6.9425 | E3: ='Energy Schedule'!BA$103 -> 3.15
A4: IEX Payout | C4: ='Energy Schedule'!AY$5 -> 0 | D4: ='Energy Schedule'!AZ$5 -> 29034.378 | E4: ='Energy Schedule'!BA$5 -> 11232.94
A5: Total Units in kWh | C5: =C3*1000 -> 0 | D5: =D3*1000 -> 6942.5 | E5: =E3*1000 -> 3150 | I5: IEX Delivered | J5: Consumption | K5: Balance
A6: CTU | B6: ='Savings Sheet'!B5 -> 0.0343 | C6: =C5-(C5*$B$6) -> 0 | D6: =D5-(D5*$B$6) -> 6704.3723 | E6: =E5-(E5*$B$6) -> 3041.955 | H6: C1 | I6: =D33 -> 0 | J6: ='Consumption Details'!$B19 -> 2500 | K6: =J6-I6 -> 2500
A7: STU | B7: ='TNEB Charges'!B1 -> 0.0234 | C7: =C6-(C6*$B$7) -> 0 | D7: =D6-(D6*$B$7) -> 6547.4899 | E7: =E6-(E6*$B$7) -> 2970.7733 | H7: C2 | I7: =D34 -> 4184.3223 | J7: ='Consumption Details'!$C19 -> 10000 | K7: =J7-I7 -> 5815.6777
A8: Discom Losses | B8: ='TNEB Charges'!B2 -> 0.0195 | C8: =C7-(C7*$B$8) -> 0 | D8: =D7-(D7*$B$8) -> 6419.8139 | E8: =E7-(E7*$B$8) -> 2912.8432 | H8: C4 | I8: =D35 -> 2998.379 | J8: ='Consumption Details'!$D19 -> 19650 | K8: =J8-I8 -> 16651.621
A9: Delivered @ Bus | B9: ='TNEB Charges'!B3 -> 0 | C9: =C8 -> 0 | D9: =D8 -> 6419.8139 | E9: =E8 -> 2912.8432 | H9: C5 | I9: =D36 -> 2149.9557 | J9: ='Consumption Details'!$E19 -> 4000 | K9: =J9-I9 -> 1850.0443
A10: IEX Payout / Unit | B10: ='TNEB Charges'!B4 -> 0 | C10: =C4/C9 -> #DIV/0! | D10: =D4/D9 -> 4.5226198 | E10: =E4/E9 -> 3.856349
A11: IEX Transaction Charges | B11: ='TNEB Charges'!B5 -> 0.02 | C11: =(C3*1000*$B$11)+(C3*1000*$B$11*18%) -> 0 | D11: =(D3*1000*$B$11)+(D3*1000*$B$11*18%) -> 163.843 | E11: =(E3*1000*$B$11)+(E3*1000*$B$11*18%) -> 74.34
A12: NLDC Application fee | B12: ='TNEB Charges'!B6 -> 0 | C12: ='Energy Schedule'!AY$6 -> 0 | D12: ='Energy Schedule'!AZ$6 -> 8.5 | E12: ='Energy Schedule'!BA$6 -> 18.66
A13: CTU Transmission Charges | B13: ='TNEB Charges'!B7 -> 457.6 | C13: =C3*$B$13 -> 0 | D13: =D3*$B$13 -> 3176.888 | E13: =E3*$B$13 -> 1441.44
A14: NLDC Sched & Oprn Charges | B14: ='TNEB Charges'!B8 -> 1 | C14: =C3*$B$14 -> 0 | D14: =D3*$B$14 -> 6.9425 | E14: =E3*$B$14 -> 3.15
A15: STU Transmission Charges | B15: ='TNEB Charges'!B9 -> 260 | C15: =C3*$B$15 -> 0 | D15: =D3*$B$15 -> 1805.05 | E15: =E3*$B$15 -> 819
A16: STU Scheduling | B16: ='TNEB Charges'!B10 -> 170 | C16: =IF(C3>0,$B$16,0) -> 0 | D16: =IF(D3>0,$B$16,0) -> 170 | E16: =IF(E3>0,$B$16,0) -> 170
A17: STU System Operating Charge | B17: ='TNEB Charges'!B11 -> 33.74 | C17: =C3*$B$17/24 -> 0 | D17: =D3*$B$17/24 -> 9.7599979 | E17: =E3*$B$17/24 -> 4.428375
A18: TPTCL Margin | B18: ='TNEB Charges'!B12 -> 0.02 | C18: =C3*$B$18*1000 -> 0 | D18: =D3*$B$18*1000 -> 138.85 | E18: =E3*$B$18*1000 -> 63
A19: CSS | B19: ='TNEB Charges'!B13 -> 1.99 | C19: =C9*$B$19 -> 0 | D19: =D9*$B$19 -> 12775.43 | E19: =E9*$B$19 -> 5796.5579
A20: ASC | B20: ='TNEB Charges'!B14 -> 0 | C20: =C9*$B$20 -> 0 | D20: =D9*$B$20 -> 0 | E20: =E9*$B$20 -> 0
A21: Wheeling Charges | B21: ='TNEB Charges'!B15 -> 1.04 | C21: =C8*$B$21 -> 0 | D21: =D8*$B$21 -> 6676.6064 | E21: =E8*$B$21 -> 3029.3569
A22: E-Tax | B22: ='TNEB Charges'!B16 -> 0 | C22: =C9*$B$22 -> 0 | D22: =D9*$B$22 -> 0 | E22: =E9*$B$22 -> 0
A23: Solar RPO Charges | B23: ='TNEB Charges'!B17 -> 0.12 | C23: 0 | D23: =D9*$B$23*10.5% -> 80.889655 | E23: =E9*$B$23*10.5% -> 36.701824
